Workbook

Sheet Model Summary
AO1: created for stair plot
AO2: Used
AO3: year | AP3: MW | AQ3: Adjusted
Y4: Version 15, 2025-07-24 | AO4: 2024 | AP4: =HLOOKUP(AO4,$E$49:$X$50,2) -> 1.8045286 | AQ4: =HLOOKUP($AO4,$E$57:$X$58,2) -> 1.0101286
AO5: 2024.25 | AP5: =AP4 -> 1.8045286 | AQ5: =AQ4 -> 1.0101286
AO6: 2024.25 | AP6: =HLOOKUP(AO6,$E$49:$X$50,2) -> 1.8045286 | AQ6: =HLOOKUP($AO6,$E$57:$X$58,2) -> 1.0101286
AO7: 2024.5 | AP7: =AP6 -> 1.8045286 | AQ7: =AQ6 -> 1.0101286
AO8: 2024.5 | AP8: =HLOOKUP(AO8,$E$49:$X$50,2) -> 1.9559571 | AQ8: =HLOOKUP($AO8,$E$57:$X$58,2) -> 1.1615571
AO9: 2024.75 | AP9: =AP8 -> 1.9559571 | AQ9: =AQ8 -> 1.1615571
AO10: 2024.75 | AP10: =HLOOKUP(AO10,$E$49:$X$50,2) -> 2.2838429 | AQ10: =HLOOKUP($AO10,$E$57:$X$58,2) -> 1.4894429
AO11: 2025 | AP11: =AP10 -> 2.2838429 | AQ11: =AQ10 -> 1.4894429
AO12: 2025 | AP12: =HLOOKUP(AO12,$E$49:$X$50,2) -> 2.2838429 | AQ12: =HLOOKUP($AO12,$E$57:$X$58,2) -> 1.4894429
AO13: 2025.25 | AP13: =AP12 -> 2.2838429 | AQ13: =AQ12 -> 1.4894429
AO14: 2025.25 | AP14: =HLOOKUP(AO14,$E$49:$X$50,2) -> 2.2838429 | AQ14: =HLOOKUP($AO14,$E$57:$X$58,2) -> 1.4894429
AO15: 2025.5 | AP15: =AP14 -> 2.2838429 | AQ15: =AQ14 -> 1.4894429
AO16: 2025.5 | AP16: =HLOOKUP(AO16,$E$49:$X$50,2) -> 2.3484286 | AQ16: =HLOOKUP($AO16,$E$57:$X$58,2) -> 1.4894429
AO17: 2025.75 | AP17: =AP16 -> 2.3484286 | AQ17: =AQ16 -> 1.4894429
AO18: 2025.75 | AP18: =HLOOKUP(AO18,$E$49:$X$50,2) -> 2.5695714 | AQ18: =HLOOKUP($AO18,$E$57:$X$58,2) -> 1.7105857
AO19: 2026 | AP19: =AP18 -> 2.5695714 | AQ19: =AQ18 -> 1.7105857
AO20: 2026 | AP20: =HLOOKUP(AO20,$E$49:$X$50,2) -> 2.5695714 | AQ20: =HLOOKUP($AO20,$E$57:$X$58,2) -> 1.7105857
AO21: 2026.25 | AP21: =AP20 -> 2.5695714 | AQ21: =AQ20 -> 1.7105857
AO22: 2026.25 | AP22: =HLOOKUP(AO22,$E$49:$X$50,2) -> 2.5695714 | AQ22: =HLOOKUP($AO22,$E$57:$X$58,2) -> 1.7105857
AO23: 2026.5 | AP23: =AP22 -> 2.5695714 | AQ23: =AQ22 -> 1.7105857
AO24: 2026.5 | AP24: =HLOOKUP(AO24,$E$49:$X$50,2) -> 2.5695714 | AQ24: =HLOOKUP($AO24,$E$57:$X$58,2) -> 1.7105857
AO25: 2026.75 | AP25: =AP24 -> 2.5695714 | AQ25: =AQ24 -> 1.7105857
AO26: 2026.75 | AP26: =HLOOKUP(AO26,$E$49:$X$50,2) -> 2.5695714 | AQ26: =HLOOKUP($AO26,$E$57:$X$58,2) -> 1.7105857
AO27: 2027 | AP27: =AP26 -> 2.5695714 | AQ27: =AQ26 -> 1.7105857
AO28: 2027 | AP28: =HLOOKUP(AO28,$E$49:$X$50,2) -> 2.5695714 | AQ28: =HLOOKUP($AO28,$E$57:$X$58,2) -> 1.7105857
AO29: 2027.25 | AP29: =AP28 -> 2.5695714 | AQ29: =AQ28 -> 1.7105857
AO30: 2027.25 | AP30: =HLOOKUP(AO30,$E$49:$X$50,2) -> 1.3074429 | AQ30: =HLOOKUP($AO30,$E$57:$X$58,2) -> 0.94845714
AO31: 2027.5 | AP31: =AP30 -> 1.3074429 | AQ31: =AQ30 -> 0.94845714
AO32: 2027.5 | AP32: =HLOOKUP(AO32,$E$49:$X$50,2) -> 1.3074429 | AQ32: =HLOOKUP($AO32,$E$57:$X$58,2) -> 0.94845714
AO33: 2027.75 | AP33: =AP32 -> 1.3074429 | AQ33: =AQ32 -> 0.94845714
AO34: 2027.75 | AP34: =HLOOKUP(AO34,$E$49:$X$50,2) -> 1.3074429 | AQ34: =HLOOKUP($AO34,$E$57:$X$58,2) -> 0.94845714
AO35: 2028 | AP35: =AP34 -> 1.3074429 | AQ35: =AQ34 -> 0.94845714
AO36: 2028 | AP36: =HLOOKUP(AO36,$E$49:$X$50,2) -> 1.3074429 | AQ36: =HLOOKUP($AO36,$E$57:$X$58,2) -> 0.94845714
AO37: 2028.25 | AP37: =AP36 -> 1.3074429 | AQ37: =AQ36 -> 0.94845714
AO38: 2028.25 | AP38: =HLOOKUP(AO38,$E$49:$X$50,2) -> 1.3074429 | AQ38: =HLOOKUP($AO38,$E$57:$X$58,2) -> 0.94845714
AO39: 2028.5 | AP39: =AP38 -> 1.3074429 | AQ39: =AQ38 -> 0.94845714
AO40: 2028.5 | AP40: =HLOOKUP(AO40,$E$49:$X$50,2) -> 0.98344286 | AQ40: =HLOOKUP($AO40,$E$57:$X$58,2) -> 0.62445714
AO41: 2028.75 | AP41: =AP40 -> 0.98344286 | AQ41: =AQ40 -> 0.62445714
AO42: 2028.75 | AP42: =HLOOKUP(AO42,$E$49:$X$50,2) -> 0.98344286 | AQ42: =HLOOKUP($AO42,$E$57:$X$58,2) -> 0.62445714
C49: POWER USE [MW] | D49: year | E49: 2024 | F49: 2024.25 | G49: 2024.5 | H49: 2024.75 | I49: 2025 | J49: 2025.25 | K49: =J49+0.25 -> 2025.5 | L49: =K49+0.25 -> 2025.75 | M49: =L49+0.25 -> 2026 | N49: =M49+0.25 -> 2026.25 | O49: =N49+0.25 -> 2026.5 | P49: =O49+0.25 -> 2026.75 | Q49: =P49+0.25 -> 2027 | R49: =Q49+0.25 -> 2027.25 | ... X49: =W49+0.25 -> 2028.75
D50: Total | E50: =SUM(E51:E53) -> 1.8045286 | F50: =SUM(F51:F53) -> 1.8045286 | G50: =SUM(G51:G53) -> 1.9559571 | H50: =SUM(H51:H53) -> 2.2838429 | I50: =SUM(I51:I53) -> 2.2838429 | J50: =SUM(J51:J53) -> 2.2838429 | K50: =SUM(K51:K53) -> 2.3484286 | L50: =SUM(L51:L53) -> 2.5695714 | ... X50: =SUM(X51:X53) -> 0.98344286
D51: BayView | E51: =BayView!K48 -> 0.91212857 | F51: =BayView!L48 -> 0.91212857 | G51: =BayView!M48 -> 0.91212857 | H51: =BayView!N48 -> 1.2400143 | I51: =BayView!O48 -> 1.2400143 | J51: =BayView!P48 -> 1.2400143 | K51: =BayView!Q48 -> 1.2400143 | L51: =BayView!R48 -> 1.3754429 | ... X51: =BayView!AD48 -> 0.28931429
D52: Mt. Wash | E52: =Mt.Wash!K48 -> 0.598 | F52: =Mt.Wash!L48 -> 0.598 | G52: =Mt.Wash!M48 -> 0.74942857 | H52: =Mt.Wash!N48 -> 0.74942857 | I52: =Mt.Wash!O48 -> 0.74942857 | J52: =Mt.Wash!P48 -> 0.74942857 | K52: =Mt.Wash!Q48 -> 0.74942857 | L52: =Mt.Wash!R48 -> 0.83514286 | ... X52: =Mt.Wash!AD48 -> 0.33514286
D53: Bloomberg | E53: =Bloomberg!K48 -> 0.2944 | F53: =Bloomberg!L48 -> 0.2944 | G53: =Bloomberg!M48 -> 0.2944 | H53: =Bloomberg!N48 -> 0.2944 | I53: =Bloomberg!O48 -> 0.2944 | J53: =Bloomberg!P48 -> 0.2944 | K53: =Bloomberg!Q48 -> 0.35898571 | L53: =Bloomberg!R48 -> 0.35898571 | ... X53: =Bloomberg!AD48 -> 0.35898571
C54: This is the total amount of power consumed
C57: ADJUSTED POWER [MW] | D57: year | E57: 2024 | F57: 2024.25 | G57: 2024.5 | H57: 2024.75 | I57: 2025 | J57: 2025.25 | K57: =J57+0.25 -> 2025.5 | L57: =K57+0.25 -> 2025.75 | M57: =L57+0.25 -> 2026 | N57: =M57+0.25 -> 2026.25 | O57: =N57+0.25 -> 2026.5 | P57: =O57+0.25 -> 2026.75 | Q57: =P57+0.25 -> 2027 | R57: =Q57+0.25 -> 2027.25 | ... X57: =W57+0.25 -> 2028.75
D58: Total | E58: =SUM(E59:E61) -> 1.0101286 | F58: =SUM(F59:F61) -> 1.0101286 | G58: =SUM(G59:G61) -> 1.1615571 | H58: =SUM(H59:H61) -> 1.4894429 | I58: =SUM(I59:I61) -> 1.4894429 | J58: =SUM(J59:J61) -> 1.4894429 | K58: =SUM(K59:K61) -> 1.4894429 | L58: =SUM(L59:L61) -> 1.7105857 | ... X58: =SUM(X59:X61) -> 0.62445714
D59: BayView | E59: =BayView!K46 -> 0.91212857 | F59: =BayView!L46 -> 0.91212857 | G59: =BayView!M46 -> 0.91212857 | H59: =BayView!N46 -> 1.2400143 | I59: =BayView!O46 -> 1.2400143 | J59: =BayView!P46 -> 1.2400143 | K59: =BayView!Q46 -> 1.2400143 | L59: =BayView!R46 -> 1.3754429 | ... X59: =BayView!AD46 -> 0.28931429
D60: Mt. Wash | E60: =Mt.Wash!K46 -> 0.098 | F60: =Mt.Wash!L46 -> 0.098 | G60: =Mt.Wash!M46 -> 0.24942857 | H60: =Mt.Wash!N46 -> 0.24942857 | I60: =Mt.Wash!O46 -> 0.24942857 | J60: =Mt.Wash!P46 -> 0.24942857 | K60: =Mt.Wash!Q46 -> 0.24942857 | L60: =Mt.Wash!R46 -> 0.33514286 | ... X60: =Mt.Wash!AD46 -> 0.33514286
D61: Bloomberg | E61: =Bloomberg!K46 -> 0 | F61: =Bloomberg!L46 -> 0 | G61: =Bloomberg!M46 -> 0 | H61: =Bloomberg!N46 -> 0 | I61: =Bloomberg!O46 -> 0 | J61: =Bloomberg!P46 -> 0 | K61: =Bloomberg!Q46 -> 0 | L61: =Bloomberg!R46 -> 0 | ... X61: =Bloomberg!AD46 -> 0
C62: This is the amount that incurs utility charges
C65: ADJUSTED UTILITY COSTS [$k/qt] | D65: year | E65: 2024 | F65: 2024.25 | G65: 2024.5 | H65: 2024.75 | I65: 2025 | J65: 2025.25 | K65: =J65+0.25 -> 2025.5 | L65: =K65+0.25 -> 2025.75 | M65: =L65+0.25 -> 2026 | N65: =M65+0.25 -> 2026.25 | O65: =N65+0.25 -> 2026.5 | P65: =O65+0.25 -> 2026.75 | Q65: =P65+0.25 -> 2027 | R65: =Q65+0.25 -> 2027.25 | ... X65: =W65+0.25 -> 2028.75
D66: =D59 -> BayView | E66: =E59*'Power Blocks'!S12/4*('Power Blocks'!$S$7+1) -> 239.70739 | F66: =F59*'Power Blocks'!T12/4*('Power Blocks'!$S$7+1) -> 239.70739 | G66: =G59*'Power Blocks'!U12/4*('Power Blocks'!$S$7+1) -> 239.70739 | H66: =H59*'Power Blocks'!V12/4*('Power Blocks'!$S$7+1) -> 325.87575 | I66: =I59*'Power Blocks'!W12/4*('Power Blocks'!$S$7+1) -> 325.87575 | J66: =J59*'Power Blocks'!X12/4*('Power Blocks'!$S$7+1) -> 325.87575 | K66: =K59*'Power Blocks'!Y12/4*('Power Blocks'!$S$7+1) -> 358.46333 | L66: =L59*'Power Blocks'!Z12/4*('Power Blocks'!$S$7+1) -> 397.61302 | ... X66: =X59*'Power Blocks'!AL12/4*('Power Blocks'!$S$7+1) -> 111.31815
D67: =D60 -> Mt. Wash | E67: =E60*'Power Blocks'!S14/4*(1+'Power Blocks'!$S$7) -> 19.444572 | F67: =F60*'Power Blocks'!T14/4*(1+'Power Blocks'!$S$7) -> 19.444572 | G67: =G60*'Power Blocks'!U14/4*(1+'Power Blocks'!$S$7) -> 59.650344 | H67: =H60*'Power Blocks'!V14/4*(1+'Power Blocks'!$S$7) -> 59.650344 | I67: =I60*'Power Blocks'!W14/4*(1+'Power Blocks'!$S$7) -> 59.650344 | J67: =J60*'Power Blocks'!X14/4*(1+'Power Blocks'!$S$7) -> 59.650344 | K67: =K60*'Power Blocks'!Y14/4*(1+'Power Blocks'!$S$7) -> 59.650344 | L67: =L60*'Power Blocks'!Z14/4*(1+'Power Blocks'!$S$7) -> 80.148744 | ... X67: =X60*'Power Blocks'!AL14/4*(1+'Power Blocks'!$S$7) -> 96.97998
D68: =D61 -> Bloomberg | E68: =E61*'Power Blocks'!S14/4*(1+'Power Blocks'!$S$7) -> 0 | F68: =F61*'Power Blocks'!T14/4*(1+'Power Blocks'!$S$7) -> 0 | G68: =G61*'Power Blocks'!U14/4*(1+'Power Blocks'!$S$7) -> 0 | H68: =H61*'Power Blocks'!V14/4*(1+'Power Blocks'!$S$7) -> 0 | I68: =I61*'Power Blocks'!W14/4*(1+'Power Blocks'!$S$7) -> 0 | J68: =J61*'Power Blocks'!X14/4*(1+'Power Blocks'!$S$7) -> 0 | K68: =K61*'Power Blocks'!Y14/4*(1+'Power Blocks'!$S$7) -> 0 | L68: =L61*'Power Blocks'!Z14/4*(1+'Power Blocks'!$S$7) -> 0 | ... X68: =X61*'Power Blocks'!AL14/4*(1+'Power Blocks'!$S$7) -> 0
D69: total [$k] | E69: =SUM(E66:E68) -> 259.15196 | F69: =SUM(F66:F68) -> 259.15196 | G69: =SUM(G66:G68) -> 299.35773 | H69: =SUM(H66:H68) -> 385.5261 | I69: =SUM(I66:I68) -> 385.5261 | J69: =SUM(J66:J68) -> 385.5261 | K69: =SUM(K66:K68) -> 418.11367 | L69: =SUM(L66:L68) -> 477.76177 | ... X69: =SUM(X66:X68) -> 208.29813
D70: year | G70: FY 2025 | K70: FY 2026 | O70: FY 2027 | S70: FY 2028
D71: $k/year | G71: =SUM(G69:J69) -> 1455.936 | K71: =SUM(K69:N69) -> 1851.399 | O71: =SUM(O69:R69) -> 1827.7445 | S71: =SUM(S69:V69) -> 1210.7714
C72: The quarterly and annual utility costs, using the costing model on the Power Blocks tab
C73: The costs also carry an overhead due to the power consumend by the cooling equipment (see Power Blocks tab)
C75: CAPEX [$M] | D75: year | E75: 2024 | F75: 2024.25 | G75: 2024.5 | H75: 2024.75 | I75: 2025 | J75: 2025.25 | K75: =J75+0.25 -> 2025.5 | L75: =K75+0.25 -> 2025.75 | M75: =L75+0.25 -> 2026 | N75: =M75+0.25 -> 2026.25 | O75: =N75+0.25 -> 2026.5 | P75: =O75+0.25 -> 2026.75 | Q75: =P75+0.25 -> 2027 | R75: =Q75+0.25 -> 2027.25 | ... X75: =W75+0.25 -> 2028.75
D76: Total | E76: =SUM(E77:E79) -> 0 | F76: =SUM(F77:F79) -> 2569.136 | G76: =SUM(G77:G79) -> 5074.826 | H76: =SUM(H77:H79) -> 0 | I76: =SUM(I77:I79) -> 0 | J76: =SUM(J77:J79) -> 1821.42 | K76: =SUM(K77:K79) -> 9595.656 | L76: =SUM(L77:L79) -> 0 | ... X76: =SUM(X77:X79) -> 0
D77: BayView | E77: =BayView!K$103 -> 0 | F77: =BayView!L$103 -> 0 | G77: =BayView!M$103 -> 5074.826 | H77: =BayView!N$103 -> 0 | I77: =BayView!O$103 -> 0 | J77: =BayView!P$103 -> 0 | K77: =BayView!Q$103 -> 6167.136 | L77: =BayView!R$103 -> 0 | ... X77: =BayView!AD$103 -> 0
D78: Mt. Wash | E78: =Mt.Wash!K$102 -> 0 | F78: =Mt.Wash!L$102 -> 2569.136 | G78: =Mt.Wash!M$102 -> 0 | H78: =Mt.Wash!N$102 -> 0 | I78: =Mt.Wash!O$102 -> 0 | J78: =Mt.Wash!P$102 -> 0 | K78: =Mt.Wash!Q$102 -> 3428.52 | L78: =Mt.Wash!R$102 -> 0 | ... X78: =Mt.Wash!AD$102 -> 0
D79: Bloomberg | E79: =Bloomberg!K$102 -> 0 | F79: =Bloomberg!L$102 -> 0 | G79: =Bloomberg!M$102 -> 0 | H79: =Bloomberg!N$102 -> 0 | I79: =Bloomberg!O$102 -> 0 | J79: =Bloomberg!P$102 -> 1821.42 | K79: =Bloomberg!Q$102 -> 0 | L79: =Bloomberg!R$102 -> 0 | ... X79: =Bloomberg!AD$102 -> 0
C80: The quarterly CAPEX spent on equipment purchases
D83: year | E83: 2024 | F83: 2024.25 | G83: 2024.5 | H83: 2024.75 | I83: 2025 | J83: 2025.25 | K83: =J83+0.25 -> 2025.5 | L83: =K83+0.25 -> 2025.75 | M83: =L83+0.25 -> 2026 | N83: =M83+0.25 -> 2026.25 | O83: =N83+0.25 -> 2026.5 | P83: =O83+0.25 -> 2026.75 | Q83: =P83+0.25 -> 2027 | R83: =Q83+0.25 -> 2027.25 | ... X83: =W83+0.25 -> 2028.75
C84: TOTAL EQUIPMENT | D84: GPU | E84: =E90+E95+E100 -> 180 | F84: =F90+F95+F100 -> 180 | G84: =G90+G95+G100 -> 244 | H84: =H90+H95+H100 -> 436 | I84: =I90+I95+I100 -> 436 | J84: =J90+J95+J100 -> 436 | K84: =K90+K95+K100 -> 452 | L84: =L90+L95+L100 -> 612 | ... X84: =X90+X95+X100 -> 264
D85: CPU | E85: =E91+E96+E101 -> 72064 | F85: =F91+F96+F101 -> 72064 | G85: =G91+G96+G101 -> 77184 | H85: =H91+H96+H101 -> 87424 | I85: =I91+I96+I101 -> 87424 | J85: =J91+J96+J101 -> 87424 | K85: =K91+K96+K101 -> 89984 | L85: =L91+L96+L101 -> 89984 | ... X85: =X91+X96+X101 -> 31744
D86: Storage | E86: =E87+E88 -> 111.54 | F86: =F87+F88 -> 111.54 | G86: =G87+G88 -> 120.02 | H86: =H87+H88 -> 124.55 | I86: =I87+I88 -> 124.55 | J86: =J87+J88 -> 124.55 | K86: =K87+K88 -> 139.95 | L86: =L87+L88 -> 213.53 | ... X86: =X87+X88 -> 194.93
D87: Hdisk | E87: =E92+E97+E102 -> 104.94 | F87: =F92+F97+F102 -> 104.94 | G87: =G92+G97+G102 -> 113.42 | H87: =H92+H97+H102 -> 116.6 | I87: =I92+I97+I102 -> 116.6 | J87: =J92+J97+J102 -> 116.6 | K87: =K92+K97+K102 -> 127.2 | L87: =L92+L97+L102 -> 199.28 | ... X87: =X92+X97+X102 -> 183.38
D88: Sdisk | E88: =E93+E98+E103 -> 6.6 | F88: =F93+F98+F103 -> 6.6 | G88: =G93+G98+G103 -> 6.6 | H88: =H93+H98+H103 -> 7.95 | I88: =I93+I98+I103 -> 7.95 | J88: =J93+J98+J103 -> 7.95 | K88: =K93+K98+K103 -> 12.75 | L88: =L93+L98+L103 -> 14.25 | ... X88: =X93+X98+X103 -> 11.55
E89: 2024 | F89: 2024.25 | G89: 2024.5 | H89: 2024.75 | I89: 2025 | J89: 2025.25 | K89: =J89+0.25 -> 2025.5 | L89: =K89+0.25 -> 2025.75 | M89: =L89+0.25 -> 2026 | N89: =M89+0.25 -> 2026.25 | O89: =N89+0.25 -> 2026.5 | P89: =O89+0.25 -> 2026.75 | Q89: =P89+0.25 -> 2027 | R89: =Q89+0.25 -> 2027.25 | ... X89: =W89+0.25 -> 2028.75
C90: Bayview | D90: GPU | E90: =BayView!K153 -> 156 | F90: =BayView!L153 -> 156 | G90: =BayView!M153 -> 156 | H90: =BayView!N153 -> 348 | I90: =BayView!O153 -> 348 | J90: =BayView!P153 -> 348 | K90: =BayView!Q153 -> 348 | L90: =BayView!R153 -> 508 | ... X90: =BayView!AD153 -> 160
D91: CPU | E91: =BayView!K154 -> 48000 | F91: =BayView!L154 -> 48000 | G91: =BayView!M154 -> 48000 | H91: =BayView!N154 -> 58240 | I91: =BayView!O154 -> 58240 | J91: =BayView!P154 -> 58240 | K91: =BayView!Q154 -> 58240 | L91: =BayView!R154 -> 58240 | ... X91: =BayView!AD154 -> 0
D92: Hdisk | E92: =BayView!K155 -> 15.9 | F92: =BayView!L155 -> 15.9 | G92: =BayView!M155 -> 15.9 | H92: =BayView!N155 -> 19.08 | I92: =BayView!O155 -> 19.08 | J92: =BayView!P155 -> 19.08 | K92: =BayView!Q155 -> 19.08 | L92: =BayView!R155 -> 27.56 | ... X92: =BayView!AD155 -> 11.66
D93: Sdisk | E93: =BayView!K156 -> 1.2 | F93: =BayView!L156 -> 1.2 | G93: =BayView!M156 -> 1.2 | H93: =BayView!N156 -> 2.55 | I93: =BayView!O156 -> 2.55 | J93: =BayView!P156 -> 2.55 | K93: =BayView!Q156 -> 2.55 | L93: =BayView!R156 -> 4.05 | ... X93: =BayView!AD156 -> 1.35
E94: 2024 | F94: 2024.25 | G94: 2024.5 | H94: 2024.75 | I94: 2025 | J94: 2025.25 | K94: =J94+0.25 -> 2025.5 | L94: =K94+0.25 -> 2025.75 | M94: =L94+0.25 -> 2026 | N94: =M94+0.25 -> 2026.25 | O94: =N94+0.25 -> 2026.5 | P94: =O94+0.25 -> 2026.75 | Q94: =P94+0.25 -> 2027 | R94: =Q94+0.25 -> 2027.25 | ... X94: =W94+0.25 -> 2028.75
C95: Mt.Wash | D95: GPU | E95: =Mt.Wash!K152 -> 0 | F95: =Mt.Wash!L152 -> 0 | G95: =Mt.Wash!M152 -> 64 | H95: =Mt.Wash!N152 -> 64 | I95: =Mt.Wash!O152 -> 64 | J95: =Mt.Wash!P152 -> 64 | K95: =Mt.Wash!Q152 -> 64 | L95: =Mt.Wash!R152 -> 64 | ... X95: =Mt.Wash!AD152 -> 64
D96: CPU | E96: =Mt.Wash!K153 -> 4864 | F96: =Mt.Wash!L153 -> 4864 | G96: =Mt.Wash!M153 -> 9984 | H96: =Mt.Wash!N153 -> 9984 | I96: =Mt.Wash!O153 -> 9984 | J96: =Mt.Wash!P153 -> 9984 | K96: =Mt.Wash!Q153 -> 9984 | L96: =Mt.Wash!R153 -> 9984 | ... X96: =Mt.Wash!AD153 -> 9984
D97: Hdisk | E97: =Mt.Wash!K154 -> 14.84 | F97: =Mt.Wash!L154 -> 14.84 | G97: =Mt.Wash!M154 -> 23.32 | H97: =Mt.Wash!N154 -> 23.32 | I97: =Mt.Wash!O154 -> 23.32 | J97: =Mt.Wash!P154 -> 23.32 | K97: =Mt.Wash!Q154 -> 23.32 | L97: =Mt.Wash!R154 -> 86.92 | ... X97: =Mt.Wash!AD154 -> 86.92
D98: Sdisk | E98: =Mt.Wash!K155 -> 0 | F98: =Mt.Wash!L155 -> 0 | G98: =Mt.Wash!M155 -> 0 | H98: =Mt.Wash!N155 -> 0 | I98: =Mt.Wash!O155 -> 0 | J98: =Mt.Wash!P155 -> 0 | K98: =Mt.Wash!Q155 -> 0 | L98: =Mt.Wash!R155 -> 0 | ... X98: =Mt.Wash!AD155 -> 0
E99: 2024 | F99: 2024.25 | G99: 2024.5 | H99: 2024.75 | I99: 2025 | J99: 2025.25 | K99: =J99+0.25 -> 2025.5 | L99: =K99+0.25 -> 2025.75 | M99: =L99+0.25 -> 2026 | N99: =M99+0.25 -> 2026.25 | O99: =N99+0.25 -> 2026.5 | P99: =O99+0.25 -> 2026.75 | Q99: =P99+0.25 -> 2027 | R99: =Q99+0.25 -> 2027.25 | ... X99: =W99+0.25 -> 2028.75
C100: Bloomberg | D100: GPU | E100: =Bloomberg!K152 -> 24 | F100: =Bloomberg!L152 -> 24 | G100: =Bloomberg!M152 -> 24 | H100: =Bloomberg!N152 -> 24 | I100: =Bloomberg!O152 -> 24 | J100: =Bloomberg!P152 -> 24 | K100: =Bloomberg!Q152 -> 40 | L100: =Bloomberg!R152 -> 40 | ... X100: =Bloomberg!AD152 -> 40
D101: CPU | E101: =Bloomberg!K153 -> 19200 | F101: =Bloomberg!L153 -> 19200 | G101: =Bloomberg!M153 -> 19200 | H101: =Bloomberg!N153 -> 19200 | I101: =Bloomberg!O153 -> 19200 | J101: =Bloomberg!P153 -> 19200 | K101: =Bloomberg!Q153 -> 21760 | L101: =Bloomberg!R153 -> 21760 | ... X101: =Bloomberg!AD153 -> 21760
D102: Hdisk | E102: =Bloomberg!K154 -> 74.2 | F102: =Bloomberg!L154 -> 74.2 | G102: =Bloomberg!M154 -> 74.2 | H102: =Bloomberg!N154 -> 74.2 | I102: =Bloomberg!O154 -> 74.2 | J102: =Bloomberg!P154 -> 74.2 | K102: =Bloomberg!Q154 -> 84.8 | L102: =Bloomberg!R154 -> 84.8 | ... X102: =Bloomberg!AD154 -> 84.8
D103: Sdisk | E103: =Bloomberg!K155 -> 5.4 | F103: =Bloomberg!L155 -> 5.4 | G103: =Bloomberg!M155 -> 5.4 | H103: =Bloomberg!N155 -> 5.4 | I103: =Bloomberg!O155 -> 5.4 | J103: =Bloomberg!P155 -> 5.4 | K103: =Bloomberg!Q155 -> 10.2 | L103: =Bloomberg!R155 -> 10.2 | ... X103: =Bloomberg!AD155 -> 10.2

Sheet BayView
AU1: created for stair plot
AU2: Used
AU3: year | AV3: MW | AW3: adjusted
AU4: 2024 | AV4: =HLOOKUP(AU4,$K$47:$AD$48,2) -> 0.91212857 | AW4: =HLOOKUP($AU4,$K$45:$AD$46,2) -> 0.91212857
AU5: 2024.25 | AV5: =AV4 -> 0.91212857 | AW5: =AW4 -> 0.91212857
AU6: 2024.25 | AV6: =HLOOKUP(AU6,$K$47:$AD$48,2) -> 0.91212857 | AW6: =HLOOKUP($AU6,$K$45:$AD$46,2) -> 0.91212857
AU7: 2024.5 | AV7: =AV6 -> 0.91212857 | AW7: =AW6 -> 0.91212857
AU8: 2024.5 | AV8: =HLOOKUP(AU8,$K$47:$AD$48,2) -> 0.91212857 | AW8: =HLOOKUP($AU8,$K$45:$AD$46,2) -> 0.91212857
AU9: 2024.75 | AV9: =AV8 -> 0.91212857 | AW9: =AW8 -> 0.91212857
AU10: 2024.75 | AV10: =HLOOKUP(AU10,$K$47:$AD$48,2) -> 1.2400143 | AW10: =HLOOKUP($AU10,$K$45:$AD$46,2) -> 1.2400143
AU11: 2025 | AV11: =AV10 -> 1.2400143 | AW11: =AW10 -> 1.2400143
AU12: 2025 | AV12: =HLOOKUP(AU12,$K$47:$AD$48,2) -> 1.2400143 | AW12: =HLOOKUP($AU12,$K$45:$AD$46,2) -> 1.2400143
AU13: 2025.25 | AV13: =AV12 -> 1.2400143 | AW13: =AW12 -> 1.2400143
AU14: 2025.25 | AV14: =HLOOKUP(AU14,$K$47:$AD$48,2) -> 1.2400143 | AW14: =HLOOKUP($AU14,$K$45:$AD$46,2) -> 1.2400143
AU15: 2025.5 | AV15: =AV14 -> 1.2400143 | AW15: =AW14 -> 1.2400143
AU16: 2025.5 | AV16: =HLOOKUP(AU16,$K$47:$AD$48,2) -> 1.2400143 | AW16: =HLOOKUP($AU16,$K$45:$AD$46,2) -> 1.2400143
AU17: 2025.75 | AV17: =AV16 -> 1.2400143 | AW17: =AW16 -> 1.2400143
AU18: 2025.75 | AV18: =HLOOKUP(AU18,$K$47:$AD$48,2) -> 1.3754429 | AW18: =HLOOKUP($AU18,$K$45:$AD$46,2) -> 1.3754429
AU19: 2026 | AV19: =AV18 -> 1.3754429 | AW19: =AW18 -> 1.3754429
AU20: 2026 | AV20: =HLOOKUP(AU20,$K$47:$AD$48,2) -> 1.3754429 | AW20: =HLOOKUP($AU20,$K$45:$AD$46,2) -> 1.3754429
AU21: 2026.25 | AV21: =AV20 -> 1.3754429 | AW21: =AW20 -> 1.3754429
AU22: 2026.25 | AV22: =HLOOKUP(AU22,$K$47:$AD$48,2) -> 1.3754429 | AW22: =HLOOKUP($AU22,$K$45:$AD$46,2) -> 1.3754429
AU23: 2026.5 | AV23: =AV22 -> 1.3754429 | AW23: =AW22 -> 1.3754429
AU24: 2026.5 | AV24: =HLOOKUP(AU24,$K$47:$AD$48,2) -> 1.3754429 | AW24: =HLOOKUP($AU24,$K$45:$AD$46,2) -> 1.3754429
AU25: 2026.75 | AV25: =AV24 -> 1.3754429 | AW25: =AW24 -> 1.3754429
AU26: 2026.75 | AV26: =HLOOKUP(AU26,$K$47:$AD$48,2) -> 1.3754429 | AW26: =HLOOKUP($AU26,$K$45:$AD$46,2) -> 1.3754429
AU27: 2027 | AV27: =AV26 -> 1.3754429 | AW27: =AW26 -> 1.3754429
AU28: 2027 | AV28: =HLOOKUP(AU28,$K$47:$AD$48,2) -> 1.3754429 | AW28: =HLOOKUP($AU28,$K$45:$AD$46,2) -> 1.3754429
AU29: 2027.25 | AV29: =AV28 -> 1.3754429 | AW29: =AW28 -> 1.3754429
AU30: 2027.25 | AV30: =HLOOKUP(AU30,$K$47:$AD$48,2) -> 0.61331429 | AW30: =HLOOKUP($AU30,$K$45:$AD$46,2) -> 0.61331429
AU31: 2027.5 | AV31: =AV30 -> 0.61331429 | AW31: =AW30 -> 0.61331429
AU32: 2027.5 | AV32: =HLOOKUP(AU32,$K$47:$AD$48,2) -> 0.61331429 | AW32: =HLOOKUP($AU32,$K$45:$AD$46,2) -> 0.61331429
AU33: 2027.75 | AV33: =AV32 -> 0.61331429 | AW33: =AW32 -> 0.61331429
AU34: 2027.75 | AV34: =HLOOKUP(AU34,$K$47:$AD$48,2) -> 0.61331429 | AW34: =HLOOKUP($AU34,$K$45:$AD$46,2) -> 0.61331429
AU35: 2028 | AV35: =AV34 -> 0.61331429 | AW35: =AW34 -> 0.61331429
AU36: 2028 | AV36: =HLOOKUP(AU36,$K$47:$AD$48,2) -> 0.61331429 | AW36: =HLOOKUP($AU36,$K$45:$AD$46,2) -> 0.61331429
AU37: 2028.25 | AV37: =AV36 -> 0.61331429 | AW37: =AW36 -> 0.61331429
AU38: 2028.25 | AV38: =HLOOKUP(AU38,$K$47:$AD$48,2) -> 0.61331429 | AW38: =HLOOKUP($AU38,$K$45:$AD$46,2) -> 0.61331429
AU39: 2028.5 | AV39: =AV38 -> 0.61331429 | AW39: =AW38 -> 0.61331429
AU40: 2028.5 | AV40: =HLOOKUP(AU40,$K$47:$AD$48,2) -> 0.28931429 | AW40: =HLOOKUP($AU40,$K$45:$AD$46,2) -> 0.28931429
AU41: 2028.75 | AV41: =AV40 -> 0.28931429 | AW41: =AW40 -> 0.28931429
AU42: 2028.75 | AV42: =HLOOKUP(AU42,$K$47:$AD$48,2) -> 0.28931429 | AW42: =HLOOKUP($AU42,$K$45:$AD$46,2) -> 0.28931429
K45: 2024 | L45: 2024.25 | M45: 2024.5 | N45: 2024.75 | O45: 2025 | P45: 2025.25 | Q45: =P45+0.25 -> 2025.5 | R45: =Q45+0.25 -> 2025.75 | S45: =R45+0.25 -> 2026 | T45: =S45+0.25 -> 2026.25 | U45: =T45+0.25 -> 2026.5 | V45: =U45+0.25 -> 2026.75 | W45: =V45+0.25 -> 2027 | X45: =W45+0.25 -> 2027.25 | ... AD45: =AC45+0.25 -> 2028.75
J46: adjusted | K46: =K48 -> 0.91212857 | L46: =L48 -> 0.91212857 | M46: =M48 -> 0.91212857 | N46: =N48 -> 1.2400143 | O46: =O48 -> 1.2400143 | P46: =P48 -> 1.2400143 | Q46: =Q48 -> 1.2400143 | R46: =R48 -> 1.3754429 | ... AD46: =AD48 -> 0.28931429
C47: BayView | J47: POWER USE [MW] | K47: 2024 | L47: 2024.25 | M47: 2024.5 | N47: 2024.75 | O47: 2025 | P47: 2025.25 | Q47: =P47+0.25 -> 2025.5 | R47: =Q47+0.25 -> 2025.75 | S47: =R47+0.25 -> 2026 | T47: =S47+0.25 -> 2026.25 | U47: =T47+0.25 -> 2026.5 | V47: =U47+0.25 -> 2026.75 | W47: =V47+0.25 -> 2027 | X47: =W47+0.25 -> 2027.25 | ... AD47: =AC47+0.25 -> 2028.75
K48: =SUM(K51:K76) -> 0.91212857 | L48: =SUM(L51:L76) -> 0.91212857 | M48: =SUM(M51:M76) -> 0.91212857 | N48: =SUM(N51:N76) -> 1.2400143 | O48: =SUM(O51:O76) -> 1.2400143 | P48: =SUM(P51:P76) -> 1.2400143 | Q48: =SUM(Q51:Q76) -> 1.2400143 | R48: =SUM(R51:R76) -> 1.3754429 | ... AD48: =SUM(AD51:AD76) -> 0.28931429
C49: INPUT | F49: LOOKUP
C50: category | D50: units | E50: project | F50: type | G50: blocks | H50: MW | I50: $K | J50: quantity | K50: 2024 | O50: 2025 | S50: 2026 | W50: 2027 | AA50: 2028
C51: HPC2 | D51: 150 | E51: COLO | F51: =_xlfn.XLOOKUP($C51,'Power Blocks'!$C$20:$C$31,'Power Blocks'!$D$20:$D$31,,) -> CPU | G51: =IF(F51=" "," ",D51/_xlfn.XLOOKUP($C51,'Power Blocks'!$C$20:$C$31,'Power Blocks'!$I$20:$I$31,,)) -> 1.875 | H51: =IF(F51=" "," ",_xlfn.XLOOKUP($C51,'Power Blocks'!$C$20:$C$31,'Power Blocks'!$J$20:$J$31,,)*$G51) -> 0.1875 | I51: =IF(F51=" "," ",_xlfn.XLOOKUP($C51,'Power Blocks'!$C$20:$C$31,'Power Blocks'!$K$20:$K$31,,)/1000*$G51) -> 2250 | J51: =IF(F51=" "," ",_xlfn.XLOOKUP($C51,'Power Blocks'!$C$20:$C$31,'Power Blocks'!$M$20:$M$31,,)*$G51) -> 38400 | K51: =$H51 -> 0.1875 | L51: =$H51 -> 0.1875 | M51: =$H51 -> 0.1875 | N51: =$H51 -> 0.1875 | O51: =$H51 -> 0.1875 | P51: =$H51 -> 0.1875 | Q51: =$H51 -> 0.1875 | R51: =$H51 -> 0.1875 | ... W51: =$H51 -> 0.1875
C52: HPC1 | D52: 375 | E52: RockFish | F52: =_xlfn.XLOOKUP($C52,'Power Blocks'!$C$20:$C$31,'Power Blocks'!$D$20:$D$31,,) -> CPU | G52: =IF(F52=" "," ",D52/_xlfn.XLOOKUP($C52,'Power Blocks'!$C$20:$C$31,'Power Blocks'!$I$20:$I$31,,)) -> 3.75 | H52: =IF(F52=" "," ",_xlfn.XLOOKUP($C52,'Power Blocks'!$C$20:$C$31,'Power Blocks'!$J$20:$J$31,,)*$G52) -> 0.375 | I52: =IF(F52=" "," ",_xlfn.XLOOKUP($C52,'Power Blocks'!$C$20:$C$31,'Power Blocks'!$K$20:$K$31,,)/1000*$G52) -> 3750 | J52: =IF(F52=" "," ",_xlfn.XLOOKUP($C52,'Power Blocks'!$C$20:$C$31,'Power Blocks'!$M$20:$M$31,,)*$G52) -> 48000 | K52: =$H52 -> 0.375 | L52: =$H52 -> 0.375 | M52: =$H52 -> 0.375 | N52: =$H52 -> 0.375 | O52: =$H52 -> 0.375 | P52: =$H52 -> 0.375 | Q52: =$H52 -> 0.375 | R52: =$H52 -> 0.375 | ... W52: =$H52 -> 0.375
C53: V100-4 | D53: 31 | E53: ARCH | F53: =_xlfn.XLOOKUP($C53,'Power Blocks'!$C$20:$C$31,'Power Blocks'!$D$20:$D$31,,) -> GPU | G53: =IF(F53=" "," ",D53/_xlfn.XLOOKUP($C53,'Power Blocks'!$C$20:$C$31,'Power Blocks'!$I$20:$I$31,,)) -> 1.55 | H53: =IF(F53=" "," ",_xlfn.XLOOKUP($C53,'Power Blocks'!$C$20:$C$31,'Power Blocks'!$J$20:$J$31,,)*$G53) -> 0.155 | I53: =IF(F53=" "," ",_xlfn.XLOOKUP($C53,'Power Blocks'!$C$20:$C$31,'Power Blocks'!$K$20:$K$31,,)/1000*$G53) -> 620 | J53: =IF(F53=" "," ",_xlfn.XLOOKUP($C53,'Power Blocks'!$C$20:$C$31,'Power Blocks'!$M$20:$M$31,,)*$G53) -> 124 | K53: =$H53 -> 0.155 | L53: =$H53 -> 0.155 | M53: =$H53 -> 0.155 | N53: =$H53 -> 0.155 | O53: =$H53 -> 0.155 | P53: =$H53 -> 0.155 | Q53: =$H53 -> 0.155 | R53: =$H53 -> 0.155 | ... W53: =$H53 -> 0.155
C54: HDD | D54: 30 | E54: ARCH | F54: =_xlfn.XLOOKUP($C54,'Power Blocks'!$C$20:$C$31,'Power Blocks'!$D$20:$D$31,,) -> Hdisk | G54: =IF(F54=" "," ",D54/_xlfn.XLOOKUP($C54,'Power Blocks'!$C$20:$C$31,'Power Blocks'!$I$20:$I$31,,)) -> 0.21428571 | H54: =IF(F54=" "," ",_xlfn.XLOOKUP($C54,'Power Blocks'!$C$20:$C$31,'Power Blocks'!$J$20:$J$31,,)*$G54) -> 0.021428571 | I54: =IF(F54=" "," ",_xlfn.XLOOKUP($C54,'Power Blocks'!$C$20:$C$31,'Power Blocks'!$K$20:$K$31,,)/1000*$G54) -> 857.13 | J54: =IF(F54=" "," ",_xlfn.XLOOKUP($C54,'Power Blocks'!$C$20:$C$31,'Power Blocks'!$M$20:$M$31,,)*$G54) -> 15.9 | K54: =$H54 -> 0.021428571 | L54: =$H54 -> 0.021428571 | M54: =$H54 -> 0.021428571 | N54: =$H54 -> 0.021428571 | O54: =$H54 -> 0.021428571 | P54: =$H54 -> 0.021428571 | Q54: =$H54 -> 0.021428571 | R54: =$H54 -> 0.021428571 | ... W54: =$H54 -> 0.021428571
C55: SSD | D55: 4 | E55: ARCH | F55: =_xlfn.XLOOKUP($C55,'Power Blocks'!$C$20:$C$31,'Power Blocks'!$D$20:$D$31,,) -> Sdisk | G55: =IF(F55=" "," ",D55/_xlfn.XLOOKUP($C55,'Power Blocks'!$C$20:$C$31,'Power Blocks'!$I$20:$I$31,,)) -> 0.032 | H55: =IF(F55=" "," ",_xlfn.XLOOKUP($C55,'Power Blocks'!$C$20:$C$31,'Power Blocks'!$J$20:$J$31,,)*$G55) -> 0.0032 | I55: =IF(F55=" "," ",_xlfn.XLOOKUP($C55,'Power Blocks'!$C$20:$C$31,'Power Blocks'!$K$20:$K$31,,)/1000*$G55) -> 168 | J55: =IF(F55=" "," ",_xlfn.XLOOKUP($C55,'Power Blocks'!$C$20:$C$31,'Power Blocks'!$M$20:$M$31,,)*$G55) -> 1.2 | K55: =$H55 -> 0.0032 | L55: =$H55 -> 0.0032 | M55: =$H55 -> 0.0032 | N55: =$H55 -> 0.0032 | O55: =$H55 -> 0.0032 | P55: =$H55 -> 0.0032 | Q55: =$H55 -> 0.0032 | R55: =$H55 -> 0.0032 | ... W55: =$H55 -> 0.0032
C56: L40-8 | D56: 4 | E56: ARCH | F56: =_xlfn.XLOOKUP($C56,'Power Blocks'!$C$20:$C$31,'Power Blocks'!$D$20:$D$31,,) -> GPU | G56: =IF(F56=" "," ",D56/_xlfn.XLOOKUP($C56,'Power Blocks'!$C$20:$C$31,'Power Blocks'!$I$20:$I$31,,)) -> 0.2 | H56: =IF(F56=" "," ",_xlfn.XLOOKUP($C56,'Power Blocks'!$C$20:$C$31,'Power Blocks'!$J$20:$J$31,,)*$G56) -> 0.02 | I56: =IF(F56=" "," ",_xlfn.XLOOKUP($C56,'Power Blocks'!$C$20:$C$31,'Power Blocks'!$K$20:$K$31,,)/1000*$G56) -> 245.2 | J56: =IF(F56=" "," ",_xlfn.XLOOKUP($C56,'Power Blocks'!$C$20:$C$31,'Power Blocks'!$M$20:$M$31,,)*$G56) -> 32 | K56: =$H56 -> 0.02 | L56: =$H56 -> 0.02 | M56: =$H56 -> 0.02 | N56: =$H56 -> 0.02 | O56: =$H56 -> 0.02 | P56: =$H56 -> 0.02 | Q56: =$H56 -> 0.02 | R56: =$H56 -> 0.02 | ... W56: =$H56 -> 0.02
C57: A100-8 | D57: 15 | E57: DSAI P1 | F57: =_xlfn.XLOOKUP($C57,'Power Blocks'!$C$20:$C$31,'Power Blocks'!$D$20:$D$31,,) -> GPU | G57: =IF(F57=" "," ",D57/_xlfn.XLOOKUP($C57,'Power Blocks'!$C$20:$C$31,'Power Blocks'!$I$20:$I$31,,)) -> 1.5 | H57: =IF(F57=" "," ",_xlfn.XLOOKUP($C57,'Power Blocks'!$C$20:$C$31,'Power Blocks'!$J$20:$J$31,,)*$G57) -> 0.15 | I57: =IF(F57=" "," ",_xlfn.XLOOKUP($C57,'Power Blocks'!$C$20:$C$31,'Power Blocks'!$K$20:$K$31,,)/1000*$G57) -> 1680 | J57: =IF(F57=" "," ",_xlfn.XLOOKUP($C57,'Power Blocks'!$C$20:$C$31,'Power Blocks'!$M$20:$M$31,,)*$G57) -> 120 | K57: =$H57 -> 0.15 | L57: =$H57 -> 0.15 | M57: =$H57 -> 0.15 | N57: =$H57 -> 0.15 | O57: =$H57 -> 0.15 | P57: =$H57 -> 0.15 | Q57: =$H57 -> 0.15 | R57: =$H57 -> 0.15 | ... AD57: =$H57 -> 0.15
C58: H100-4 | D58: 32 | E58: DSAI P1 | F58: =_xlfn.XLOOKUP($C58,'Power Blocks'!$C$20:$C$31,'Power Blocks'!$D$20:$D$31,,) -> GPU | G58: =IF(F58=" "," ",D58/_xlfn.XLOOKUP($C58,'Power Blocks'!$C$20:$C$31,'Power Blocks'!$I$20:$I$31,,)) -> 2 | H58: =IF(F58=" "," ",_xlfn.XLOOKUP($C58,'Power Blocks'!$C$20:$C$31,'Power Blocks'!$J$20:$J$31,,)*$G58) -> 0.2 | I58: =IF(F58=" "," ",_xlfn.XLOOKUP($C58,'Power Blocks'!$C$20:$C$31,'Power Blocks'!$K$20:$K$31,,)/1000*$G58) -> 3424 | J58: =IF(F58=" "," ",_xlfn.XLOOKUP($C58,'Power Blocks'!$C$20:$C$31,'Power Blocks'!$M$20:$M$31,,)*$G58) -> 128 | N58: =$H58 -> 0.2 | O58: =$H58 -> 0.2 | P58: =$H58 -> 0.2 | Q58: =$H58 -> 0.2 | R58: =$H58 -> 0.2 | S58: =$H58 -> 0.2 | T58: =$H58 -> 0.2 | U58: =$H58 -> 0.2 | ... AB58: =$H58 -> 0.2
C59: L40-8 | D59: 8 | E59: DSAI P1 | F59: =_xlfn.XLOOKUP($C59,'Power Blocks'!$C$20:$C$31,'Power Blocks'!$D$20:$D$31,,) -> GPU | G59: =IF(F59=" "," ",D59/_xlfn.XLOOKUP($C59,'Power Blocks'!$C$20:$C$31,'Power Blocks'!$I$20:$I$31,,)) -> 0.4 | H59: =IF(F59=" "," ",_xlfn.XLOOKUP($C59,'Power Blocks'!$C$20:$C$31,'Power Blocks'!$J$20:$J$31,,)*$G59) -> 0.04 | I59: =IF(F59=" "," ",_xlfn.XLOOKUP($C59,'Power Blocks'!$C$20:$C$31,'Power Blocks'!$K$20:$K$31,,)/1000*$G59) -> 490.4 | J59: =IF(F59=" "," ",_xlfn.XLOOKUP($C59,'Power Blocks'!$C$20:$C$31,'Power Blocks'!$M$20:$M$31,,)*$G59) -> 64 | N59: =$H59 -> 0.04 | O59: =$H59 -> 0.04 | P59: =$H59 -> 0.04 | Q59: =$H59 -> 0.04 | R59: =$H59 -> 0.04 | S59: =$H59 -> 0.04 | T59: =$H59 -> 0.04 | U59: =$H59 -> 0.04 | ... AB59: =$H59 -> 0.04
C60: HPC1 | D60: 80 | E60: DSAI P1 | F60: =_xlfn.XLOOKUP($C60,'Power Blocks'!$C$20:$C$31,'Power Blocks'!$D$20:$D$31,,) -> CPU | G60: =IF(F60=" "," ",D60/_xlfn.XLOOKUP($C60,'Power Blocks'!$C$20:$C$31,'Power Blocks'!$I$20:$I$31,,)) -> 0.8 | H60: =IF(F60=" "," ",_xlfn.XLOOKUP($C60,'Power Blocks'!$C$20:$C$31,'Power Blocks'!$J$20:$J$31,,)*$G60) -> 0.08 | I60: =IF(F60=" "," ",_xlfn.XLOOKUP($C60,'Power Blocks'!$C$20:$C$31,'Power Blocks'!$K$20:$K$31,,)/1000*$G60) -> 800 | J60: =IF(F60=" "," ",_xlfn.XLOOKUP($C60,'Power Blocks'!$C$20:$C$31,'Power Blocks'!$M$20:$M$31,,)*$G60) -> 10240 | N60: =$H60 -> 0.08 | O60: =$H60 -> 0.08 | P60: =$H60 -> 0.08 | Q60: =$H60 -> 0.08 | R60: =$H60 -> 0.08 | S60: =$H60 -> 0.08 | T60: =$H60 -> 0.08 | U60: =$H60 -> 0.08 | ... AB60: =$H60 -> 0.08
C61: HDD | D61: 6 | E61: DSAI P1 | F61: =_xlfn.XLOOKUP($C61,'Power Blocks'!$C$20:$C$31,'Power Blocks'!$D$20:$D$31,,) -> Hdisk | G61: =IF(F61=" "," ",D61/_xlfn.XLOOKUP($C61,'Power Blocks'!$C$20:$C$31,'Power Blocks'!$I$20:$I$31,,)) -> 0.042857143 | H61: =IF(F61=" "," ",_xlfn.XLOOKUP($C61,'Power Blocks'!$C$20:$C$31,'Power Blocks'!$J$20:$J$31,,)*$G61) -> 0.0042857143 | I61: =IF(F61=" "," ",_xlfn.XLOOKUP($C61,'Power Blocks'!$C$20:$C$31,'Power Blocks'!$K$20:$K$31,,)/1000*$G61) -> 171.426 | J61: =IF(F61=" "," ",_xlfn.XLOOKUP($C61,'Power Blocks'!$C$20:$C$31,'Power Blocks'!$M$20:$M$31,,)*$G61) -> 3.18 | N61: =$H61 -> 0.0042857143 | O61: =$H61 -> 0.0042857143 | P61: =$H61 -> 0.0042857143 | Q61: =$H61 -> 0.0042857143 | R61: =$H61 -> 0.0042857143 | S61: =$H61 -> 0.0042857143 | T61: =$H61 -> 0.0042857143 | U61: =$H61 -> 0.0042857143 | ... AD61: =$H61 -> 0.0042857143
C62: SSD | D62: 4.5 | E62: DSAI P1 | F62: =_xlfn.XLOOKUP($C62,'Power Blocks'!$C$20:$C$31,'Power Blocks'!$D$20:$D$31,,) -> Sdisk | G62: =IF(F62=" "," ",D62/_xlfn.XLOOKUP($C62,'Power Blocks'!$C$20:$C$31,'Power Blocks'!$I$20:$I$31,,)) -> 0.036 | H62: =IF(F62=" "," ",_xlfn.XLOOKUP($C62,'Power Blocks'!$C$20:$C$31,'Power Blocks'!$J$20:$J$31,,)*$G62) -> 0.0036 | I62: =IF(F62=" "," ",_xlfn.XLOOKUP($C62,'Power Blocks'!$C$20:$C$31,'Power Blocks'!$K$20:$K$31,,)/1000*$G62) -> 189 | J62: =IF(F62=" "," ",_xlfn.XLOOKUP($C62,'Power Blocks'!$C$20:$C$31,'Power Blocks'!$M$20:$M$31,,)*$G62) -> 1.35 | N62: =$H62 -> 0.0036 | O62: =$H62 -> 0.0036 | P62: =$H62 -> 0.0036 | Q62: =$H62 -> 0.0036 | R62: =$H62 -> 0.0036 | S62: =$H62 -> 0.0036 | T62: =$H62 -> 0.0036 | U62: =$H62 -> 0.0036 | ... AD62: =$H62 -> 0.0036
C63: H200-8 | D63: 8 | E63: Schmidt | F63: =_xlfn.XLOOKUP($C63,'Power Blocks'!$C$20:$C$31,'Power Blocks'!$D$20:$D$31,,) -> GPU | G63: =IF(F63=" "," ",D63/_xlfn.XLOOKUP($C63,'Power Blocks'!$C$20:$C$31,'Power Blocks'!$I$20:$I$31,,)) -> 0.8 | H63: =IF(F63=" "," ",_xlfn.XLOOKUP($C63,'Power Blocks'!$C$20:$C$31,'Power Blocks'!$J$20:$J$31,,)*$G63) -> 0.08 | I63: =IF(F63=" "," ",_xlfn.XLOOKUP($C63,'Power Blocks'!$C$20:$C$31,'Power Blocks'!$K$20:$K$31,,)/1000*$G63) -> 2200 | J63: =IF(F63=" "," ",_xlfn.XLOOKUP($C63,'Power Blocks'!$C$20:$C$31,'Power Blocks'!$M$20:$M$31,,)*$G63) -> 64 | R63: =$H63 -> 0.08 | S63: =$H63 -> 0.08 | T63: =$H63 -> 0.08 | U63: =$H63 -> 0.08 | V63: =$H63 -> 0.08 | W63: =$H63 -> 0.08 | X63: =$H63 -> 0.08 | Y63: =$H63 -> 0.08 | ... AD63: =$H63 -> 0.08
C64: HDD | D64: 16 | E64: Schmidt | F64: =_xlfn.XLOOKUP($C64,'Power Blocks'!$C$20:$C$31,'Power Blocks'!$D$20:$D$31,,) -> Hdisk | G64: =IF(F64=" "," ",D64/_xlfn.XLOOKUP($C64,'Power Blocks'!$C$20:$C$31,'Power Blocks'!$I$20:$I$31,,)) -> 0.11428571 | H64: =IF(F64=" "," ",_xlfn.XLOOKUP($C64,'Power Blocks'!$C$20:$C$31,'Power Blocks'!$J$20:$J$31,,)*$G64) -> 0.011428571 | I64: =IF(F64=" "," ",_xlfn.XLOOKUP($C64,'Power Blocks'!$C$20:$C$31,'Power Blocks'!$K$20:$K$31,,)/1000*$G64) -> 457.136 | J64: =IF(F64=" "," ",_xlfn.XLOOKUP($C64,'Power Blocks'!$C$20:$C$31,'Power Blocks'!$M$20:$M$31,,)*$G64) -> 8.48 | R64: =$H64 -> 0.011428571 | S64: =$H64 -> 0.011428571 | T64: =$H64 -> 0.011428571 | U64: =$H64 -> 0.011428571 | V64: =$H64 -> 0.011428571 | W64: =$H64 -> 0.011428571 | X64: =$H64 -> 0.011428571 | Y64: =$H64 -> 0.011428571 | ... AD64: =$H64 -> 0.011428571
C65: SSD | D65: 5 | E65: Schmidt | F65: =_xlfn.XLOOKUP($C65,'Power Blocks'!$C$20:$C$31,'Power Blocks'!$D$20:$D$31,,) -> Sdisk | G65: =IF(F65=" "," ",D65/_xlfn.XLOOKUP($C65,'Power Blocks'!$C$20:$C$31,'Power Blocks'!$I$20:$I$31,,)) -> 0.04 | H65: =IF(F65=" "," ",_xlfn.XLOOKUP($C65,'Power Blocks'!$C$20:$C$31,'Power Blocks'!$J$20:$J$31,,)*$G65) -> 0.004 | I65: =IF(F65=" "," ",_xlfn.XLOOKUP($C65,'Power Blocks'!$C$20:$C$31,'Power Blocks'!$K$20:$K$31,,)/1000*$G65) -> 210 | J65: =IF(F65=" "," ",_xlfn.XLOOKUP($C65,'Power Blocks'!$C$20:$C$31,'Power Blocks'!$M$20:$M$31,,)*$G65) -> 1.5 | R65: =$H65 -> 0.004 | S65: =$H65 -> 0.004 | T65: =$H65 -> 0.004 | U65: =$H65 -> 0.004 | V65: =$H65 -> 0.004 | W65: =$H65 -> 0.004 | X65: =$H65 -> 0.004 | Y65: =$H65 -> 0.004 | ... AB65: =$H65 -> 0.004
C66: H200-8 | D66: 4 | E66: Schmidt | F66: =_xlfn.XLOOKUP($C66,'Power Blocks'!$C$20:$C$31,'Power Blocks'!$D$20:$D$31,,) -> GPU | G66: =IF(F66=" "," ",D66/_xlfn.XLOOKUP($C66,'Power Blocks'!$C$20:$C$31,'Power Blocks'!$I$20:$I$31,,)) -> 0.4 | H66: =IF(F66=" "," ",_xlfn.XLOOKUP($C66,'Power Blocks'!$C$20:$C$31,'Power Blocks'!$J$20:$J$31,,)*$G66) -> 0.04 | I66: =IF(F66=" "," ",_xlfn.XLOOKUP($C66,'Power Blocks'!$C$20:$C$31,'Power Blocks'!$K$20:$K$31,,)/1000*$G66) -> 1100 | J66: =IF(F66=" "," ",_xlfn.XLOOKUP($C66,'Power Blocks'!$C$20:$C$31,'Power Blocks'!$M$20:$M$31,,)*$G66) -> 32 | R66: =$H66 -> 0.04 | S66: =$H66 -> 0.04 | T66: =$H66 -> 0.04 | U66: =$H66 -> 0.04 | V66: =$H66 -> 0.04 | W66: =$H66 -> 0.04 | X66: =$H66 -> 0.04 | Y66: =$H66 -> 0.04 | ... AD66: =$H66 -> 0.04
C67: HPC1 | F67: =_xlfn.XLOOKUP($C67,'Power Blocks'!$C$20:$C$31,'Power Blocks'!$D$20:$D$31,,) -> CPU | G67: =IF(F67=" "," ",D67/_xlfn.XLOOKUP($C67,'Power Blocks'!$C$20:$C$31,'Power Blocks'!$I$20:$I$31,,)) -> 0 | H67: =IF(F67=" "," ",_xlfn.XLOOKUP($C67,'Power Blocks'!$C$20:$C$31,'Power Blocks'!$J$20:$J$31,,)*$G67) -> 0 | I67: =IF(F67=" "," ",_xlfn.XLOOKUP($C67,'Power Blocks'!$C$20:$C$31,'Power Blocks'!$K$20:$K$31,,)/1000*$G67) -> 0 | J67: =IF(F67=" "," ",_xlfn.XLOOKUP($C67,'Power Blocks'!$C$20:$C$31,'Power Blocks'!$M$20:$M$31,,)*$G67) -> 0 | S67: =$H67 -> 0 | T67: =$H67 -> 0 | U67: =$H67 -> 0 | V67: =$H67 -> 0 | W67: =$H67 -> 0 | X67: =$H67 -> 0 | Y67: =$H67 -> 0 | Z67: =$H67 -> 0 | ... AD67: =$H67 -> 0
C68: -- | F68: =_xlfn.XLOOKUP($C68,'Power Blocks'!$C$20:$C$31,'Power Blocks'!$D$20:$D$31,,) | G68: =IF(F68=" "," ",D68/_xlfn.XLOOKUP($C68,'Power Blocks'!$C$20:$C$31,'Power Blocks'!$I$20:$I$31,,)) | H68: =IF(F68=" "," ",_xlfn.XLOOKUP($C68,'Power Blocks'!$C$20:$C$31,'Power Blocks'!$J$20:$J$31,,)*$G68) | I68: =IF(F68=" "," ",_xlfn.XLOOKUP($C68,'Power Blocks'!$C$20:$C$31,'Power Blocks'!$K$20:$K$31,,)/1000*$G68) | J68: =IF(F68=" "," ",_xlfn.XLOOKUP($C68,'Power Blocks'!$C$20:$C$31,'Power Blocks'!$M$20:$M$31,,)*$G68) | S68: =$H68 | T68: =$H68 | U68: =$H68 | V68: =$H68 | W68: =$H68 | X68: =$H68 | Y68: =$H68 | Z68: =$H68 | ... AB68: =$H68
C69: -- | F69: =_xlfn.XLOOKUP($C69,'Power Blocks'!$C$20:$C$31,'Power Blocks'!$D$20:$D$31,,) | G69: =IF(F69=" "," ",D69/_xlfn.XLOOKUP($C69,'Power Blocks'!$C$20:$C$31,'Power Blocks'!$I$20:$I$31,,)) | H69: =IF(F69=" "," ",_xlfn.XLOOKUP($C69,'Power Blocks'!$C$20:$C$31,'Power Blocks'!$J$20:$J$31,,)*$G69) | I69: =IF(F69=" "," ",_xlfn.XLOOKUP($C69,'Power Blocks'!$C$20:$C$31,'Power Blocks'!$K$20:$K$31,,)/1000*$G69) | J69: =IF(F69=" "," ",_xlfn.XLOOKUP($C69,'Power Blocks'!$C$20:$C$31,'Power Blocks'!$M$20:$M$31,,)*$G69) | S69: =$H69 | T69: =$H69 | U69: =$H69 | V69: =$H69 | W69: =$H69 | X69: =$H69 | Y69: =$H69 | Z69: =$H69 | ... AB69: =$H69
C70: -- | F70: =_xlfn.XLOOKUP($C70,'Power Blocks'!$C$20:$C$31,'Power Blocks'!$D$20:$D$31,,) | G70: =IF(F70=" "," ",D70/_xlfn.XLOOKUP($C70,'Power Blocks'!$C$20:$C$31,'Power Blocks'!$I$20:$I$31,,)) | H70: =IF(F70=" "," ",_xlfn.XLOOKUP($C70,'Power Blocks'!$C$20:$C$31,'Power Blocks'!$J$20:$J$31,,)*$G70) | I70: =IF(F70=" "," ",_xlfn.XLOOKUP($C70,'Power Blocks'!$C$20:$C$31,'Power Blocks'!$K$20:$K$31,,)/1000*$G70) | J70: =IF(F70=" "," ",_xlfn.XLOOKUP($C70,'Power Blocks'!$C$20:$C$31,'Power Blocks'!$M$20:$M$31,,)*$G70) | S70: =$H70 | T70: =$H70 | U70: =$H70 | V70: =$H70 | W70: =$H70 | X70: =$H70 | Y70: =$H70 | Z70: =$H70 | ... AB70: =$H70
C71: -- | F71: =_xlfn.XLOOKUP($C71,'Power Blocks'!$C$20:$C$31,'Power Blocks'!$D$20:$D$31,,) | G71: =IF(F71=" "," ",D71/_xlfn.XLOOKUP($C71,'Power Blocks'!$C$20:$C$31,'Power Blocks'!$I$20:$I$31,,)) | H71: =IF(F71=" "," ",_xlfn.XLOOKUP($C71,'Power Blocks'!$C$20:$C$31,'Power Blocks'!$J$20:$J$31,,)*$G71) | I71: =IF(F71=" "," ",_xlfn.XLOOKUP($C71,'Power Blocks'!$C$20:$C$31,'Power Blocks'!$K$20:$K$31,,)/1000*$G71) | J71: =IF(F71=" "," ",_xlfn.XLOOKUP($C71,'Power Blocks'!$C$20:$C$31,'Power Blocks'!$M$20:$M$31,,)*$G71) | K71: =$H71 | L71: =$H71 | M71: =$H71 | N71: =$H71 | O71: =$H71 | P71: =$H71 | Q71: =$H71 | R71: =$H71 | ... AD71: =$H71
C72: -- | F72: =_xlfn.XLOOKUP($C72,'Power Blocks'!$C$20:$C$31,'Power Blocks'!$D$20:$D$31,,) | G72: =IF(F72=" "," ",D72/_xlfn.XLOOKUP($C72,'Power Blocks'!$C$20:$C$31,'Power Blocks'!$I$20:$I$31,,)) | H72: =IF(F72=" "," ",_xlfn.XLOOKUP($C72,'Power Blocks'!$C$20:$C$31,'Power Blocks'!$J$20:$J$31,,)*$G72) | I72: =IF(F72=" "," ",_xlfn.XLOOKUP($C72,'Power Blocks'!$C$20:$C$31,'Power Blocks'!$K$20:$K$31,,)/1000*$G72) | J72: =IF(F72=" "," ",_xlfn.XLOOKUP($C72,'Power Blocks'!$C$20:$C$31,'Power Blocks'!$M$20:$M$31,,)*$G72)
C73: HPC1 | D73: 200 | E73: ARCH-2(*) | F73: =_xlfn.XLOOKUP($C73,'Power Blocks'!$C$20:$C$31,'Power Blocks'!$D$20:$D$31,,) -> CPU | G73: =IF(F73=" "," ",D73/_xlfn.XLOOKUP($C73,'Power Blocks'!$C$20:$C$31,'Power Blocks'!$I$20:$I$31,,)) -> 2 | H73: =IF(F73=" "," ",_xlfn.XLOOKUP($C73,'Power Blocks'!$C$20:$C$31,'Power Blocks'!$J$20:$J$31,,)*$G73) -> 0.2 | I73: =IF(F73=" "," ",_xlfn.XLOOKUP($C73,'Power Blocks'!$C$20:$C$31,'Power Blocks'!$K$20:$K$31,,)/1000*$G73) -> 2000 | J73: =IF(F73=" "," ",_xlfn.XLOOKUP($C73,'Power Blocks'!$C$20:$C$31,'Power Blocks'!$M$20:$M$31,,)*$G73) -> 25600
C74: H200-8 | D74: 10 | E74: Faculty(*) | F74: =_xlfn.XLOOKUP($C74,'Power Blocks'!$C$20:$C$31,'Power Blocks'!$D$20:$D$31,,) -> GPU | G74: =IF(F74=" "," ",D74/_xlfn.XLOOKUP($C74,'Power Blocks'!$C$20:$C$31,'Power Blocks'!$I$20:$I$31,,)) -> 1 | H74: =IF(F74=" "," ",_xlfn.XLOOKUP($C74,'Power Blocks'!$C$20:$C$31,'Power Blocks'!$J$20:$J$31,,)*$G74) -> 0.1 | I74: =IF(F74=" "," ",_xlfn.XLOOKUP($C74,'Power Blocks'!$C$20:$C$31,'Power Blocks'!$K$20:$K$31,,)/1000*$G74) -> 2750 | J74: =IF(F74=" "," ",_xlfn.XLOOKUP($C74,'Power Blocks'!$C$20:$C$31,'Power Blocks'!$M$20:$M$31,,)*$G74) -> 80
C75: L40-8 | D75: 10 | E75: Faculty(*) | F75: =_xlfn.XLOOKUP($C75,'Power Blocks'!$C$20:$C$31,'Power Blocks'!$D$20:$D$31,,) -> GPU | G75: =IF(F75=" "," ",D75/_xlfn.XLOOKUP($C75,'Power Blocks'!$C$20:$C$31,'Power Blocks'!$I$20:$I$31,,)) -> 0.5 | H75: =IF(F75=" "," ",_xlfn.XLOOKUP($C75,'Power Blocks'!$C$20:$C$31,'Power Blocks'!$J$20:$J$31,,)*$G75) -> 0.05 | I75: =IF(F75=" "," ",_xlfn.XLOOKUP($C75,'Power Blocks'!$C$20:$C$31,'Power Blocks'!$K$20:$K$31,,)/1000*$G75) -> 613 | J75: =IF(F75=" "," ",_xlfn.XLOOKUP($C75,'Power Blocks'!$C$20:$C$31,'Power Blocks'!$M$20:$M$31,,)*$G75) -> 80
C76: H200-8 | D76: 8 | E76: ARCH-2(*) | F76: =_xlfn.XLOOKUP($C76,'Power Blocks'!$C$20:$C$31,'Power Blocks'!$D$20:$D$31,,) -> GPU | G76: =IF(F76=" "," ",D76/_xlfn.XLOOKUP($C76,'Power Blocks'!$C$20:$C$31,'Power Blocks'!$I$20:$I$31,,)) -> 0.8 | H76: =IF(F76=" "," ",_xlfn.XLOOKUP($C76,'Power Blocks'!$C$20:$C$31,'Power Blocks'!$J$20:$J$31,,)*$G76) -> 0.08 | I76: =IF(F76=" "," ",_xlfn.XLOOKUP($C76,'Power Blocks'!$C$20:$C$31,'Power Blocks'!$K$20:$K$31,,)/1000*$G76) -> 2200 | J76: =IF(F76=" "," ",_xlfn.XLOOKUP($C76,'Power Blocks'!$C$20:$C$31,'Power Blocks'!$M$20:$M$31,,)*$G76) -> 64
E78: faculty for row 68 are condos for start ups and others
C79: Need to model the schmidt purchase at every 6 months
C102: Bayview Quarterly CAPEX | K102: 2024 | L102: 2024.25 | M102: 2024.5 | N102: 2024.75 | O102: 2025 | P102: 2025.25 | Q102: =P102+0.25 -> 2025.5 | R102: =Q102+0.25 -> 2025.75 | S102: =R102+0.25 -> 2026 | T102: =S102+0.25 -> 2026.25 | U102: =T102+0.25 -> 2026.5 | V102: =U102+0.25 -> 2026.75 | W102: =V102+0.25 -> 2027 | X102: =W102+0.25 -> 2027.25 | ... AD102: =AC102+0.25 -> 2028.75
K103: =SUM(K106:K129) -> 0 | L103: =SUM(L106:L129) -> 0 | M103: =SUM(M106:M129) -> 5074.826 | N103: =SUM(N106:N129) -> 0 | O103: =SUM(O106:O129) -> 0 | P103: =SUM(P106:P129) -> 0 | Q103: =SUM(Q106:Q129) -> 6167.136 | R103: =SUM(R106:R129) -> 0 | ... AD103: =SUM(AD106:AD129) -> 0
C104: =C52 -> HPC1 | D104: =D52 -> 375 | E104: =E52 -> RockFish | F104: =F52 -> CPU | G104: =G52 -> 3.75 | H104: =H52 -> 0.375 | I104: =I52 -> 3750 | J104: =J52 -> 48000 | K104: =IF(AND(ISBLANK(K52),NOT(ISBLANK(L52))),$I52,0) -> 0 | L104: =IF(AND(ISBLANK(L52),NOT(ISBLANK(M52))),$I52,0) -> 0 | M104: =IF(AND(ISBLANK(M52),NOT(ISBLANK(N52))),$I52,0) -> 0 | N104: =IF(AND(ISBLANK(N52),NOT(ISBLANK(O52))),$I52,0) -> 0 | O104: =IF(AND(ISBLANK(O52),NOT(ISBLANK(P52))),$I52,0) -> 0 | P104: =IF(AND(ISBLANK(P52),NOT(ISBLANK(Q52))),$I52,0) -> 0 | Q104: =IF(AND(ISBLANK(Q52),NOT(ISBLANK(R52))),$I52,0) -> 0 | R104: =IF(AND(ISBLANK(R52),NOT(ISBLANK(S52))),$I52,0) -> 0 | ... AD104: =IF(AND(ISBLANK(AD52),NOT(ISBLANK(AE52))),$I52,0) -> 0
C105: =C53 -> V100-4 | D105: =D53 -> 31 | E105: =E53 -> ARCH | F105: =F53 -> GPU | G105: =G53 -> 1.55 | H105: =H53 -> 0.155 | I105: =I53 -> 620 | J105: =J53 -> 124 | K105: =IF(AND(ISBLANK(K53),NOT(ISBLANK(L53))),$I53,0) -> 0 | L105: =IF(AND(ISBLANK(L53),NOT(ISBLANK(M53))),$I53,0) -> 0 | M105: =IF(AND(ISBLANK(M53),NOT(ISBLANK(N53))),$I53,0) -> 0 | N105: =IF(AND(ISBLANK(N53),NOT(ISBLANK(O53))),$I53,0) -> 0 | O105: =IF(AND(ISBLANK(O53),NOT(ISBLANK(P53))),$I53,0) -> 0 | P105: =IF(AND(ISBLANK(P53),NOT(ISBLANK(Q53))),$I53,0) -> 0 | Q105: =IF(AND(ISBLANK(Q53),NOT(ISBLANK(R53))),$I53,0) -> 0 | R105: =IF(AND(ISBLANK(R53),NOT(ISBLANK(S53))),$I53,0) -> 0 | ... AD105: =IF(AND(ISBLANK(AD53),NOT(ISBLANK(AE53))),$I53,0) -> 0
C106: =C54 -> HDD | D106: =D54 -> 30 | E106: =E54 -> ARCH | F106: =F54 -> Hdisk | G106: =G54 -> 0.21428571 | H106: =H54 -> 0.021428571 | I106: =I54 -> 857.13 | J106: =J54 -> 15.9 | K106: =IF(AND(ISBLANK(K54),NOT(ISBLANK(L54))),$I54,0) -> 0 | L106: =IF(AND(ISBLANK(L54),NOT(ISBLANK(M54))),$I54,0) -> 0 | M106: =IF(AND(ISBLANK(M54),NOT(ISBLANK(N54))),$I54,0) -> 0 | N106: =IF(AND(ISBLANK(N54),NOT(ISBLANK(O54))),$I54,0) -> 0 | O106: =IF(AND(ISBLANK(O54),NOT(ISBLANK(P54))),$I54,0) -> 0 | P106: =IF(AND(ISBLANK(P54),NOT(ISBLANK(Q54))),$I54,0) -> 0 | Q106: =IF(AND(ISBLANK(Q54),NOT(ISBLANK(R54))),$I54,0) -> 0 | R106: =IF(AND(ISBLANK(R54),NOT(ISBLANK(S54))),$I54,0) -> 0 | ... AD106: =IF(AND(ISBLANK(AD54),NOT(ISBLANK(AE54))),$I54,0) -> 0
C107: =C55 -> SSD | D107: =D55 -> 4 | E107: =E55 -> ARCH | F107: =F55 -> Sdisk | G107: =G55 -> 0.032 | H107: =H55 -> 0.0032 | I107: =I55 -> 168 | J107: =J55 -> 1.2 | K107: =IF(AND(ISBLANK(K55),NOT(ISBLANK(L55))),$I55,0) -> 0 | L107: =IF(AND(ISBLANK(L55),NOT(ISBLANK(M55))),$I55,0) -> 0 | M107: =IF(AND(ISBLANK(M55),NOT(ISBLANK(N55))),$I55,0) -> 0 | N107: =IF(AND(ISBLANK(N55),NOT(ISBLANK(O55))),$I55,0) -> 0 | O107: =IF(AND(ISBLANK(O55),NOT(ISBLANK(P55))),$I55,0) -> 0 | P107: =IF(AND(ISBLANK(P55),NOT(ISBLANK(Q55))),$I55,0) -> 0 | Q107: =IF(AND(ISBLANK(Q55),NOT(ISBLANK(R55))),$I55,0) -> 0 | R107: =IF(AND(ISBLANK(R55),NOT(ISBLANK(S55))),$I55,0) -> 0 | ... AD107: =IF(AND(ISBLANK(AD55),NOT(ISBLANK(AE55))),$I55,0) -> 0
C108: =C56 -> L40-8 | D108: =D56 -> 4 | E108: =E56 -> ARCH | F108: =F56 -> GPU | G108: =G56 -> 0.2 | H108: =H56 -> 0.02 | I108: =I56 -> 245.2 | J108: =J56 -> 32 | K108: =IF(AND(ISBLANK(K56),NOT(ISBLANK(L56))),$I56,0) -> 0 | L108: =IF(AND(ISBLANK(L56),NOT(ISBLANK(M56))),$I56,0) -> 0 | M108: =IF(AND(ISBLANK(M56),NOT(ISBLANK(N56))),$I56,0) -> 0 | N108: =IF(AND(ISBLANK(N56),NOT(ISBLANK(O56))),$I56,0) -> 0 | O108: =IF(AND(ISBLANK(O56),NOT(ISBLANK(P56))),$I56,0) -> 0 | P108: =IF(AND(ISBLANK(P56),NOT(ISBLANK(Q56))),$I56,0) -> 0 | Q108: =IF(AND(ISBLANK(Q56),NOT(ISBLANK(R56))),$I56,0) -> 0 | R108: =IF(AND(ISBLANK(R56),NOT(ISBLANK(S56))),$I56,0) -> 0 | ... AD108: =IF(AND(ISBLANK(AD56),NOT(ISBLANK(AE56))),$I56,0) -> 0
C109: =C58 -> H100-4 | D109: =D58 -> 32 | E109: =E58 -> DSAI P1 | F109: =F58 -> GPU | G109: =G58 -> 2 | H109: =H58 -> 0.2 | I109: =I58 -> 3424 | J109: =J58 -> 128 | K109: =IF(AND(ISBLANK(K58),NOT(ISBLANK(L58))),$I58,0) -> 0 | L109: =IF(AND(ISBLANK(L58),NOT(ISBLANK(M58))),$I58,0) -> 0 | M109: =IF(AND(ISBLANK(M58),NOT(ISBLANK(N58))),$I58,0) -> 3424 | N109: =IF(AND(ISBLANK(N58),NOT(ISBLANK(O58))),$I58,0) -> 0 | O109: =IF(AND(ISBLANK(O58),NOT(ISBLANK(P58))),$I58,0) -> 0 | P109: =IF(AND(ISBLANK(P58),NOT(ISBLANK(Q58))),$I58,0) -> 0 | Q109: =IF(AND(ISBLANK(Q58),NOT(ISBLANK(R58))),$I58,0) -> 0 | R109: =IF(AND(ISBLANK(R58),NOT(ISBLANK(S58))),$I58,0) -> 0 | ... AD109: =IF(AND(ISBLANK(AD58),NOT(ISBLANK(AE58))),$I58,0) -> 0
C110: =C59 -> L40-8 | D110: =D59 -> 8 | E110: =E59 -> DSAI P1 | F110: =F59 -> GPU | G110: =G59 -> 0.4 | H110: =H59 -> 0.04 | I110: =I59 -> 490.4 | J110: =J59 -> 64 | K110: =IF(AND(ISBLANK(K59),NOT(ISBLANK(L59))),$I59,0) -> 0 | L110: =IF(AND(ISBLANK(L59),NOT(ISBLANK(M59))),$I59,0) -> 0 | M110: =IF(AND(ISBLANK(M59),NOT(ISBLANK(N59))),$I59,0) -> 490.4 | N110: =IF(AND(ISBLANK(N59),NOT(ISBLANK(O59))),$I59,0) -> 0 | O110: =IF(AND(ISBLANK(O59),NOT(ISBLANK(P59))),$I59,0) -> 0 | P110: =IF(AND(ISBLANK(P59),NOT(ISBLANK(Q59))),$I59,0) -> 0 | Q110: =IF(AND(ISBLANK(Q59),NOT(ISBLANK(R59))),$I59,0) -> 0 | R110: =IF(AND(ISBLANK(R59),NOT(ISBLANK(S59))),$I59,0) -> 0 | ... AD110: =IF(AND(ISBLANK(AD59),NOT(ISBLANK(AE59))),$I59,0) -> 0
C111: =C60 -> HPC1 | D111: =D60 -> 80 | E111: =E60 -> DSAI P1 | F111: =F60 -> CPU | G111: =G60 -> 0.8 | H111: =H60 -> 0.08 | I111: =I60 -> 800 | J111: =J60 -> 10240 | K111: =IF(AND(ISBLANK(K60),NOT(ISBLANK(L60))),$I60,0) -> 0 | L111: =IF(AND(ISBLANK(L60),NOT(ISBLANK(M60))),$I60,0) -> 0 | M111: =IF(AND(ISBLANK(M60),NOT(ISBLANK(N60))),$I60,0) -> 800 | N111: =IF(AND(ISBLANK(N60),NOT(ISBLANK(O60))),$I60,0) -> 0 | O111: =IF(AND(ISBLANK(O60),NOT(ISBLANK(P60))),$I60,0) -> 0 | P111: =IF(AND(ISBLANK(P60),NOT(ISBLANK(Q60))),$I60,0) -> 0 | Q111: =IF(AND(ISBLANK(Q60),NOT(ISBLANK(R60))),$I60,0) -> 0 | R111: =IF(AND(ISBLANK(R60),NOT(ISBLANK(S60))),$I60,0) -> 0 | ... AD111: =IF(AND(ISBLANK(AD60),NOT(ISBLANK(AE60))),$I60,0) -> 0
C112: =C61 -> HDD | D112: =D61 -> 6 | E112: =E61 -> DSAI P1 | F112: =F61 -> Hdisk | G112: =G61 -> 0.042857143 | H112: =H61 -> 0.0042857143 | I112: =I61 -> 171.426 | J112: =J61 -> 3.18 | K112: =IF(AND(ISBLANK(K61),NOT(ISBLANK(L61))),$I61,0) -> 0 | L112: =IF(AND(ISBLANK(L61),NOT(ISBLANK(M61))),$I61,0) -> 0 | M112: =IF(AND(ISBLANK(M61),NOT(ISBLANK(N61))),$I61,0) -> 171.426 | N112: =IF(AND(ISBLANK(N61),NOT(ISBLANK(O61))),$I61,0) -> 0 | O112: =IF(AND(ISBLANK(O61),NOT(ISBLANK(P61))),$I61,0) -> 0 | P112: =IF(AND(ISBLANK(P61),NOT(ISBLANK(Q61))),$I61,0) -> 0 | Q112: =IF(AND(ISBLANK(Q61),NOT(ISBLANK(R61))),$I61,0) -> 0 | R112: =IF(AND(ISBLANK(R61),NOT(ISBLANK(S61))),$I61,0) -> 0 | ... AD112: =IF(AND(ISBLANK(AD61),NOT(ISBLANK(AE61))),$I61,0) -> 0
C113: =C62 -> SSD | D113: =D62 -> 4.5 | E113: =E62 -> DSAI P1 | F113: =F62 -> Sdisk | G113: =G62 -> 0.036 | H113: =H62 -> 0.0036 | I113: =I62 -> 189 | J113: =J62 -> 1.35 | K113: =IF(AND(ISBLANK(K62),NOT(ISBLANK(L62))),$I62,0) -> 0 | L113: =IF(AND(ISBLANK(L62),NOT(ISBLANK(M62))),$I62,0) -> 0 | M113: =IF(AND(ISBLANK(M62),NOT(ISBLANK(N62))),$I62,0) -> 189 | N113: =IF(AND(ISBLANK(N62),NOT(ISBLANK(O62))),$I62,0) -> 0 | O113: =IF(AND(ISBLANK(O62),NOT(ISBLANK(P62))),$I62,0) -> 0 | P113: =IF(AND(ISBLANK(P62),NOT(ISBLANK(Q62))),$I62,0) -> 0 | Q113: =IF(AND(ISBLANK(Q62),NOT(ISBLANK(R62))),$I62,0) -> 0 | R113: =IF(AND(ISBLANK(R62),NOT(ISBLANK(S62))),$I62,0) -> 0 | ... AD113: =IF(AND(ISBLANK(AD62),NOT(ISBLANK(AE62))),$I62,0) -> 0
C114: =C63 -> H200-8 | D114: =D63 -> 8 | E114: =E63 -> Schmidt | F114: =F63 -> GPU | G114: =G63 -> 0.8 | H114: =H63 -> 0.08 | I114: =I63 -> 2200 | J114: =J63 -> 64 | K114: =IF(AND(ISBLANK(K63),NOT(ISBLANK(L63))),$I63,0) -> 0 | L114: =IF(AND(ISBLANK(L63),NOT(ISBLANK(M63))),$I63,0) -> 0 | M114: =IF(AND(ISBLANK(M63),NOT(ISBLANK(N63))),$I63,0) -> 0 | N114: =IF(AND(ISBLANK(N63),NOT(ISBLANK(O63))),$I63,0) -> 0 | O114: =IF(AND(ISBLANK(O63),NOT(ISBLANK(P63))),$I63,0) -> 0 | P114: =IF(AND(ISBLANK(P63),NOT(ISBLANK(Q63))),$I63,0) -> 0 | Q114: =IF(AND(ISBLANK(Q63),NOT(ISBLANK(R63))),$I63,0) -> 2200 | R114: =IF(AND(ISBLANK(R63),NOT(ISBLANK(S63))),$I63,0) -> 0 | ... AD114: =IF(AND(ISBLANK(AD63),NOT(ISBLANK(AE63))),$I63,0) -> 0
C115: =C63 -> H200-8 | D115: =D63 -> 8 | E115: =E63 -> Schmidt | F115: =F63 -> GPU | G115: =G63 -> 0.8 | H115: =H63 -> 0.08 | I115: =I63 -> 2200 | J115: =J63 -> 64 | K115: =IF(AND(ISBLANK(K63),NOT(ISBLANK(L63))),$I63,0) -> 0 | L115: =IF(AND(ISBLANK(L63),NOT(ISBLANK(M63))),$I63,0) -> 0 | M115: =IF(AND(ISBLANK(M63),NOT(ISBLANK(N63))),$I63,0) -> 0 | N115: =IF(AND(ISBLANK(N63),NOT(ISBLANK(O63))),$I63,0) -> 0 | O115: =IF(AND(ISBLANK(O63),NOT(ISBLANK(P63))),$I63,0) -> 0 | P115: =IF(AND(ISBLANK(P63),NOT(ISBLANK(Q63))),$I63,0) -> 0 | Q115: =IF(AND(ISBLANK(Q63),NOT(ISBLANK(R63))),$I63,0) -> 2200 | R115: =IF(AND(ISBLANK(R63),NOT(ISBLANK(S63))),$I63,0) -> 0 | ... AD115: =IF(AND(ISBLANK(AD63),NOT(ISBLANK(AE63))),$I63,0) -> 0
C116: =C64 -> HDD | D116: =D64 -> 16 | E116: =E64 -> Schmidt | F116: =F64 -> Hdisk | G116: =G64 -> 0.11428571 | H116: =H64 -> 0.011428571 | I116: =I64 -> 457.136 | J116: =J64 -> 8.48 | K116: =IF(AND(ISBLANK(K64),NOT(ISBLANK(L64))),$I64,0) -> 0 | L116: =IF(AND(ISBLANK(L64),NOT(ISBLANK(M64))),$I64,0) -> 0 | M116: =IF(AND(ISBLANK(M64),NOT(ISBLANK(N64))),$I64,0) -> 0 | N116: =IF(AND(ISBLANK(N64),NOT(ISBLANK(O64))),$I64,0) -> 0 | O116: =IF(AND(ISBLANK(O64),NOT(ISBLANK(P64))),$I64,0) -> 0 | P116: =IF(AND(ISBLANK(P64),NOT(ISBLANK(Q64))),$I64,0) -> 0 | Q116: =IF(AND(ISBLANK(Q64),NOT(ISBLANK(R64))),$I64,0) -> 457.136 | R116: =IF(AND(ISBLANK(R64),NOT(ISBLANK(S64))),$I64,0) -> 0 | ... AD116: =IF(AND(ISBLANK(AD64),NOT(ISBLANK(AE64))),$I64,0) -> 0
C117: =C65 -> SSD | D117: =D65 -> 5 | E117: =E65 -> Schmidt | F117: =F65 -> Sdisk | G117: =G65 -> 0.04 | H117: =H65 -> 0.004 | I117: =I65 -> 210 | J117: =J65 -> 1.5 | K117: =IF(AND(ISBLANK(K65),NOT(ISBLANK(L65))),$I65,0) -> 0 | L117: =IF(AND(ISBLANK(L65),NOT(ISBLANK(M65))),$I65,0) -> 0 | M117: =IF(AND(ISBLANK(M65),NOT(ISBLANK(N65))),$I65,0) -> 0 | N117: =IF(AND(ISBLANK(N65),NOT(ISBLANK(O65))),$I65,0) -> 0 | O117: =IF(AND(ISBLANK(O65),NOT(ISBLANK(P65))),$I65,0) -> 0 | P117: =IF(AND(ISBLANK(P65),NOT(ISBLANK(Q65))),$I65,0) -> 0 | Q117: =IF(AND(ISBLANK(Q65),NOT(ISBLANK(R65))),$I65,0) -> 210 | R117: =IF(AND(ISBLANK(R65),NOT(ISBLANK(S65))),$I65,0) -> 0 | ... AD117: =IF(AND(ISBLANK(AD65),NOT(ISBLANK(AE65))),$I65,0) -> 0
C118: =C66 -> H200-8 | E118: =E66 -> Schmidt | F118: =F66 -> GPU | G118: =G66 -> 0.4 | H118: =H66 -> 0.04 | I118: =I66 -> 1100 | J118: =J66 -> 32 | K118: =IF(AND(ISBLANK(K66),NOT(ISBLANK(L66))),$I66,0) -> 0 | L118: =IF(AND(ISBLANK(L66),NOT(ISBLANK(M66))),$I66,0) -> 0 | M118: =IF(AND(ISBLANK(M66),NOT(ISBLANK(N66))),$I66,0) -> 0 | N118: =IF(AND(ISBLANK(N66),NOT(ISBLANK(O66))),$I66,0) -> 0 | O118: =IF(AND(ISBLANK(O66),NOT(ISBLANK(P66))),$I66,0) -> 0 | P118: =IF(AND(ISBLANK(P66),NOT(ISBLANK(Q66))),$I66,0) -> 0 | Q118: =IF(AND(ISBLANK(Q66),NOT(ISBLANK(R66))),$I66,0) -> 1100 | R118: =IF(AND(ISBLANK(R66),NOT(ISBLANK(S66))),$I66,0) -> 0 | ... AD118: =IF(AND(ISBLANK(AD66),NOT(ISBLANK(AE66))),$I66,0) -> 0
C119: =C67 -> HPC1 | D119: =D67 -> 0 | E119: =E67 -> 0 | F119: =F67 -> CPU | G119: =G67 -> 0 | H119: =H67 -> 0 | I119: =I67 -> 0 | J119: =J67 -> 0 | K119: =IF(AND(ISBLANK(K67),NOT(ISBLANK(L67))),$I67,0) -> 0 | L119: =IF(AND(ISBLANK(L67),NOT(ISBLANK(M67))),$I67,0) -> 0 | M119: =IF(AND(ISBLANK(M67),NOT(ISBLANK(N67))),$I67,0) -> 0 | N119: =IF(AND(ISBLANK(N67),NOT(ISBLANK(O67))),$I67,0) -> 0 | O119: =IF(AND(ISBLANK(O67),NOT(ISBLANK(P67))),$I67,0) -> 0 | P119: =IF(AND(ISBLANK(P67),NOT(ISBLANK(Q67))),$I67,0) -> 0 | Q119: =IF(AND(ISBLANK(Q67),NOT(ISBLANK(R67))),$I67,0) -> 0 | R119: =IF(AND(ISBLANK(R67),NOT(ISBLANK(S67))),$I67,0) -> 0 | ... AD119: =IF(AND(ISBLANK(AD67),NOT(ISBLANK(AE67))),$I67,0) -> 0
C120: =C68 -> -- | D120: =D68 -> 0 | E120: =E68 -> 0 | F120: =F68 | G120: =G68 | H120: =H68 | I120: =I68 | J120: =J68 | K120: =IF(AND(ISBLANK(K68),NOT(ISBLANK(L68))),$I68,0) -> 0 | L120: =IF(AND(ISBLANK(L68),NOT(ISBLANK(M68))),$I68,0) -> 0 | M120: =IF(AND(ISBLANK(M68),NOT(ISBLANK(N68))),$I68,0) -> 0 | N120: =IF(AND(ISBLANK(N68),NOT(ISBLANK(O68))),$I68,0) -> 0 | O120: =IF(AND(ISBLANK(O68),NOT(ISBLANK(P68))),$I68,0) -> 0 | P120: =IF(AND(ISBLANK(P68),NOT(ISBLANK(Q68))),$I68,0) -> 0 | Q120: =IF(AND(ISBLANK(Q68),NOT(ISBLANK(R68))),$I68,0) -> 0 | R120: =IF(AND(ISBLANK(R68),NOT(ISBLANK(S68))),$I68,0) | ... AD120: =IF(AND(ISBLANK(AD68),NOT(ISBLANK(AE68))),$I68,0) -> 0
C121: =C69 -> -- | D121: =D69 -> 0 | E121: =E69 -> 0 | F121: =F69 | G121: =G69 | H121: =H69 | I121: =I69 | J121: =J69 | K121: =IF(AND(ISBLANK(K69),NOT(ISBLANK(L69))),$I69,0) -> 0 | L121: =IF(AND(ISBLANK(L69),NOT(ISBLANK(M69))),$I69,0) -> 0 | M121: =IF(AND(ISBLANK(M69),NOT(ISBLANK(N69))),$I69,0) -> 0 | N121: =IF(AND(ISBLANK(N69),NOT(ISBLANK(O69))),$I69,0) -> 0 | O121: =IF(AND(ISBLANK(O69),NOT(ISBLANK(P69))),$I69,0) -> 0 | P121: =IF(AND(ISBLANK(P69),NOT(ISBLANK(Q69))),$I69,0) -> 0 | Q121: =IF(AND(ISBLANK(Q69),NOT(ISBLANK(R69))),$I69,0) -> 0 | R121: =IF(AND(ISBLANK(R69),NOT(ISBLANK(S69))),$I69,0) | ... AD121: =IF(AND(ISBLANK(AD69),NOT(ISBLANK(AE69))),$I69,0) -> 0
C122: =C70 -> -- | D122: =D70 -> 0 | E122: =E70 -> 0 | F122: =F70 | G122: =G70 | H122: =H70 | I122: =I70 | J122: =J70 | K122: =IF(AND(ISBLANK(K70),NOT(ISBLANK(L70))),$I70,0) -> 0 | L122: =IF(AND(ISBLANK(L70),NOT(ISBLANK(M70))),$I70,0) -> 0 | M122: =IF(AND(ISBLANK(M70),NOT(ISBLANK(N70))),$I70,0) -> 0 | N122: =IF(AND(ISBLANK(N70),NOT(ISBLANK(O70))),$I70,0) -> 0 | O122: =IF(AND(ISBLANK(O70),NOT(ISBLANK(P70))),$I70,0) -> 0 | P122: =IF(AND(ISBLANK(P70),NOT(ISBLANK(Q70))),$I70,0) -> 0 | Q122: =IF(AND(ISBLANK(Q70),NOT(ISBLANK(R70))),$I70,0) -> 0 | R122: =IF(AND(ISBLANK(R70),NOT(ISBLANK(S70))),$I70,0) | ... AD122: =IF(AND(ISBLANK(AD70),NOT(ISBLANK(AE70))),$I70,0) -> 0
C123: =C71 -> -- | D123: =D71 | E123: =E71 -> 0 | F123: =F71 | G123: =G71 | H123: =H71 | I123: =I71 | J123: =J71 | K123: =IF(AND(ISBLANK(K71),NOT(ISBLANK(L71))),$I71,0) -> 0 | L123: =IF(AND(ISBLANK(L71),NOT(ISBLANK(M71))),$I71,0) -> 0 | M123: =IF(AND(ISBLANK(M71),NOT(ISBLANK(N71))),$I71,0) -> 0 | N123: =IF(AND(ISBLANK(N71),NOT(ISBLANK(O71))),$I71,0) -> 0 | O123: =IF(AND(ISBLANK(O71),NOT(ISBLANK(P71))),$I71,0) -> 0 | P123: =IF(AND(ISBLANK(P71),NOT(ISBLANK(Q71))),$I71,0) -> 0 | Q123: =IF(AND(ISBLANK(Q71),NOT(ISBLANK(R71))),$I71,0) -> 0 | R123: =IF(AND(ISBLANK(R71),NOT(ISBLANK(S71))),$I71,0) -> 0 | ... AD123: =IF(AND(ISBLANK(AD71),NOT(ISBLANK(AE71))),$I71,0) -> 0
C124: =C72 -> -- | D124: =D72 | E124: =E72 | F124: =F72 | G124: =G72 | H124: =H72 | I124: =I72 | J124: =J72 | K124: =IF(AND(ISBLANK(K72),NOT(ISBLANK(L72))),$I72,0) -> 0 | L124: =IF(AND(ISBLANK(L72),NOT(ISBLANK(M72))),$I72,0) -> 0 | M124: =IF(AND(ISBLANK(M72),NOT(ISBLANK(N72))),$I72,0) -> 0 | N124: =IF(AND(ISBLANK(N72),NOT(ISBLANK(O72))),$I72,0) -> 0 | O124: =IF(AND(ISBLANK(O72),NOT(ISBLANK(P72))),$I72,0) -> 0 | P124: =IF(AND(ISBLANK(P72),NOT(ISBLANK(Q72))),$I72,0) -> 0 | Q124: =IF(AND(ISBLANK(Q72),NOT(ISBLANK(R72))),$I72,0) -> 0 | R124: =IF(AND(ISBLANK(R72),NOT(ISBLANK(S72))),$I72,0) -> 0 | ... AD124: =IF(AND(ISBLANK(AD72),NOT(ISBLANK(AE72))),$I72,0) -> 0
C125: =C73 -> HPC1 | D125: =D73 -> 200 | E125: =E73 -> ARCH-2(*) | F125: =F73 -> CPU | G125: =G73 -> 2 | H125: =H73 -> 0.2 | I125: =I73 -> 2000 | J125: =J73 -> 25600 | K125: =IF(AND(ISBLANK(K73),NOT(ISBLANK(L73))),$I73,0) -> 0 | L125: =IF(AND(ISBLANK(L73),NOT(ISBLANK(M73))),$I73,0) -> 0 | M125: =IF(AND(ISBLANK(M73),NOT(ISBLANK(N73))),$I73,0) -> 0 | N125: =IF(AND(ISBLANK(N73),NOT(ISBLANK(O73))),$I73,0) -> 0 | O125: =IF(AND(ISBLANK(O73),NOT(ISBLANK(P73))),$I73,0) -> 0 | P125: =IF(AND(ISBLANK(P73),NOT(ISBLANK(Q73))),$I73,0) -> 0 | Q125: =IF(AND(ISBLANK(Q73),NOT(ISBLANK(R73))),$I73,0) -> 0 | R125: =IF(AND(ISBLANK(R73),NOT(ISBLANK(S73))),$I73,0) -> 0 | ... AD125: =IF(AND(ISBLANK(AD73),NOT(ISBLANK(AE73))),$I73,0) -> 0
...

Sheet Mt.Wash
AU1: created for stair plot
AU2: Used
AU3: year | AV3: MW | AW3: adjusted
AU4: 2024 | AV4: =HLOOKUP(AU4,$K$47:$AD$48,2) -> 0.598 | AW4: =HLOOKUP($AU4,$K$45:$AD$46,2) -> 0.098
AU5: 2024.25 | AV5: =AV4 -> 0.598 | AW5: =AW4 -> 0.098
AU6: 2024.25 | AV6: =HLOOKUP(AU6,$K$47:$AD$48,2) -> 0.598 | AW6: =HLOOKUP($AU6,$K$45:$AD$46,2) -> 0.098
AU7: 2024.5 | AV7: =AV6 -> 0.598 | AW7: =AW6 -> 0.098
AU8: 2024.5 | AV8: =HLOOKUP(AU8,$K$47:$AD$48,2) -> 0.74942857 | AW8: =HLOOKUP($AU8,$K$45:$AD$46,2) -> 0.24942857
AU9: 2024.75 | AV9: =AV8 -> 0.74942857 | AW9: =AW8 -> 0.24942857
AU10: 2024.75 | AV10: =HLOOKUP(AU10,$K$47:$AD$48,2) -> 0.74942857 | AW10: =HLOOKUP($AU10,$K$45:$AD$46,2) -> 0.24942857
N11: adjusted - something in our budget - to estimate for DSAI and other purchases | AU11: 2025 | AV11: =AV10 -> 0.74942857 | AW11: =AW10 -> 0.24942857
AU12: 2025 | AV12: =HLOOKUP(AU12,$K$47:$AD$48,2) -> 0.74942857 | AW12: =HLOOKUP($AU12,$K$45:$AD$46,2) -> 0.24942857
AU13: 2025.25 | AV13: =AV12 -> 0.74942857 | AW13: =AW12 -> 0.24942857
AU14: 2025.25 | AV14: =HLOOKUP(AU14,$K$47:$AD$48,2) -> 0.74942857 | AW14: =HLOOKUP($AU14,$K$45:$AD$46,2) -> 0.24942857
AU15: 2025.5 | AV15: =AV14 -> 0.74942857 | AW15: =AW14 -> 0.24942857
AU16: 2025.5 | AV16: =HLOOKUP(AU16,$K$47:$AD$48,2) -> 0.74942857 | AW16: =HLOOKUP($AU16,$K$45:$AD$46,2) -> 0.24942857
AU17: 2025.75 | AV17: =AV16 -> 0.74942857 | AW17: =AW16 -> 0.24942857
AU18: 2025.75 | AV18: =HLOOKUP(AU18,$K$47:$AD$48,2) -> 0.83514286 | AW18: =HLOOKUP($AU18,$K$45:$AD$46,2) -> 0.33514286
AU19: 2026 | AV19: =AV18 -> 0.83514286 | AW19: =AW18 -> 0.33514286
AU20: 2026 | AV20: =HLOOKUP(AU20,$K$47:$AD$48,2) -> 0.83514286 | AW20: =HLOOKUP($AU20,$K$45:$AD$46,2) -> 0.33514286
AU21: 2026.25 | AV21: =AV20 -> 0.83514286 | AW21: =AW20 -> 0.33514286
AU22: 2026.25 | AV22: =HLOOKUP(AU22,$K$47:$AD$48,2) -> 0.83514286 | AW22: =HLOOKUP($AU22,$K$45:$AD$46,2) -> 0.33514286
AU23: 2026.5 | AV23: =AV22 -> 0.83514286 | AW23: =AW22 -> 0.33514286
AU24: 2026.5 | AV24: =HLOOKUP(AU24,$K$47:$AD$48,2) -> 0.83514286 | AW24: =HLOOKUP($AU24,$K$45:$AD$46,2) -> 0.33514286
AU25: 2026.75 | AV25: =AV24 -> 0.83514286 | AW25: =AW24 -> 0.33514286
AU26: 2026.75 | AV26: =HLOOKUP(AU26,$K$47:$AD$48,2) -> 0.83514286 | AW26: =HLOOKUP($AU26,$K$45:$AD$46,2) -> 0.33514286
AU27: 2027 | AV27: =AV26 -> 0.83514286 | AW27: =AW26 -> 0.33514286
AU28: 2027 | AV28: =HLOOKUP(AU28,$K$47:$AD$48,2) -> 0.83514286 | AW28: =HLOOKUP($AU28,$K$45:$AD$46,2) -> 0.33514286
AU29: 2027.25 | AV29: =AV28 -> 0.83514286 | AW29: =AW28 -> 0.33514286
AU30: 2027.25 | AV30: =HLOOKUP(AU30,$K$47:$AD$48,2) -> 0.33514286 | AW30: =HLOOKUP($AU30,$K$45:$AD$46,2) -> 0.33514286
AU31: 2027.5 | AV31: =AV30 -> 0.33514286 | AW31: =AW30 -> 0.33514286
AU32: 2027.5 | AV32: =HLOOKUP(AU32,$K$47:$AD$48,2) -> 0.33514286 | AW32: =HLOOKUP($AU32,$K$45:$AD$46,2) -> 0.33514286
AU33: 2027.75 | AV33: =AV32 -> 0.33514286 | AW33: =AW32 -> 0.33514286
AU34: 2027.75 | AV34: =HLOOKUP(AU34,$K$47:$AD$48,2) -> 0.33514286 | AW34: =HLOOKUP($AU34,$K$45:$AD$46,2) -> 0.33514286
AU35: 2028 | AV35: =AV34 -> 0.33514286 | AW35: =AW34 -> 0.33514286
AU36: 2028 | AV36: =HLOOKUP(AU36,$K$47:$AD$48,2) -> 0.33514286 | AW36: =HLOOKUP($AU36,$K$45:$AD$46,2) -> 0.33514286
AU37: 2028.25 | AV37: =AV36 -> 0.33514286 | AW37: =AW36 -> 0.33514286
AU38: 2028.25 | AV38: =HLOOKUP(AU38,$K$47:$AD$48,2) -> 0.33514286 | AW38: =HLOOKUP($AU38,$K$45:$AD$46,2) -> 0.33514286
AU39: 2028.5 | AV39: =AV38 -> 0.33514286 | AW39: =AW38 -> 0.33514286
AU40: 2028.5 | AV40: =HLOOKUP(AU40,$K$47:$AD$48,2) -> 0.33514286 | AW40: =HLOOKUP($AU40,$K$45:$AD$46,2) -> 0.33514286
AU41: 2028.75 | AV41: =AV40 -> 0.33514286 | AW41: =AW40 -> 0.33514286
AU42: 2028.75 | AV42: =HLOOKUP(AU42,$K$47:$AD$48,2) -> 0.33514286 | AW42: =HLOOKUP($AU42,$K$45:$AD$46,2) -> 0.33514286
K45: 2024 | L45: 2024.25 | M45: 2024.5 | N45: 2024.75 | O45: 2025 | P45: 2025.25 | Q45: =P45+0.25 -> 2025.5 | R45: =Q45+0.25 -> 2025.75 | S45: =R45+0.25 -> 2026 | T45: =S45+0.25 -> 2026.25 | U45: =T45+0.25 -> 2026.5 | V45: =U45+0.25 -> 2026.75 | W45: =V45+0.25 -> 2027 | X45: =W45+0.25 -> 2027.25 | ... AD45: =AC45+0.25 -> 2028.75
J46: adjusted | K46: =K48-K51 -> 0.098 | L46: =L48-L51 -> 0.098 | M46: =M48-M51 -> 0.24942857 | N46: =N48-N51 -> 0.24942857 | O46: =O48-O51 -> 0.24942857 | P46: =P48-P51 -> 0.24942857 | Q46: =Q48-Q51 -> 0.24942857 | R46: =R48-R51 -> 0.33514286 | ... AD46: =AD48-AD51 -> 0.33514286
C47: Mt. Washington | J47: POWER USE [MW] | K47: 2024 | L47: 2024.25 | M47: 2024.5 | N47: 2024.75 | O47: 2025 | P47: 2025.25 | Q47: =P47+0.25 -> 2025.5 | R47: =Q47+0.25 -> 2025.75 | S47: =R47+0.25 -> 2026 | T47: =S47+0.25 -> 2026.25 | U47: =T47+0.25 -> 2026.5 | V47: =U47+0.25 -> 2026.75 | W47: =V47+0.25 -> 2027 | X47: =W47+0.25 -> 2027.25 | ... AD47: =AC47+0.25 -> 2028.75
K48: =SUM(K51:K74) -> 0.598 | L48: =SUM(L51:L74) -> 0.598 | M48: =SUM(M51:M74) -> 0.74942857 | N48: =SUM(N51:N74) -> 0.74942857 | O48: =SUM(O51:O74) -> 0.74942857 | P48: =SUM(P51:P74) -> 0.74942857 | Q48: =SUM(Q51:Q74) -> 0.74942857 | R48: =SUM(R51:R74) -> 0.83514286 | ... AD48: =SUM(AD51:AD74) -> 0.33514286
C49: INPUT | F49: LOOKUP
C50: category | D50: units | E50: project | F50: type | G50: blocks | H50: MW | I50: $K | J50: quantity | K50: 2024 | O50: 2025 | S50: 2026 | W50: 2027 | AA50: 2028
C51: HPC1 | D51: 500 | E51: Enterprise | F51: IT | G51: =IF(F51=" "," ",D51/_xlfn.XLOOKUP($C51,'Power Blocks'!$C$20:$C$31,'Power Blocks'!$I$20:$I$31,,)) -> 5 | H51: =IF(F51=" "," ",_xlfn.XLOOKUP($C51,'Power Blocks'!$C$20:$C$31,'Power Blocks'!$J$20:$J$31,,)*$G51) -> 0.5 | I51: =IF(F51=" "," ",_xlfn.XLOOKUP($C51,'Power Blocks'!$C$20:$C$31,'Power Blocks'!$K$20:$K$31,,)/1000*$G51) -> 5000 | J51: 0 | K51: =$H51 -> 0.5 | L51: =$H51 -> 0.5 | M51: =$H51 -> 0.5 | N51: =$H51 -> 0.5 | O51: =$H51 -> 0.5 | P51: =$H51 -> 0.5 | Q51: =$H51 -> 0.5 | R51: =$H51 -> 0.5 | ... W51: =$H51 -> 0.5 | AF51: (*) Existing equipment updated 2024-12-4
C52: HPC1 | D52: 38 | E52: Discovery | F52: =_xlfn.XLOOKUP($C52,'Power Blocks'!$C$20:$C$31,'Power Blocks'!$D$20:$D$31,,) -> CPU | G52: =IF(F52=" "," ",D52/_xlfn.XLOOKUP($C52,'Power Blocks'!$C$20:$C$31,'Power Blocks'!$I$20:$I$31,,)) -> 0.38 | H52: =IF(F52=" "," ",_xlfn.XLOOKUP($C52,'Power Blocks'!$C$20:$C$31,'Power Blocks'!$J$20:$J$31,,)*$G52) -> 0.038 | I52: =IF(F52=" "," ",_xlfn.XLOOKUP($C52,'Power Blocks'!$C$20:$C$31,'Power Blocks'!$K$20:$K$31,,)/1000*$G52) -> 380 | J52: =IF(F52=" "," ",_xlfn.XLOOKUP($C52,'Power Blocks'!$C$20:$C$31,'Power Blocks'!$M$20:$M$31,,)*$G52) -> 4864 | K52: =$H52 -> 0.038 | L52: =$H52 -> 0.038 | M52: =$H52 -> 0.038 | N52: =$H52 -> 0.038 | O52: =$H52 -> 0.038 | P52: =$H52 -> 0.038 | Q52: =$H52 -> 0.038 | R52: =$H52 -> 0.038 | ... AD52: =$H52 -> 0.038 | AF52: (*) following email from Pat Pflaumer
C53: HDD | D53: 28 | E53: Research | F53: =_xlfn.XLOOKUP($C53,'Power Blocks'!$C$20:$C$31,'Power Blocks'!$D$20:$D$31,,) -> Hdisk | G53: =IF(F53=" "," ",D53/_xlfn.XLOOKUP($C53,'Power Blocks'!$C$20:$C$31,'Power Blocks'!$I$20:$I$31,,)) -> 0.2 | H53: 0.06 | I53: =IF(F53=" "," ",_xlfn.XLOOKUP($C53,'Power Blocks'!$C$20:$C$31,'Power Blocks'!$K$20:$K$31,,)/1000*$G53) -> 799.988 | J53: =IF(F53=" "," ",_xlfn.XLOOKUP($C53,'Power Blocks'!$C$20:$C$31,'Power Blocks'!$M$20:$M$31,,)*$G53) -> 14.84 | K53: =$H53 -> 0.06 | L53: =$H53 -> 0.06 | M53: =$H53 -> 0.06 | N53: =$H53 -> 0.06 | O53: =$H53 -> 0.06 | P53: =$H53 -> 0.06 | Q53: =$H53 -> 0.06 | R53: =$H53 -> 0.06 | ... AD53: =$H53 -> 0.06
C54: HPC1 | D54: 40 | E54: DSAI P1 | F54: =_xlfn.XLOOKUP($C54,'Power Blocks'!$C$20:$C$31,'Power Blocks'!$D$20:$D$31,,) -> CPU | G54: =IF(F54=" "," ",D54/_xlfn.XLOOKUP($C54,'Power Blocks'!$C$20:$C$31,'Power Blocks'!$I$20:$I$31,,)) -> 0.4 | H54: =IF(F54=" "," ",_xlfn.XLOOKUP($C54,'Power Blocks'!$C$20:$C$31,'Power Blocks'!$J$20:$J$31,,)*$G54) -> 0.04 | I54: =IF(F54=" "," ",_xlfn.XLOOKUP($C54,'Power Blocks'!$C$20:$C$31,'Power Blocks'!$K$20:$K$31,,)/1000*$G54) -> 400 | J54: =IF(F54=" "," ",_xlfn.XLOOKUP($C54,'Power Blocks'!$C$20:$C$31,'Power Blocks'!$M$20:$M$31,,)*$G54) -> 5120 | M54: =$H54 -> 0.04 | N54: =$H54 -> 0.04 | O54: =$H54 -> 0.04 | P54: =$H54 -> 0.04 | Q54: =$H54 -> 0.04 | R54: =$H54 -> 0.04 | S54: =$H54 -> 0.04 | T54: =$H54 -> 0.04 | ... AD54: =$H54 -> 0.04
C55: H100-4 | D55: 16 | E55: DSAI P1 | F55: =_xlfn.XLOOKUP($C55,'Power Blocks'!$C$20:$C$31,'Power Blocks'!$D$20:$D$31,,) -> GPU | G55: =IF(F55=" "," ",D55/_xlfn.XLOOKUP($C55,'Power Blocks'!$C$20:$C$31,'Power Blocks'!$I$20:$I$31,,)) -> 1 | H55: =IF(F55=" "," ",_xlfn.XLOOKUP($C55,'Power Blocks'!$C$20:$C$31,'Power Blocks'!$J$20:$J$31,,)*$G55) -> 0.1 | I55: =IF(F55=" "," ",_xlfn.XLOOKUP($C55,'Power Blocks'!$C$20:$C$31,'Power Blocks'!$K$20:$K$31,,)/1000*$G55) -> 1712 | J55: =IF(F55=" "," ",_xlfn.XLOOKUP($C55,'Power Blocks'!$C$20:$C$31,'Power Blocks'!$M$20:$M$31,,)*$G55) -> 64 | M55: =$H55 -> 0.1 | N55: =$H55 -> 0.1 | O55: =$H55 -> 0.1 | P55: =$H55 -> 0.1 | Q55: =$H55 -> 0.1 | R55: =$H55 -> 0.1 | S55: =$H55 -> 0.1 | T55: =$H55 -> 0.1 | ... AD55: =$H55 -> 0.1
C56: HDD | D56: 16 | E56: DSAI P1 | F56: =_xlfn.XLOOKUP($C56,'Power Blocks'!$C$20:$C$31,'Power Blocks'!$D$20:$D$31,,) -> Hdisk | G56: =IF(F56=" "," ",D56/_xlfn.XLOOKUP($C56,'Power Blocks'!$C$20:$C$31,'Power Blocks'!$I$20:$I$31,,)) -> 0.11428571 | H56: =IF(F56=" "," ",_xlfn.XLOOKUP($C56,'Power Blocks'!$C$20:$C$31,'Power Blocks'!$J$20:$J$31,,)*$G56) -> 0.011428571 | I56: =IF(F56=" "," ",_xlfn.XLOOKUP($C56,'Power Blocks'!$C$20:$C$31,'Power Blocks'!$K$20:$K$31,,)/1000*$G56) -> 457.136 | J56: =IF(F56=" "," ",_xlfn.XLOOKUP($C56,'Power Blocks'!$C$20:$C$31,'Power Blocks'!$M$20:$M$31,,)*$G56) -> 8.48 | M56: =$H56 -> 0.011428571 | N56: =$H56 -> 0.011428571 | O56: =$H56 -> 0.011428571 | P56: =$H56 -> 0.011428571 | Q56: =$H56 -> 0.011428571 | R56: =$H56 -> 0.011428571 | S56: =$H56 -> 0.011428571 | T56: =$H56 -> 0.011428571 | ... AD56: =$H56 -> 0.011428571
C57: HDD | D57: 120 | E57: DSAI P2 | F57: =_xlfn.XLOOKUP($C57,'Power Blocks'!$C$20:$C$31,'Power Blocks'!$D$20:$D$31,,) -> Hdisk | G57: =IF(F57=" "," ",D57/_xlfn.XLOOKUP($C57,'Power Blocks'!$C$20:$C$31,'Power Blocks'!$I$20:$I$31,,)) -> 0.85714286 | H57: =IF(F57=" "," ",_xlfn.XLOOKUP($C57,'Power Blocks'!$C$20:$C$31,'Power Blocks'!$J$20:$J$31,,)*$G57) -> 0.085714286 | I57: =IF(F57=" "," ",_xlfn.XLOOKUP($C57,'Power Blocks'!$C$20:$C$31,'Power Blocks'!$K$20:$K$31,,)/1000*$G57) -> 3428.52 | J57: =IF(F57=" "," ",_xlfn.XLOOKUP($C57,'Power Blocks'!$C$20:$C$31,'Power Blocks'!$M$20:$M$31,,)*$G57) -> 63.6 | R57: =$H57 -> 0.085714286 | S57: =$H57 -> 0.085714286 | T57: =$H57 -> 0.085714286 | U57: =$H57 -> 0.085714286 | V57: =$H57 -> 0.085714286 | W57: =$H57 -> 0.085714286 | X57: =$H57 -> 0.085714286 | Y57: =$H57 -> 0.085714286 | ... AD57: =$H57 -> 0.085714286
C58: -- | F58: =_xlfn.XLOOKUP($C58,'Power Blocks'!$C$20:$C$31,'Power Blocks'!$D$20:$D$31,,) | G58: =IF(F58=" "," ",D58/_xlfn.XLOOKUP($C58,'Power Blocks'!$C$20:$C$31,'Power Blocks'!$I$20:$I$31,,)) | H58: =IF(F58=" "," ",_xlfn.XLOOKUP($C58,'Power Blocks'!$C$20:$C$31,'Power Blocks'!$J$20:$J$31,,)*$G58) | I58: =IF(F58=" "," ",_xlfn.XLOOKUP($C58,'Power Blocks'!$C$20:$C$31,'Power Blocks'!$K$20:$K$31,,)/1000*$G58) | J58: =IF(F58=" "," ",_xlfn.XLOOKUP($C58,'Power Blocks'!$C$20:$C$31,'Power Blocks'!$M$20:$M$31,,)*$G58) | N58: =$H58 | O58: =$H58 | P58: =$H58 | Q58: =$H58 | R58: =$H58 | S58: =$H58 | T58: =$H58 | U58: =$H58 | ... AB58: =$H58
C59: -- | F59: =_xlfn.XLOOKUP($C59,'Power Blocks'!$C$20:$C$31,'Power Blocks'!$D$20:$D$31,,) | G59: =IF(F59=" "," ",D59/_xlfn.XLOOKUP($C59,'Power Blocks'!$C$20:$C$31,'Power Blocks'!$I$20:$I$31,,)) | H59: =IF(F59=" "," ",_xlfn.XLOOKUP($C59,'Power Blocks'!$C$20:$C$31,'Power Blocks'!$J$20:$J$31,,)*$G59) | I59: =IF(F59=" "," ",_xlfn.XLOOKUP($C59,'Power Blocks'!$C$20:$C$31,'Power Blocks'!$K$20:$K$31,,)/1000*$G59) | J59: =IF(F59=" "," ",_xlfn.XLOOKUP($C59,'Power Blocks'!$C$20:$C$31,'Power Blocks'!$M$20:$M$31,,)*$G59) | N59: =$H59 | O59: =$H59 | P59: =$H59 | Q59: =$H59 | R59: =$H59 | S59: =$H59 | T59: =$H59 | U59: =$H59 | ... X59: =$H59
C60: -- | F60: =_xlfn.XLOOKUP($C60,'Power Blocks'!$C$20:$C$31,'Power Blocks'!$D$20:$D$31,,) | G60: =IF(F60=" "," ",D60/_xlfn.XLOOKUP($C60,'Power Blocks'!$C$20:$C$31,'Power Blocks'!$I$20:$I$31,,)) | H60: =IF(F60=" "," ",_xlfn.XLOOKUP($C60,'Power Blocks'!$C$20:$C$31,'Power Blocks'!$J$20:$J$31,,)*$G60) | I60: =IF(F60=" "," ",_xlfn.XLOOKUP($C60,'Power Blocks'!$C$20:$C$31,'Power Blocks'!$K$20:$K$31,,)/1000*$G60) | J60: =IF(F60=" "," ",_xlfn.XLOOKUP($C60,'Power Blocks'!$C$20:$C$31,'Power Blocks'!$M$20:$M$31,,)*$G60) | N60: =$H60 | O60: =$H60 | P60: =$H60 | Q60: =$H60 | R60: =$H60 | S60: =$H60 | T60: =$H60 | U60: =$H60 | ... X60: =$H60
C61: -- | F61: =_xlfn.XLOOKUP($C61,'Power Blocks'!$C$20:$C$31,'Power Blocks'!$D$20:$D$31,,) | G61: =IF(F61=" "," ",D61/_xlfn.XLOOKUP($C61,'Power Blocks'!$C$20:$C$31,'Power Blocks'!$I$20:$I$31,,)) | H61: =IF(F61=" "," ",_xlfn.XLOOKUP($C61,'Power Blocks'!$C$20:$C$31,'Power Blocks'!$J$20:$J$31,,)*$G61) | I61: =IF(F61=" "," ",_xlfn.XLOOKUP($C61,'Power Blocks'!$C$20:$C$31,'Power Blocks'!$K$20:$K$31,,)/1000*$G61) | J61: =IF(F61=" "," ",_xlfn.XLOOKUP($C61,'Power Blocks'!$C$20:$C$31,'Power Blocks'!$M$20:$M$31,,)*$G61) | Q61: =$H61 | R61: =$H61 | S61: =$H61 | T61: =$H61 | U61: =$H61 | V61: =$H61 | W61: =$H61 | X61: =$H61 | ... Z61: =$H61
C62: -- | F62: =_xlfn.XLOOKUP($C62,'Power Blocks'!$C$20:$C$31,'Power Blocks'!$D$20:$D$31,,) | G62: =IF(F62=" "," ",D62/_xlfn.XLOOKUP($C62,'Power Blocks'!$C$20:$C$31,'Power Blocks'!$I$20:$I$31,,)) | H62: =IF(F62=" "," ",_xlfn.XLOOKUP($C62,'Power Blocks'!$C$20:$C$31,'Power Blocks'!$J$20:$J$31,,)*$G62) | I62: =IF(F62=" "," ",_xlfn.XLOOKUP($C62,'Power Blocks'!$C$20:$C$31,'Power Blocks'!$K$20:$K$31,,)/1000*$G62) | J62: =IF(F62=" "," ",_xlfn.XLOOKUP($C62,'Power Blocks'!$C$20:$C$31,'Power Blocks'!$M$20:$M$31,,)*$G62)
C63: -- | F63: =_xlfn.XLOOKUP($C63,'Power Blocks'!$C$20:$C$31,'Power Blocks'!$D$20:$D$31,,) | G63: =IF(F63=" "," ",D63/_xlfn.XLOOKUP($C63,'Power Blocks'!$C$20:$C$31,'Power Blocks'!$I$20:$I$31,,)) | H63: =IF(F63=" "," ",_xlfn.XLOOKUP($C63,'Power Blocks'!$C$20:$C$31,'Power Blocks'!$J$20:$J$31,,)*$G63) | I63: =IF(F63=" "," ",_xlfn.XLOOKUP($C63,'Power Blocks'!$C$20:$C$31,'Power Blocks'!$K$20:$K$31,,)/1000*$G63) | J63: =IF(F63=" "," ",_xlfn.XLOOKUP($C63,'Power Blocks'!$C$20:$C$31,'Power Blocks'!$M$20:$M$31,,)*$G63)
C64: -- | F64: =_xlfn.XLOOKUP($C64,'Power Blocks'!$C$20:$C$31,'Power Blocks'!$D$20:$D$31,,) | G64: =IF(F64=" "," ",D64/_xlfn.XLOOKUP($C64,'Power Blocks'!$C$20:$C$31,'Power Blocks'!$I$20:$I$31,,)) | H64: =IF(F64=" "," ",_xlfn.XLOOKUP($C64,'Power Blocks'!$C$20:$C$31,'Power Blocks'!$J$20:$J$31,,)*$G64) | I64: =IF(F64=" "," ",_xlfn.XLOOKUP($C64,'Power Blocks'!$C$20:$C$31,'Power Blocks'!$K$20:$K$31,,)/1000*$G64) | J64: =IF(F64=" "," ",_xlfn.XLOOKUP($C64,'Power Blocks'!$C$20:$C$31,'Power Blocks'!$M$20:$M$31,,)*$G64)
C65: -- | F65: =_xlfn.XLOOKUP($C65,'Power Blocks'!$C$20:$C$31,'Power Blocks'!$D$20:$D$31,,) | G65: =IF(F65=" "," ",D65/_xlfn.XLOOKUP($C65,'Power Blocks'!$C$20:$C$31,'Power Blocks'!$I$20:$I$31,,)) | H65: =IF(F65=" "," ",_xlfn.XLOOKUP($C65,'Power Blocks'!$C$20:$C$31,'Power Blocks'!$J$20:$J$31,,)*$G65) | I65: =IF(F65=" "," ",_xlfn.XLOOKUP($C65,'Power Blocks'!$C$20:$C$31,'Power Blocks'!$K$20:$K$31,,)/1000*$G65) | J65: =IF(F65=" "," ",_xlfn.XLOOKUP($C65,'Power Blocks'!$C$20:$C$31,'Power Blocks'!$M$20:$M$31,,)*$G65)
C66: -- | F66: =_xlfn.XLOOKUP($C66,'Power Blocks'!$C$20:$C$31,'Power Blocks'!$D$20:$D$31,,) | G66: =IF(F66=" "," ",D66/_xlfn.XLOOKUP($C66,'Power Blocks'!$C$20:$C$31,'Power Blocks'!$I$20:$I$31,,)) | H66: =IF(F66=" "," ",_xlfn.XLOOKUP($C66,'Power Blocks'!$C$20:$C$31,'Power Blocks'!$J$20:$J$31,,)*$G66) | I66: =IF(F66=" "," ",_xlfn.XLOOKUP($C66,'Power Blocks'!$C$20:$C$31,'Power Blocks'!$K$20:$K$31,,)/1000*$G66) | J66: =IF(F66=" "," ",_xlfn.XLOOKUP($C66,'Power Blocks'!$C$20:$C$31,'Power Blocks'!$M$20:$M$31,,)*$G66)
C67: -- | F67: =_xlfn.XLOOKUP($C67,'Power Blocks'!$C$20:$C$31,'Power Blocks'!$D$20:$D$31,,) | G67: =IF(F67=" "," ",D67/_xlfn.XLOOKUP($C67,'Power Blocks'!$C$20:$C$31,'Power Blocks'!$I$20:$I$31,,)) | H67: =IF(F67=" "," ",_xlfn.XLOOKUP($C67,'Power Blocks'!$C$20:$C$31,'Power Blocks'!$J$20:$J$31,,)*$G67) | I67: =IF(F67=" "," ",_xlfn.XLOOKUP($C67,'Power Blocks'!$C$20:$C$31,'Power Blocks'!$K$20:$K$31,,)/1000*$G67) | J67: =IF(F67=" "," ",_xlfn.XLOOKUP($C67,'Power Blocks'!$C$20:$C$31,'Power Blocks'!$M$20:$M$31,,)*$G67)
C68: -- | F68: =_xlfn.XLOOKUP($C68,'Power Blocks'!$C$20:$C$31,'Power Blocks'!$D$20:$D$31,,) | G68: =IF(F68=" "," ",D68/_xlfn.XLOOKUP($C68,'Power Blocks'!$C$20:$C$31,'Power Blocks'!$I$20:$I$31,,)) | H68: =IF(F68=" "," ",_xlfn.XLOOKUP($C68,'Power Blocks'!$C$20:$C$31,'Power Blocks'!$J$20:$J$31,,)*$G68) | I68: =IF(F68=" "," ",_xlfn.XLOOKUP($C68,'Power Blocks'!$C$20:$C$31,'Power Blocks'!$K$20:$K$31,,)/1000*$G68) | J68: =IF(F68=" "," ",_xlfn.XLOOKUP($C68,'Power Blocks'!$C$20:$C$31,'Power Blocks'!$M$20:$M$31,,)*$G68)
C69: -- | F69: =_xlfn.XLOOKUP($C69,'Power Blocks'!$C$20:$C$31,'Power Blocks'!$D$20:$D$31,,) | G69: =IF(F69=" "," ",D69/_xlfn.XLOOKUP($C69,'Power Blocks'!$C$20:$C$31,'Power Blocks'!$I$20:$I$31,,)) | H69: =IF(F69=" "," ",_xlfn.XLOOKUP($C69,'Power Blocks'!$C$20:$C$31,'Power Blocks'!$J$20:$J$31,,)*$G69) | I69: =IF(F69=" "," ",_xlfn.XLOOKUP($C69,'Power Blocks'!$C$20:$C$31,'Power Blocks'!$K$20:$K$31,,)/1000*$G69) | J69: =IF(F69=" "," ",_xlfn.XLOOKUP($C69,'Power Blocks'!$C$20:$C$31,'Power Blocks'!$M$20:$M$31,,)*$G69)
C70: -- | F70: =_xlfn.XLOOKUP($C70,'Power Blocks'!$C$20:$C$31,'Power Blocks'!$D$20:$D$31,,) | G70: =IF(F70=" "," ",D70/_xlfn.XLOOKUP($C70,'Power Blocks'!$C$20:$C$31,'Power Blocks'!$I$20:$I$31,,)) | H70: =IF(F70=" "," ",_xlfn.XLOOKUP($C70,'Power Blocks'!$C$20:$C$31,'Power Blocks'!$J$20:$J$31,,)*$G70) | I70: =IF(F70=" "," ",_xlfn.XLOOKUP($C70,'Power Blocks'!$C$20:$C$31,'Power Blocks'!$K$20:$K$31,,)/1000*$G70) | J70: =IF(F70=" "," ",_xlfn.XLOOKUP($C70,'Power Blocks'!$C$20:$C$31,'Power Blocks'!$M$20:$M$31,,)*$G70)
C71: -- | F71: =_xlfn.XLOOKUP($C71,'Power Blocks'!$C$20:$C$31,'Power Blocks'!$D$20:$D$31,,) | G71: =IF(F71=" "," ",D71/_xlfn.XLOOKUP($C71,'Power Blocks'!$C$20:$C$31,'Power Blocks'!$I$20:$I$31,,)) | H71: =IF(F71=" "," ",_xlfn.XLOOKUP($C71,'Power Blocks'!$C$20:$C$31,'Power Blocks'!$J$20:$J$31,,)*$G71) | I71: =IF(F71=" "," ",_xlfn.XLOOKUP($C71,'Power Blocks'!$C$20:$C$31,'Power Blocks'!$K$20:$K$31,,)/1000*$G71) | J71: =IF(F71=" "," ",_xlfn.XLOOKUP($C71,'Power Blocks'!$C$20:$C$31,'Power Blocks'!$M$20:$M$31,,)*$G71)
C72: -- | F72: =_xlfn.XLOOKUP($C72,'Power Blocks'!$C$20:$C$31,'Power Blocks'!$D$20:$D$31,,) | G72: =IF(F72=" "," ",D72/_xlfn.XLOOKUP($C72,'Power Blocks'!$C$20:$C$31,'Power Blocks'!$I$20:$I$31,,)) | H72: =IF(F72=" "," ",_xlfn.XLOOKUP($C72,'Power Blocks'!$C$20:$C$31,'Power Blocks'!$J$20:$J$31,,)*$G72) | I72: =IF(F72=" "," ",_xlfn.XLOOKUP($C72,'Power Blocks'!$C$20:$C$31,'Power Blocks'!$K$20:$K$31,,)/1000*$G72) | J72: =IF(F72=" "," ",_xlfn.XLOOKUP($C72,'Power Blocks'!$C$20:$C$31,'Power Blocks'!$M$20:$M$31,,)*$G72)
C73: -- | F73: =_xlfn.XLOOKUP($C73,'Power Blocks'!$C$20:$C$31,'Power Blocks'!$D$20:$D$31,,) | G73: =IF(F73=" "," ",D73/_xlfn.XLOOKUP($C73,'Power Blocks'!$C$20:$C$31,'Power Blocks'!$I$20:$I$31,,)) | H73: =IF(F73=" "," ",_xlfn.XLOOKUP($C73,'Power Blocks'!$C$20:$C$31,'Power Blocks'!$J$20:$J$31,,)*$G73) | I73: =IF(F73=" "," ",_xlfn.XLOOKUP($C73,'Power Blocks'!$C$20:$C$31,'Power Blocks'!$K$20:$K$31,,)/1000*$G73) | J73: =IF(F73=" "," ",_xlfn.XLOOKUP($C73,'Power Blocks'!$C$20:$C$31,'Power Blocks'!$M$20:$M$31,,)*$G73)
C74: -- | F74: =_xlfn.XLOOKUP($C74,'Power Blocks'!$C$20:$C$31,'Power Blocks'!$D$20:$D$31,,) | G74: =IF(F74=" "," ",D74/_xlfn.XLOOKUP($C74,'Power Blocks'!$C$20:$C$31,'Power Blocks'!$I$20:$I$31,,)) | H74: =IF(F74=" "," ",_xlfn.XLOOKUP($C74,'Power Blocks'!$C$20:$C$31,'Power Blocks'!$J$20:$J$31,,)*$G74) | I74: =IF(F74=" "," ",_xlfn.XLOOKUP($C74,'Power Blocks'!$C$20:$C$31,'Power Blocks'!$K$20:$K$31,,)/1000*$G74) | J74: =IF(F74=" "," ",_xlfn.XLOOKUP($C74,'Power Blocks'!$C$20:$C$31,'Power Blocks'!$M$20:$M$31,,)*$G74)
C101: Mt. Washington Quarterly CAPEX | K101: 2024 | L101: 2024.25 | M101: 2024.5 | N101: 2024.75 | O101: 2025 | P101: 2025.25 | Q101: =P101+0.25 -> 2025.5 | R101: =Q101+0.25 -> 2025.75 | S101: =R101+0.25 -> 2026 | T101: =S101+0.25 -> 2026.25 | U101: =T101+0.25 -> 2026.5 | V101: =U101+0.25 -> 2026.75 | W101: =V101+0.25 -> 2027 | X101: =W101+0.25 -> 2027.25 | ... AD101: =AC101+0.25 -> 2028.75
K102: =SUM(K105:K128) -> 0 | L102: =SUM(L105:L128) -> 2569.136 | M102: =SUM(M105:M128) -> 0 | N102: =SUM(N105:N128) -> 0 | O102: =SUM(O105:O128) -> 0 | P102: =SUM(P105:P128) -> 0 | Q102: =SUM(Q105:Q128) -> 3428.52 | R102: =SUM(R105:R128) -> 0 | ... AD102: =SUM(AD105:AD128) -> 0
C103: =C51 -> HPC1 | D103: =D51 -> 500 | E103: =E51 -> Enterprise | F103: =F51 -> IT | G103: =G51 -> 5 | H103: =H51 -> 0.5 | I103: =I51 -> 5000 | J103: =J51 -> 0 | K103: =IF(AND(ISBLANK(K51),NOT(ISBLANK(L51))),$I51,0) -> 0 | L103: =IF(AND(ISBLANK(L51),NOT(ISBLANK(M51))),$I51,0) -> 0 | M103: =IF(AND(ISBLANK(M51),NOT(ISBLANK(N51))),$I51,0) -> 0 | N103: =IF(AND(ISBLANK(N51),NOT(ISBLANK(O51))),$I51,0) -> 0 | O103: =IF(AND(ISBLANK(O51),NOT(ISBLANK(P51))),$I51,0) -> 0 | P103: =IF(AND(ISBLANK(P51),NOT(ISBLANK(Q51))),$I51,0) -> 0 | Q103: =IF(AND(ISBLANK(Q51),NOT(ISBLANK(R51))),$I51,0) -> 0 | R103: =IF(AND(ISBLANK(R51),NOT(ISBLANK(S51))),$I51,0) -> 0 | ... AD103: =IF(AND(ISBLANK(AD51),NOT(ISBLANK(AE51))),$I51,0) -> 0
C104: =C52 -> HPC1 | D104: =D52 -> 38 | E104: =E52 -> Discovery | F104: =F52 -> CPU | G104: =G52 -> 0.38 | H104: =H52 -> 0.038 | I104: =I52 -> 380 | J104: =J52 -> 4864 | K104: =IF(AND(ISBLANK(K52),NOT(ISBLANK(L52))),$I52,0) -> 0 | L104: =IF(AND(ISBLANK(L52),NOT(ISBLANK(M52))),$I52,0) -> 0 | M104: =IF(AND(ISBLANK(M52),NOT(ISBLANK(N52))),$I52,0) -> 0 | N104: =IF(AND(ISBLANK(N52),NOT(ISBLANK(O52))),$I52,0) -> 0 | O104: =IF(AND(ISBLANK(O52),NOT(ISBLANK(P52))),$I52,0) -> 0 | P104: =IF(AND(ISBLANK(P52),NOT(ISBLANK(Q52))),$I52,0) -> 0 | Q104: =IF(AND(ISBLANK(Q52),NOT(ISBLANK(R52))),$I52,0) -> 0 | R104: =IF(AND(ISBLANK(R52),NOT(ISBLANK(S52))),$I52,0) -> 0 | ... AD104: =IF(AND(ISBLANK(AD52),NOT(ISBLANK(AE52))),$I52,0) -> 0
C105: =C53 -> HDD | D105: =D53 -> 28 | E105: =E53 -> Research | F105: =F53 -> Hdisk | G105: =G53 -> 0.2 | H105: =H53 -> 0.06 | I105: =I53 -> 799.988 | J105: =J53 -> 14.84 | K105: =IF(AND(ISBLANK(K53),NOT(ISBLANK(L53))),$I53,0) -> 0 | L105: =IF(AND(ISBLANK(L53),NOT(ISBLANK(M53))),$I53,0) -> 0 | M105: =IF(AND(ISBLANK(M53),NOT(ISBLANK(N53))),$I53,0) -> 0 | N105: =IF(AND(ISBLANK(N53),NOT(ISBLANK(O53))),$I53,0) -> 0 | O105: =IF(AND(ISBLANK(O53),NOT(ISBLANK(P53))),$I53,0) -> 0 | P105: =IF(AND(ISBLANK(P53),NOT(ISBLANK(Q53))),$I53,0) -> 0 | Q105: =IF(AND(ISBLANK(Q53),NOT(ISBLANK(R53))),$I53,0) -> 0 | R105: =IF(AND(ISBLANK(R53),NOT(ISBLANK(S53))),$I53,0) -> 0 | ... AD105: =IF(AND(ISBLANK(AD53),NOT(ISBLANK(AE53))),$I53,0) -> 0
C106: =C54 -> HPC1 | D106: =D54 -> 40 | E106: =E54 -> DSAI P1 | F106: =F54 -> CPU | G106: =G54 -> 0.4 | H106: =H54 -> 0.04 | I106: =I54 -> 400 | J106: =J54 -> 5120 | K106: =IF(AND(ISBLANK(K54),NOT(ISBLANK(L54))),$I54,0) -> 0 | L106: =IF(AND(ISBLANK(L54),NOT(ISBLANK(M54))),$I54,0) -> 400 | M106: =IF(AND(ISBLANK(M54),NOT(ISBLANK(N54))),$I54,0) -> 0 | N106: =IF(AND(ISBLANK(N54),NOT(ISBLANK(O54))),$I54,0) -> 0 | O106: =IF(AND(ISBLANK(O54),NOT(ISBLANK(P54))),$I54,0) -> 0 | P106: =IF(AND(ISBLANK(P54),NOT(ISBLANK(Q54))),$I54,0) -> 0 | Q106: =IF(AND(ISBLANK(Q54),NOT(ISBLANK(R54))),$I54,0) -> 0 | R106: =IF(AND(ISBLANK(R54),NOT(ISBLANK(S54))),$I54,0) -> 0 | ... AD106: =IF(AND(ISBLANK(AD54),NOT(ISBLANK(AE54))),$I54,0) -> 0
C107: =C55 -> H100-4 | D107: =D55 -> 16 | E107: =E55 -> DSAI P1 | F107: =F55 -> GPU | G107: =G55 -> 1 | H107: =H55 -> 0.1 | I107: =I55 -> 1712 | J107: =J55 -> 64 | K107: =IF(AND(ISBLANK(K55),NOT(ISBLANK(L55))),$I55,0) -> 0 | L107: =IF(AND(ISBLANK(L55),NOT(ISBLANK(M55))),$I55,0) -> 1712 | M107: =IF(AND(ISBLANK(M55),NOT(ISBLANK(N55))),$I55,0) -> 0 | N107: =IF(AND(ISBLANK(N55),NOT(ISBLANK(O55))),$I55,0) -> 0 | O107: =IF(AND(ISBLANK(O55),NOT(ISBLANK(P55))),$I55,0) -> 0 | P107: =IF(AND(ISBLANK(P55),NOT(ISBLANK(Q55))),$I55,0) -> 0 | Q107: =IF(AND(ISBLANK(Q55),NOT(ISBLANK(R55))),$I55,0) -> 0 | R107: =IF(AND(ISBLANK(R55),NOT(ISBLANK(S55))),$I55,0) -> 0 | ... AD107: =IF(AND(ISBLANK(AD55),NOT(ISBLANK(AE55))),$I55,0) -> 0
C108: =C56 -> HDD | D108: =D56 -> 16 | E108: =E56 -> DSAI P1 | F108: =F56 -> Hdisk | G108: =G56 -> 0.11428571 | H108: =H56 -> 0.011428571 | I108: =I56 -> 457.136 | J108: =J56 -> 8.48 | K108: =IF(AND(ISBLANK(K56),NOT(ISBLANK(L56))),$I56,0) -> 0 | L108: =IF(AND(ISBLANK(L56),NOT(ISBLANK(M56))),$I56,0) -> 457.136 | M108: =IF(AND(ISBLANK(M56),NOT(ISBLANK(N56))),$I56,0) -> 0 | N108: =IF(AND(ISBLANK(N56),NOT(ISBLANK(O56))),$I56,0) -> 0 | O108: =IF(AND(ISBLANK(O56),NOT(ISBLANK(P56))),$I56,0) -> 0 | P108: =IF(AND(ISBLANK(P56),NOT(ISBLANK(Q56))),$I56,0) -> 0 | Q108: =IF(AND(ISBLANK(Q56),NOT(ISBLANK(R56))),$I56,0) -> 0 | R108: =IF(AND(ISBLANK(R56),NOT(ISBLANK(S56))),$I56,0) -> 0 | ... AD108: =IF(AND(ISBLANK(AD56),NOT(ISBLANK(AE56))),$I56,0) -> 0
C109: =C57 -> HDD | D109: =D57 -> 120 | E109: =E57 -> DSAI P2 | F109: =F57 -> Hdisk | G109: =G57 -> 0.85714286 | H109: =H57 -> 0.085714286 | I109: =I57 -> 3428.52 | J109: =J57 -> 63.6 | K109: =IF(AND(ISBLANK(K57),NOT(ISBLANK(L57))),$I57,0) -> 0 | L109: =IF(AND(ISBLANK(L57),NOT(ISBLANK(M57))),$I57,0) -> 0 | M109: =IF(AND(ISBLANK(M57),NOT(ISBLANK(N57))),$I57,0) -> 0 | N109: =IF(AND(ISBLANK(N57),NOT(ISBLANK(O57))),$I57,0) -> 0 | O109: =IF(AND(ISBLANK(O57),NOT(ISBLANK(P57))),$I57,0) -> 0 | P109: =IF(AND(ISBLANK(P57),NOT(ISBLANK(Q57))),$I57,0) -> 0 | Q109: =IF(AND(ISBLANK(Q57),NOT(ISBLANK(R57))),$I57,0) -> 3428.52 | R109: =IF(AND(ISBLANK(R57),NOT(ISBLANK(S57))),$I57,0) -> 0 | ... AD109: =IF(AND(ISBLANK(AD57),NOT(ISBLANK(AE57))),$I57,0) -> 0
C110: =C58 -> -- | D110: =D58 -> 0 | E110: =E58 | F110: =F58 | G110: =G58 | H110: =H58 | I110: =I58 | J110: =J58 | K110: =IF(AND(ISBLANK(K58),NOT(ISBLANK(L58))),$I58,0) -> 0 | L110: =IF(AND(ISBLANK(L58),NOT(ISBLANK(M58))),$I58,0) -> 0 | M110: =IF(AND(ISBLANK(M58),NOT(ISBLANK(N58))),$I58,0) | N110: =IF(AND(ISBLANK(N58),NOT(ISBLANK(O58))),$I58,0) -> 0 | O110: =IF(AND(ISBLANK(O58),NOT(ISBLANK(P58))),$I58,0) -> 0 | P110: =IF(AND(ISBLANK(P58),NOT(ISBLANK(Q58))),$I58,0) -> 0 | Q110: =IF(AND(ISBLANK(Q58),NOT(ISBLANK(R58))),$I58,0) -> 0 | R110: =IF(AND(ISBLANK(R58),NOT(ISBLANK(S58))),$I58,0) -> 0 | ... AD110: =IF(AND(ISBLANK(AD58),NOT(ISBLANK(AE58))),$I58,0) -> 0
C111: =C59 -> -- | D111: =D59 -> 0 | E111: =E59 | F111: =F59 | G111: =G59 | H111: =H59 | I111: =I59 | J111: =J59 | K111: =IF(AND(ISBLANK(K59),NOT(ISBLANK(L59))),$I59,0) -> 0 | L111: =IF(AND(ISBLANK(L59),NOT(ISBLANK(M59))),$I59,0) -> 0 | M111: =IF(AND(ISBLANK(M59),NOT(ISBLANK(N59))),$I59,0) | N111: =IF(AND(ISBLANK(N59),NOT(ISBLANK(O59))),$I59,0) -> 0 | O111: =IF(AND(ISBLANK(O59),NOT(ISBLANK(P59))),$I59,0) -> 0 | P111: =IF(AND(ISBLANK(P59),NOT(ISBLANK(Q59))),$I59,0) -> 0 | Q111: =IF(AND(ISBLANK(Q59),NOT(ISBLANK(R59))),$I59,0) -> 0 | R111: =IF(AND(ISBLANK(R59),NOT(ISBLANK(S59))),$I59,0) -> 0 | ... AD111: =IF(AND(ISBLANK(AD59),NOT(ISBLANK(AE59))),$I59,0) -> 0
C112: =C60 -> -- | D112: =D60 -> 0 | E112: =E60 | F112: =F60 | G112: =G60 | H112: =H60 | I112: =I60 | J112: =J60 | K112: =IF(AND(ISBLANK(K60),NOT(ISBLANK(L60))),$I60,0) -> 0 | L112: =IF(AND(ISBLANK(L60),NOT(ISBLANK(M60))),$I60,0) -> 0 | M112: =IF(AND(ISBLANK(M60),NOT(ISBLANK(N60))),$I60,0) | N112: =IF(AND(ISBLANK(N60),NOT(ISBLANK(O60))),$I60,0) -> 0 | O112: =IF(AND(ISBLANK(O60),NOT(ISBLANK(P60))),$I60,0) -> 0 | P112: =IF(AND(ISBLANK(P60),NOT(ISBLANK(Q60))),$I60,0) -> 0 | Q112: =IF(AND(ISBLANK(Q60),NOT(ISBLANK(R60))),$I60,0) -> 0 | R112: =IF(AND(ISBLANK(R60),NOT(ISBLANK(S60))),$I60,0) -> 0 | ... AD112: =IF(AND(ISBLANK(AD60),NOT(ISBLANK(AE60))),$I60,0) -> 0
C113: =C61 -> -- | D113: =D61 -> 0 | E113: =E61 | F113: =F61 | G113: =G61 | H113: =H61 | I113: =I61 | J113: =J61 | K113: =IF(AND(ISBLANK(K61),NOT(ISBLANK(L61))),$I61,0) -> 0 | L113: =IF(AND(ISBLANK(L61),NOT(ISBLANK(M61))),$I61,0) -> 0 | M113: =IF(AND(ISBLANK(M61),NOT(ISBLANK(N61))),$I61,0) -> 0 | N113: =IF(AND(ISBLANK(N61),NOT(ISBLANK(O61))),$I61,0) -> 0 | O113: =IF(AND(ISBLANK(O61),NOT(ISBLANK(P61))),$I61,0) -> 0 | P113: =IF(AND(ISBLANK(P61),NOT(ISBLANK(Q61))),$I61,0) | Q113: =IF(AND(ISBLANK(Q61),NOT(ISBLANK(R61))),$I61,0) -> 0 | R113: =IF(AND(ISBLANK(R61),NOT(ISBLANK(S61))),$I61,0) -> 0 | ... AD113: =IF(AND(ISBLANK(AD61),NOT(ISBLANK(AE61))),$I61,0) -> 0
C114: =C62 -> -- | D114: =D62 -> 0 | E114: =E62 | F114: =F62 | G114: =G62 | H114: =H62 | I114: =I62 | J114: =J62 | K114: =IF(AND(ISBLANK(K62),NOT(ISBLANK(L62))),$I62,0) -> 0 | L114: =IF(AND(ISBLANK(L62),NOT(ISBLANK(M62))),$I62,0) -> 0 | M114: =IF(AND(ISBLANK(M62),NOT(ISBLANK(N62))),$I62,0) -> 0 | N114: =IF(AND(ISBLANK(N62),NOT(ISBLANK(O62))),$I62,0) -> 0 | O114: =IF(AND(ISBLANK(O62),NOT(ISBLANK(P62))),$I62,0) -> 0 | P114: =IF(AND(ISBLANK(P62),NOT(ISBLANK(Q62))),$I62,0) -> 0 | Q114: =IF(AND(ISBLANK(Q62),NOT(ISBLANK(R62))),$I62,0) -> 0 | R114: =IF(AND(ISBLANK(R62),NOT(ISBLANK(S62))),$I62,0) -> 0 | ... AD114: =IF(AND(ISBLANK(AD62),NOT(ISBLANK(AE62))),$I62,0) -> 0
... C124: =C72 -> -- | D124: =D72 | E124: =E72 | F124: =F72 | G124: =G72 | H124: =H72 | I124: =I72 | J124: =J72 | K124: =IF(AND(ISBLANK(K72),NOT(ISBLANK(L72))),$I72,0) -> 0 | L124: =IF(AND(ISBLANK(L72),NOT(ISBLANK(M72))),$I72,0) -> 0 | M124: =IF(AND(ISBLANK(M72),NOT(ISBLANK(N72))),$I72,0) -> 0 | N124: =IF(AND(ISBLANK(N72),NOT(ISBLANK(O72))),$I72,0) -> 0 | O124: =IF(AND(ISBLANK(O72),NOT(ISBLANK(P72))),$I72,0) -> 0 | P124: =IF(AND(ISBLANK(P72),NOT(ISBLANK(Q72))),$I72,0) -> 0 | Q124: =IF(AND(ISBLANK(Q72),NOT(ISBLANK(R72))),$I72,0) -> 0 | R124: =IF(AND(ISBLANK(R72),NOT(ISBLANK(S72))),$I72,0) -> 0 | ... AD124: =IF(AND(ISBLANK(AD72),NOT(ISBLANK(AE72))),$I72,0) -> 0
K151: 2024 | L151: 2024.25 | M151: 2024.5 | N151: 2024.75 | O151: 2025 | P151: 2025.25 | Q151: =P151+0.25 -> 2025.5 | R151: =Q151+0.25 -> 2025.75 | S151: =R151+0.25 -> 2026 | T151: =S151+0.25 -> 2026.25 | U151: =T151+0.25 -> 2026.5 | V151: =U151+0.25 -> 2026.75 | W151: =V151+0.25 -> 2027 | X151: =W151+0.25 -> 2027.25 | ... AD151: =AC151+0.25 -> 2028.75
J152: GPU | K152: =SUMIF($F$156:$F$176,$J152,K$156:K$176) -> 0 | L152: =SUMIF($F$156:$F$176,$J152,L$156:L$176) -> 0 | M152: =SUMIF($F$156:$F$176,$J152,M$156:M$176) -> 64 | N152: =SUMIF($F$156:$F$176,$J152,N$156:N$176) -> 64 | O152: =SUMIF($F$156:$F$176,$J152,O$156:O$176) -> 64 | P152: =SUMIF($F$156:$F$176,$J152,P$156:P$176) -> 64 | Q152: =SUMIF($F$156:$F$176,$J152,Q$156:Q$176) -> 64 | R152: =SUMIF($F$156:$F$176,$J152,R$156:R$176) -> 64 | ... AD152: =SUMIF($F$156:$F$176,$J152,AD$156:AD$176) -> 64
J153: CPU | K153: =SUMIF($F$156:$F$176,$J153,K$156:K$176) -> 4864 | L153: =SUMIF($F$156:$F$176,$J153,L$156:L$176) -> 4864 | M153: =SUMIF($F$156:$F$176,$J153,M$156:M$176) -> 9984 | N153: =SUMIF($F$156:$F$176,$J153,N$156:N$176) -> 9984 | O153: =SUMIF($F$156:$F$176,$J153,O$156:O$176) -> 9984 | P153: =SUMIF($F$156:$F$176,$J153,P$156:P$176) -> 9984 | Q153: =SUMIF($F$156:$F$176,$J153,Q$156:Q$176) -> 9984 | R153: =SUMIF($F$156:$F$176,$J153,R$156:R$176) -> 9984 | ... AD153: =SUMIF($F$156:$F$176,$J153,AD$156:AD$176) -> 9984
J154: Hdisk | K154: =SUMIF($F$156:$F$176,$J154,K$156:K$176) -> 14.84 | L154: =SUMIF($F$156:$F$176,$J154,L$156:L$176) -> 14.84 | M154: =SUMIF($F$156:$F$176,$J154,M$156:M$176) -> 23.32 | N154: =SUMIF($F$156:$F$176,$J154,N$156:N$176) -> 23.32 | O154: =SUMIF($F$156:$F$176,$J154,O$156:O$176) -> 23.32 | P154: =SUMIF($F$156:$F$176,$J154,P$156:P$176) -> 23.32 | Q154: =SUMIF($F$156:$F$176,$J154,Q$156:Q$176) -> 23.32 | R154: =SUMIF($F$156:$F$176,$J154,R$156:R$176) -> 86.92 | ... AD154: =SUMIF($F$156:$F$176,$J154,AD$156:AD$176) -> 86.92
J155: Sdisk | K155: =SUMIF($F$156:$F$176,$J155,K$156:K$176) -> 0 | L155: =SUMIF($F$156:$F$176,$J155,L$156:L$176) -> 0 | M155: =SUMIF($F$156:$F$176,$J155,M$156:M$176) -> 0 | N155: =SUMIF($F$156:$F$176,$J155,N$156:N$176) -> 0 | O155: =SUMIF($F$156:$F$176,$J155,O$156:O$176) -> 0 | P155: =SUMIF($F$156:$F$176,$J155,P$156:P$176) -> 0 | Q155: =SUMIF($F$156:$F$176,$J155,Q$156:Q$176) -> 0 | R155: =SUMIF($F$156:$F$176,$J155,R$156:R$176) -> 0 | ... AD155: =SUMIF($F$156:$F$176,$J155,AD$156:AD$176) -> 0
C156: =C103 -> HPC1 | F156: =F103 -> IT | K156: =IF(NOT(ISBLANK(K51)),$J51,0) -> 0 | L156: =IF(NOT(ISBLANK(L51)),$J51,0) -> 0 | M156: =IF(NOT(ISBLANK(M51)),$J51,0) -> 0 | N156: =IF(NOT(ISBLANK(N51)),$J51,0) -> 0 | O156: =IF(NOT(ISBLANK(O51)),$J51,0) -> 0 | P156: =IF(NOT(ISBLANK(P51)),$J51,0) -> 0 | Q156: =IF(NOT(ISBLANK(Q51)),$J51,0) -> 0 | R156: =IF(NOT(ISBLANK(R51)),$J51,0) -> 0 | ... AD156: =IF(NOT(ISBLANK(AD51)),$J51,0) -> 0
C157: =C104 -> HPC1 | F157: =F104 -> CPU | K157: =IF(NOT(ISBLANK(K52)),$J52,0) -> 4864 | L157: =IF(NOT(ISBLANK(L52)),$J52,0) -> 4864 | M157: =IF(NOT(ISBLANK(M52)),$J52,0) -> 4864 | N157: =IF(NOT(ISBLANK(N52)),$J52,0) -> 4864 | O157: =IF(NOT(ISBLANK(O52)),$J52,0) -> 4864 | P157: =IF(NOT(ISBLANK(P52)),$J52,0) -> 4864 | Q157: =IF(NOT(ISBLANK(Q52)),$J52,0) -> 4864 | R157: =IF(NOT(ISBLANK(R52)),$J52,0) -> 4864 | ... AD157: =IF(NOT(ISBLANK(AD52)),$J52,0) -> 4864
C158: =C105 -> HDD | F158: =F105 -> Hdisk | K158: =IF(NOT(ISBLANK(K53)),$J53,0) -> 14.84 | L158: =IF(NOT(ISBLANK(L53)),$J53,0) -> 14.84 | M158: =IF(NOT(ISBLANK(M53)),$J53,0) -> 14.84 | N158: =IF(NOT(ISBLANK(N53)),$J53,0) -> 14.84 | O158: =IF(NOT(ISBLANK(O53)),$J53,0) -> 14.84 | P158: =IF(NOT(ISBLANK(P53)),$J53,0) -> 14.84 | Q158: =IF(NOT(ISBLANK(Q53)),$J53,0) -> 14.84 | R158: =IF(NOT(ISBLANK(R53)),$J53,0) -> 14.84 | ... AD158: =IF(NOT(ISBLANK(AD53)),$J53,0) -> 14.84
C159: =C106 -> HPC1 | F159: =F106 -> CPU | K159: =IF(NOT(ISBLANK(K54)),$J54,0) -> 0 | L159: =IF(NOT(ISBLANK(L54)),$J54,0) -> 0 | M159: =IF(NOT(ISBLANK(M54)),$J54,0) -> 5120 | N159: =IF(NOT(ISBLANK(N54)),$J54,0) -> 5120 | O159: =IF(NOT(ISBLANK(O54)),$J54,0) -> 5120 | P159: =IF(NOT(ISBLANK(P54)),$J54,0) -> 5120 | Q159: =IF(NOT(ISBLANK(Q54)),$J54,0) -> 5120 | R159: =IF(NOT(ISBLANK(R54)),$J54,0) -> 5120 | ... AD159: =IF(NOT(ISBLANK(AD54)),$J54,0) -> 5120
C160: =C107 -> H100-4 | F160: =F107 -> GPU | K160: =IF(NOT(ISBLANK(K55)),$J55,0) -> 0 | L160: =IF(NOT(ISBLANK(L55)),$J55,0) -> 0 | M160: =IF(NOT(ISBLANK(M55)),$J55,0) -> 64 | N160: =IF(NOT(ISBLANK(N55)),$J55,0) -> 64 | O160: =IF(NOT(ISBLANK(O55)),$J55,0) -> 64 | P160: =IF(NOT(ISBLANK(P55)),$J55,0) -> 64 | Q160: =IF(NOT(ISBLANK(Q55)),$J55,0) -> 64 | R160: =IF(NOT(ISBLANK(R55)),$J55,0) -> 64 | ... AD160: =IF(NOT(ISBLANK(AD55)),$J55,0) -> 64
C161: =C108 -> HDD | F161: =F108 -> Hdisk | K161: =IF(NOT(ISBLANK(K56)),$J56,0) -> 0 | L161: =IF(NOT(ISBLANK(L56)),$J56,0) -> 0 | M161: =IF(NOT(ISBLANK(M56)),$J56,0) -> 8.48 | N161: =IF(NOT(ISBLANK(N56)),$J56,0) -> 8.48 | O161: =IF(NOT(ISBLANK(O56)),$J56,0) -> 8.48 | P161: =IF(NOT(ISBLANK(P56)),$J56,0) -> 8.48 | Q161: =IF(NOT(ISBLANK(Q56)),$J56,0) -> 8.48 | R161: =IF(NOT(ISBLANK(R56)),$J56,0) -> 8.48 | ... AD161: =IF(NOT(ISBLANK(AD56)),$J56,0) -> 8.48
C162: =C109 -> HDD | F162: =F109 -> Hdisk | K162: =IF(NOT(ISBLANK(K57)),$J57,0) -> 0 | L162: =IF(NOT(ISBLANK(L57)),$J57,0) -> 0 | M162: =IF(NOT(ISBLANK(M57)),$J57,0) -> 0 | N162: =IF(NOT(ISBLANK(N57)),$J57,0) -> 0 | O162: =IF(NOT(ISBLANK(O57)),$J57,0) -> 0 | P162: =IF(NOT(ISBLANK(P57)),$J57,0) -> 0 | Q162: =IF(NOT(ISBLANK(Q57)),$J57,0) -> 0 | R162: =IF(NOT(ISBLANK(R57)),$J57,0) -> 63.6 | ... AD162: =IF(NOT(ISBLANK(AD57)),$J57,0) -> 63.6
C163: =C110 -> -- | F163: =F110 | K163: =IF(NOT(ISBLANK(K58)),$J58,0) -> 0 | L163: =IF(NOT(ISBLANK(L58)),$J58,0) -> 0 | M163: =IF(NOT(ISBLANK(M58)),$J58,0) -> 0 | N163: =IF(NOT(ISBLANK(N58)),$J58,0) | O163: =IF(NOT(ISBLANK(O58)),$J58,0) | P163: =IF(NOT(ISBLANK(P58)),$J58,0) | Q163: =IF(NOT(ISBLANK(Q58)),$J58,0) | R163: =IF(NOT(ISBLANK(R58)),$J58,0) | ... AD163: =IF(NOT(ISBLANK(AD58)),$J58,0) -> 0
...

Sheet Bloomberg
AU1: created for stair plot
AU2: Used
AU3: year | AV3: MW | AW3: adjusted
AU4: 2024 | AV4: =HLOOKUP(AU4,$K$47:$AD$48,2) -> 0.2944 | AW4: =HLOOKUP($AU4,$K$45:$AD$46,2) -> 0
AU5: 2024.25 | AV5: =AV4 -> 0.2944 | AW5: =AW4 -> 0
AU6: 2024.25 | AV6: =HLOOKUP(AU6,$K$47:$AD$48,2) -> 0.2944 | AW6: =HLOOKUP($AU6,$K$45:$AD$46,2) -> 0
AU7: 2024.5 | AV7: =AV6 -> 0.2944 | AW7: =AW6 -> 0
AU8: 2024.5 | AV8: =HLOOKUP(AU8,$K$47:$AD$48,2) -> 0.2944 | AW8: =HLOOKUP($AU8,$K$45:$AD$46,2) -> 0
AU9: 2024.75 | AV9: =AV8 -> 0.2944 | AW9: =AW8 -> 0
AU10: 2024.75 | AV10: =HLOOKUP(AU10,$K$47:$AD$48,2) -> 0.2944 | AW10: =HLOOKUP($AU10,$K$45:$AD$46,2) -> 0
AU11: 2025 | AV11: =AV10 -> 0.2944 | AW11: =AW10 -> 0
AU12: 2025 | AV12: =HLOOKUP(AU12,$K$47:$AD$48,2) -> 0.2944 | AW12: =HLOOKUP($AU12,$K$45:$AD$46,2) -> 0
AU13: 2025.25 | AV13: =AV12 -> 0.2944 | AW13: =AW12 -> 0
AU14: 2025.25 | AV14: =HLOOKUP(AU14,$K$47:$AD$48,2) -> 0.2944 | AW14: =HLOOKUP($AU14,$K$45:$AD$46,2) -> 0
AU15: 2025.5 | AV15: =AV14 -> 0.2944 | AW15: =AW14 -> 0
AU16: 2025.5 | AV16: =HLOOKUP(AU16,$K$47:$AD$48,2) -> 0.35898571 | AW16: =HLOOKUP($AU16,$K$45:$AD$46,2) -> 0
AU17: 2025.75 | AV17: =AV16 -> 0.35898571 | AW17: =AW16 -> 0
AU18: 2025.75 | AV18: =HLOOKUP(AU18,$K$47:$AD$48,2) -> 0.35898571 | AW18: =HLOOKUP($AU18,$K$45:$AD$46,2) -> 0
AU19: 2026 | AV19: =AV18 -> 0.35898571 | AW19: =AW18 -> 0
AU20: 2026 | AV20: =HLOOKUP(AU20,$K$47:$AD$48,2) -> 0.35898571 | AW20: =HLOOKUP($AU20,$K$45:$AD$46,2) -> 0
AU21: 2026.25 | AV21: =AV20 -> 0.35898571 | AW21: =AW20 -> 0
AU22: 2026.25 | AV22: =HLOOKUP(AU22,$K$47:$AD$48,2) -> 0.35898571 | AW22: =HLOOKUP($AU22,$K$45:$AD$46,2) -> 0
AU23: 2026.5 | AV23: =AV22 -> 0.35898571 | AW23: =AW22 -> 0
AU24: 2026.5 | AV24: =HLOOKUP(AU24,$K$47:$AD$48,2) -> 0.35898571 | AW24: =HLOOKUP($AU24,$K$45:$AD$46,2) -> 0
AU25: 2026.75 | AV25: =AV24 -> 0.35898571 | AW25: =AW24 -> 0
AU26: 2026.75 | AV26: =HLOOKUP(AU26,$K$47:$AD$48,2) -> 0.35898571 | AW26: =HLOOKUP($AU26,$K$45:$AD$46,2) -> 0
AU27: 2027 | AV27: =AV26 -> 0.35898571 | AW27: =AW26 -> 0
AU28: 2027 | AV28: =HLOOKUP(AU28,$K$47:$AD$48,2) -> 0.35898571 | AW28: =HLOOKUP($AU28,$K$45:$AD$46,2) -> 0
AU29: 2027.25 | AV29: =AV28 -> 0.35898571 | AW29: =AW28 -> 0
AU30: 2027.25 | AV30: =HLOOKUP(AU30,$K$47:$AD$48,2) -> 0.35898571 | AW30: =HLOOKUP($AU30,$K$45:$AD$46,2) -> 0
AU31: 2027.5 | AV31: =AV30 -> 0.35898571 | AW31: =AW30 -> 0
AU32: 2027.5 | AV32: =HLOOKUP(AU32,$K$47:$AD$48,2) -> 0.35898571 | AW32: =HLOOKUP($AU32,$K$45:$AD$46,2) -> 0
AU33: 2027.75 | AV33: =AV32 -> 0.35898571 | AW33: =AW32 -> 0
AU34: 2027.75 | AV34: =HLOOKUP(AU34,$K$47:$AD$48,2) -> 0.35898571 | AW34: =HLOOKUP($AU34,$K$45:$AD$46,2) -> 0
AU35: 2028 | AV35: =AV34 -> 0.35898571 | AW35: =AW34 -> 0
AU36: 2028 | AV36: =HLOOKUP(AU36,$K$47:$AD$48,2) -> 0.35898571 | AW36: =HLOOKUP($AU36,$K$45:$AD$46,2) -> 0
AU37: 2028.25 | AV37: =AV36 -> 0.35898571 | AW37: =AW36 -> 0
AU38: 2028.25 | AV38: =HLOOKUP(AU38,$K$47:$AD$48,2) -> 0.35898571 | AW38: =HLOOKUP($AU38,$K$45:$AD$46,2) -> 0
AU39: 2028.5 | AV39: =AV38 -> 0.35898571 | AW39: =AW38 -> 0
AU40: 2028.5 | AV40: =HLOOKUP(AU40,$K$47:$AD$48,2) -> 0.35898571 | AW40: =HLOOKUP($AU40,$K$45:$AD$46,2) -> 0
AU41: 2028.75 | AV41: =AV40 -> 0.35898571 | AW41: =AW40 -> 0
AU42: 2028.75 | AV42: =HLOOKUP(AU42,$K$47:$AD$48,2) -> 0.35898571 | AW42: =HLOOKUP($AU42,$K$45:$AD$46,2) -> 0
K45: 2024 | L45: 2024.25 | M45: 2024.5 | N45: 2024.75 | O45: 2025 | P45: 2025.25 | Q45: =P45+0.25 -> 2025.5 | R45: =Q45+0.25 -> 2025.75 | S45: =R45+0.25 -> 2026 | T45: =S45+0.25 -> 2026.25 | U45: =T45+0.25 -> 2026.5 | V45: =U45+0.25 -> 2026.75 | W45: =V45+0.25 -> 2027 | X45: =W45+0.25 -> 2027.25 | ... AD45: =AC45+0.25 -> 2028.75
J46: adjusted | K46: 0 | L46: 0 | M46: 0 | N46: 0 | O46: 0 | P46: 0 | Q46: 0 | R46: 0 | S46: 0 | T46: 0 | U46: 0 | V46: 0 | W46: 0 | X46: 0 | Y46: 0 | Z46: 0 | AA46: 0 | AB46: 0 | AC46: 0 | AD46: 0
C47: Bloomberg | J47: POWER USE [MW] | K47: 2024 | L47: 2024.25 | M47: 2024.5 | N47: 2024.75 | O47: 2025 | P47: 2025.25 | Q47: =P47+0.25 -> 2025.5 | R47: =Q47+0.25 -> 2025.75 | S47: =R47+0.25 -> 2026 | T47: =S47+0.25 -> 2026.25 | U47: =T47+0.25 -> 2026.5 | V47: =U47+0.25 -> 2026.75 | W47: =V47+0.25 -> 2027 | X47: =W47+0.25 -> 2027.25 | ... AD47: =AC47+0.25 -> 2028.75
K48: =SUM(K51:K74) -> 0.2944 | L48: =SUM(L51:L74) -> 0.2944 | M48: =SUM(M51:M74) -> 0.2944 | N48: =SUM(N51:N74) -> 0.2944 | O48: =SUM(O51:O74) -> 0.2944 | P48: =SUM(P51:P74) -> 0.2944 | Q48: =SUM(Q51:Q74) -> 0.35898571 | R48: =SUM(R51:R74) -> 0.35898571 | ... AD48: =SUM(AD51:AD74) -> 0.35898571
C49: INPUT | F49: LOOKUP
C50: category | D50: units | E50: project | F50: type | G50: blocks | H50: MW | I50: $K | J50: quantity | K50: 2024 | O50: 2025 | S50: 2026 | W50: 2027 | AA50: 2028
C51: HPC1 | D51: 150 | E51: Existing | F51: =_xlfn.XLOOKUP($C51,'Power Blocks'!$C$20:$C$31,'Power Blocks'!$D$20:$D$31,,) -> CPU | G51: =IF(F51=" "," ",D51/_xlfn.XLOOKUP($C51,'Power Blocks'!$C$20:$C$31,'Power Blocks'!$I$20:$I$31,,)) -> 1.5 | H51: =IF(F51=" "," ",_xlfn.XLOOKUP($C51,'Power Blocks'!$C$20:$C$31,'Power Blocks'!$J$20:$J$31,,)*$G51) -> 0.15 | I51: =IF(F51=" "," ",_xlfn.XLOOKUP($C51,'Power Blocks'!$C$20:$C$31,'Power Blocks'!$K$20:$K$31,,)/1000*$G51) -> 1500 | J51: =IF(F51=" "," ",_xlfn.XLOOKUP($C51,'Power Blocks'!$C$20:$C$31,'Power Blocks'!$M$20:$M$31,,)*$G51) -> 19200 | K51: =$H51 -> 0.15 | L51: =$H51 -> 0.15 | M51: =$H51 -> 0.15 | N51: =$H51 -> 0.15 | O51: =$H51 -> 0.15 | P51: =$H51 -> 0.15 | Q51: =$H51 -> 0.15 | R51: =$H51 -> 0.15 | ... AD51: =$H51 -> 0.15
C52: V100-4 | D52: 6 | E52: Existing | F52: =_xlfn.XLOOKUP($C52,'Power Blocks'!$C$20:$C$31,'Power Blocks'!$D$20:$D$31,,) -> GPU | G52: =IF(F52=" "," ",D52/_xlfn.XLOOKUP($C52,'Power Blocks'!$C$20:$C$31,'Power Blocks'!$I$20:$I$31,,)) -> 0.3 | H52: =IF(F52=" "," ",_xlfn.XLOOKUP($C52,'Power Blocks'!$C$20:$C$31,'Power Blocks'!$J$20:$J$31,,)*$G52) -> 0.03 | I52: =IF(F52=" "," ",_xlfn.XLOOKUP($C52,'Power Blocks'!$C$20:$C$31,'Power Blocks'!$K$20:$K$31,,)/1000*$G52) -> 120 | J52: =IF(F52=" "," ",_xlfn.XLOOKUP($C52,'Power Blocks'!$C$20:$C$31,'Power Blocks'!$M$20:$M$31,,)*$G52) -> 24 | K52: =$H52 -> 0.03 | L52: =$H52 -> 0.03 | M52: =$H52 -> 0.03 | N52: =$H52 -> 0.03 | O52: =$H52 -> 0.03 | P52: =$H52 -> 0.03 | Q52: =$H52 -> 0.03 | R52: =$H52 -> 0.03 | ... AD52: =$H52 -> 0.03
C53: HDD | D53: 140 | E53: Existing | F53: =_xlfn.XLOOKUP($C53,'Power Blocks'!$C$20:$C$31,'Power Blocks'!$D$20:$D$31,,) -> Hdisk | G53: =IF(F53=" "," ",D53/_xlfn.XLOOKUP($C53,'Power Blocks'!$C$20:$C$31,'Power Blocks'!$I$20:$I$31,,)) -> 1 | H53: =IF(F53=" "," ",_xlfn.XLOOKUP($C53,'Power Blocks'!$C$20:$C$31,'Power Blocks'!$J$20:$J$31,,)*$G53) -> 0.1 | I53: =IF(F53=" "," ",_xlfn.XLOOKUP($C53,'Power Blocks'!$C$20:$C$31,'Power Blocks'!$K$20:$K$31,,)/1000*$G53) -> 3999.94 | J53: =IF(F53=" "," ",_xlfn.XLOOKUP($C53,'Power Blocks'!$C$20:$C$31,'Power Blocks'!$M$20:$M$31,,)*$G53) -> 74.2 | K53: =$H53 -> 0.1 | L53: =$H53 -> 0.1 | M53: =$H53 -> 0.1 | N53: =$H53 -> 0.1 | O53: =$H53 -> 0.1 | P53: =$H53 -> 0.1 | Q53: =$H53 -> 0.1 | R53: =$H53 -> 0.1 | ... AD53: =$H53 -> 0.1
C54: SSD | D54: 18 | E54: Existing | F54: =_xlfn.XLOOKUP($C54,'Power Blocks'!$C$20:$C$31,'Power Blocks'!$D$20:$D$31,,) -> Sdisk | G54: =IF(F54=" "," ",D54/_xlfn.XLOOKUP($C54,'Power Blocks'!$C$20:$C$31,'Power Blocks'!$I$20:$I$31,,)) -> 0.144 | H54: =IF(F54=" "," ",_xlfn.XLOOKUP($C54,'Power Blocks'!$C$20:$C$31,'Power Blocks'!$J$20:$J$31,,)*$G54) -> 0.0144 | I54: =IF(F54=" "," ",_xlfn.XLOOKUP($C54,'Power Blocks'!$C$20:$C$31,'Power Blocks'!$K$20:$K$31,,)/1000*$G54) -> 756 | J54: =IF(F54=" "," ",_xlfn.XLOOKUP($C54,'Power Blocks'!$C$20:$C$31,'Power Blocks'!$M$20:$M$31,,)*$G54) -> 5.4 | K54: =$H54 -> 0.0144 | L54: =$H54 -> 0.0144 | M54: =$H54 -> 0.0144 | N54: =$H54 -> 0.0144 | O54: =$H54 -> 0.0144 | P54: =$H54 -> 0.0144 | Q54: =$H54 -> 0.0144 | R54: =$H54 -> 0.0144 | ... AD54: =$H54 -> 0.0144
C55: H100-4 | D55: 4 | E55: Schmidt | F55: =_xlfn.XLOOKUP($C55,'Power Blocks'!$C$20:$C$31,'Power Blocks'!$D$20:$D$31,,) -> GPU | G55: =IF(F55=" "," ",D55/_xlfn.XLOOKUP($C55,'Power Blocks'!$C$20:$C$31,'Power Blocks'!$I$20:$I$31,,)) -> 0.25 | H55: =IF(F55=" "," ",_xlfn.XLOOKUP($C55,'Power Blocks'!$C$20:$C$31,'Power Blocks'!$J$20:$J$31,,)*$G55) -> 0.025 | I55: =IF(F55=" "," ",_xlfn.XLOOKUP($C55,'Power Blocks'!$C$20:$C$31,'Power Blocks'!$K$20:$K$31,,)/1000*$G55) -> 428 | J55: =IF(F55=" "," ",_xlfn.XLOOKUP($C55,'Power Blocks'!$C$20:$C$31,'Power Blocks'!$M$20:$M$31,,)*$G55) -> 16 | Q55: =$H55 -> 0.025 | R55: =$H55 -> 0.025 | S55: =$H55 -> 0.025 | T55: =$H55 -> 0.025 | U55: =$H55 -> 0.025 | V55: =$H55 -> 0.025 | W55: =$H55 -> 0.025 | X55: =$H55 -> 0.025 | ... AD55: =$H55 -> 0.025
C56: HPC2 | D56: 10 | E56: Schmidt | F56: =_xlfn.XLOOKUP($C56,'Power Blocks'!$C$20:$C$31,'Power Blocks'!$D$20:$D$31,,) -> CPU | G56: =IF(F56=" "," ",D56/_xlfn.XLOOKUP($C56,'Power Blocks'!$C$20:$C$31,'Power Blocks'!$I$20:$I$31,,)) -> 0.125 | H56: =IF(F56=" "," ",_xlfn.XLOOKUP($C56,'Power Blocks'!$C$20:$C$31,'Power Blocks'!$J$20:$J$31,,)*$G56) -> 0.0125 | I56: =IF(F56=" "," ",_xlfn.XLOOKUP($C56,'Power Blocks'!$C$20:$C$31,'Power Blocks'!$K$20:$K$31,,)/1000*$G56) -> 150 | J56: =IF(F56=" "," ",_xlfn.XLOOKUP($C56,'Power Blocks'!$C$20:$C$31,'Power Blocks'!$M$20:$M$31,,)*$G56) -> 2560 | Q56: =$H56 -> 0.0125 | R56: =$H56 -> 0.0125 | S56: =$H56 -> 0.0125 | T56: =$H56 -> 0.0125 | U56: =$H56 -> 0.0125 | V56: =$H56 -> 0.0125 | W56: =$H56 -> 0.0125 | X56: =$H56 -> 0.0125 | ... AD56: =$H56 -> 0.0125
C57: HDD | D57: 20 | E57: Schmidt | F57: =_xlfn.XLOOKUP($C57,'Power Blocks'!$C$20:$C$31,'Power Blocks'!$D$20:$D$31,,) -> Hdisk | G57: =IF(F57=" "," ",D57/_xlfn.XLOOKUP($C57,'Power Blocks'!$C$20:$C$31,'Power Blocks'!$I$20:$I$31,,)) -> 0.14285714 | H57: =IF(F57=" "," ",_xlfn.XLOOKUP($C57,'Power Blocks'!$C$20:$C$31,'Power Blocks'!$J$20:$J$31,,)*$G57) -> 0.014285714 | I57: =IF(F57=" "," ",_xlfn.XLOOKUP($C57,'Power Blocks'!$C$20:$C$31,'Power Blocks'!$K$20:$K$31,,)/1000*$G57) -> 571.42 | J57: =IF(F57=" "," ",_xlfn.XLOOKUP($C57,'Power Blocks'!$C$20:$C$31,'Power Blocks'!$M$20:$M$31,,)*$G57) -> 10.6 | Q57: =$H57 -> 0.014285714 | R57: =$H57 -> 0.014285714 | S57: =$H57 -> 0.014285714 | T57: =$H57 -> 0.014285714 | U57: =$H57 -> 0.014285714 | V57: =$H57 -> 0.014285714 | W57: =$H57 -> 0.014285714 | X57: =$H57 -> 0.014285714 | ... AD57: =$H57 -> 0.014285714
C58: SSD | D58: 16 | E58: Schmidt | F58: =_xlfn.XLOOKUP($C58,'Power Blocks'!$C$20:$C$31,'Power Blocks'!$D$20:$D$31,,) -> Sdisk | G58: =IF(F58=" "," ",D58/_xlfn.XLOOKUP($C58,'Power Blocks'!$C$20:$C$31,'Power Blocks'!$I$20:$I$31,,)) -> 0.128 | H58: =IF(F58=" "," ",_xlfn.XLOOKUP($C58,'Power Blocks'!$C$20:$C$31,'Power Blocks'!$J$20:$J$31,,)*$G58) -> 0.0128 | I58: =IF(F58=" "," ",_xlfn.XLOOKUP($C58,'Power Blocks'!$C$20:$C$31,'Power Blocks'!$K$20:$K$31,,)/1000*$G58) -> 672 | J58: =IF(F58=" "," ",_xlfn.XLOOKUP($C58,'Power Blocks'!$C$20:$C$31,'Power Blocks'!$M$20:$M$31,,)*$G58) -> 4.8 | Q58: =$H58 -> 0.0128 | R58: =$H58 -> 0.0128 | S58: =$H58 -> 0.0128 | T58: =$H58 -> 0.0128 | U58: =$H58 -> 0.0128 | V58: =$H58 -> 0.0128 | W58: =$H58 -> 0.0128 | X58: =$H58 -> 0.0128 | ... AD58: =$H58 -> 0.0128
C59: -- | F59: =_xlfn.XLOOKUP($C59,'Power Blocks'!$C$20:$C$31,'Power Blocks'!$D$20:$D$31,,) | G59: =IF(F59=" "," ",D59/_xlfn.XLOOKUP($C59,'Power Blocks'!$C$20:$C$31,'Power Blocks'!$I$20:$I$31,,)) | H59: =IF(F59=" "," ",_xlfn.XLOOKUP($C59,'Power Blocks'!$C$20:$C$31,'Power Blocks'!$J$20:$J$31,,)*$G59) | I59: =IF(F59=" "," ",_xlfn.XLOOKUP($C59,'Power Blocks'!$C$20:$C$31,'Power Blocks'!$K$20:$K$31,,)/1000*$G59) | J59: =IF(F59=" "," ",_xlfn.XLOOKUP($C59,'Power Blocks'!$C$20:$C$31,'Power Blocks'!$M$20:$M$31,,)*$G59) | S59: =$H59 | T59: =$H59 | U59: =$H59 | V59: =$H59 | W59: =$H59 | X59: =$H59 | Y59: =$H59 | Z59: =$H59 | ... AD59: =$H59
C60: -- | F60: =_xlfn.XLOOKUP($C60,'Power Blocks'!$C$20:$C$31,'Power Blocks'!$D$20:$D$31,,) | G60: =IF(F60=" "," ",D60/_xlfn.XLOOKUP($C60,'Power Blocks'!$C$20:$C$31,'Power Blocks'!$I$20:$I$31,,)) | H60: =IF(F60=" "," ",_xlfn.XLOOKUP($C60,'Power Blocks'!$C$20:$C$31,'Power Blocks'!$J$20:$J$31,,)*$G60) | I60: =IF(F60=" "," ",_xlfn.XLOOKUP($C60,'Power Blocks'!$C$20:$C$31,'Power Blocks'!$K$20:$K$31,,)/1000*$G60) | J60: =IF(F60=" "," ",_xlfn.XLOOKUP($C60,'Power Blocks'!$C$20:$C$31,'Power Blocks'!$M$20:$M$31,,)*$G60)
C61: -- | F61: =_xlfn.XLOOKUP($C61,'Power Blocks'!$C$20:$C$31,'Power Blocks'!$D$20:$D$31,,) | G61: =IF(F61=" "," ",D61/_xlfn.XLOOKUP($C61,'Power Blocks'!$C$20:$C$31,'Power Blocks'!$I$20:$I$31,,)) | H61: =IF(F61=" "," ",_xlfn.XLOOKUP($C61,'Power Blocks'!$C$20:$C$31,'Power Blocks'!$J$20:$J$31,,)*$G61) | I61: =IF(F61=" "," ",_xlfn.XLOOKUP($C61,'Power Blocks'!$C$20:$C$31,'Power Blocks'!$K$20:$K$31,,)/1000*$G61) | J61: =IF(F61=" "," ",_xlfn.XLOOKUP($C61,'Power Blocks'!$C$20:$C$31,'Power Blocks'!$M$20:$M$31,,)*$G61)
C62: -- | F62: =_xlfn.XLOOKUP($C62,'Power Blocks'!$C$20:$C$31,'Power Blocks'!$D$20:$D$31,,) | G62: =IF(F62=" "," ",D62/_xlfn.XLOOKUP($C62,'Power Blocks'!$C$20:$C$31,'Power Blocks'!$I$20:$I$31,,)) | H62: =IF(F62=" "," ",_xlfn.XLOOKUP($C62,'Power Blocks'!$C$20:$C$31,'Power Blocks'!$J$20:$J$31,,)*$G62) | I62: =IF(F62=" "," ",_xlfn.XLOOKUP($C62,'Power Blocks'!$C$20:$C$31,'Power Blocks'!$K$20:$K$31,,)/1000*$G62) | J62: =IF(F62=" "," ",_xlfn.XLOOKUP($C62,'Power Blocks'!$C$20:$C$31,'Power Blocks'!$M$20:$M$31,,)*$G62)
C63: -- | F63: =_xlfn.XLOOKUP($C63,'Power Blocks'!$C$20:$C$31,'Power Blocks'!$D$20:$D$31,,) | G63: =IF(F63=" "," ",D63/_xlfn.XLOOKUP($C63,'Power Blocks'!$C$20:$C$31,'Power Blocks'!$I$20:$I$31,,)) | H63: =IF(F63=" "," ",_xlfn.XLOOKUP($C63,'Power Blocks'!$C$20:$C$31,'Power Blocks'!$J$20:$J$31,,)*$G63) | I63: =IF(F63=" "," ",_xlfn.XLOOKUP($C63,'Power Blocks'!$C$20:$C$31,'Power Blocks'!$K$20:$K$31,,)/1000*$G63) | J63: =IF(F63=" "," ",_xlfn.XLOOKUP($C63,'Power Blocks'!$C$20:$C$31,'Power Blocks'!$M$20:$M$31,,)*$G63)
C64: -- | F64: =_xlfn.XLOOKUP($C64,'Power Blocks'!$C$20:$C$31,'Power Blocks'!$D$20:$D$31,,) | G64: =IF(F64=" "," ",D64/_xlfn.XLOOKUP($C64,'Power Blocks'!$C$20:$C$31,'Power Blocks'!$I$20:$I$31,,)) | H64: =IF(F64=" "," ",_xlfn.XLOOKUP($C64,'Power Blocks'!$C$20:$C$31,'Power Blocks'!$J$20:$J$31,,)*$G64) | I64: =IF(F64=" "," ",_xlfn.XLOOKUP($C64,'Power Blocks'!$C$20:$C$31,'Power Blocks'!$K$20:$K$31,,)/1000*$G64) | J64: =IF(F64=" "," ",_xlfn.XLOOKUP($C64,'Power Blocks'!$C$20:$C$31,'Power Blocks'!$M$20:$M$31,,)*$G64)
C65: -- | F65: =_xlfn.XLOOKUP($C65,'Power Blocks'!$C$20:$C$31,'Power Blocks'!$D$20:$D$31,,) | G65: =IF(F65=" "," ",D65/_xlfn.XLOOKUP($C65,'Power Blocks'!$C$20:$C$31,'Power Blocks'!$I$20:$I$31,,)) | H65: =IF(F65=" "," ",_xlfn.XLOOKUP($C65,'Power Blocks'!$C$20:$C$31,'Power Blocks'!$J$20:$J$31,,)*$G65) | I65: =IF(F65=" "," ",_xlfn.XLOOKUP($C65,'Power Blocks'!$C$20:$C$31,'Power Blocks'!$K$20:$K$31,,)/1000*$G65) | J65: =IF(F65=" "," ",_xlfn.XLOOKUP($C65,'Power Blocks'!$C$20:$C$31,'Power Blocks'!$M$20:$M$31,,)*$G65)
C66: -- | F66: =_xlfn.XLOOKUP($C66,'Power Blocks'!$C$20:$C$31,'Power Blocks'!$D$20:$D$31,,) | G66: =IF(F66=" "," ",D66/_xlfn.XLOOKUP($C66,'Power Blocks'!$C$20:$C$31,'Power Blocks'!$I$20:$I$31,,)) | H66: =IF(F66=" "," ",_xlfn.XLOOKUP($C66,'Power Blocks'!$C$20:$C$31,'Power Blocks'!$J$20:$J$31,,)*$G66) | I66: =IF(F66=" "," ",_xlfn.XLOOKUP($C66,'Power Blocks'!$C$20:$C$31,'Power Blocks'!$K$20:$K$31,,)/1000*$G66) | J66: =IF(F66=" "," ",_xlfn.XLOOKUP($C66,'Power Blocks'!$C$20:$C$31,'Power Blocks'!$M$20:$M$31,,)*$G66)
C67: -- | F67: =_xlfn.XLOOKUP($C67,'Power Blocks'!$C$20:$C$31,'Power Blocks'!$D$20:$D$31,,) | G67: =IF(F67=" "," ",D67/_xlfn.XLOOKUP($C67,'Power Blocks'!$C$20:$C$31,'Power Blocks'!$I$20:$I$31,,)) | H67: =IF(F67=" "," ",_xlfn.XLOOKUP($C67,'Power Blocks'!$C$20:$C$31,'Power Blocks'!$J$20:$J$31,,)*$G67) | I67: =IF(F67=" "," ",_xlfn.XLOOKUP($C67,'Power Blocks'!$C$20:$C$31,'Power Blocks'!$K$20:$K$31,,)/1000*$G67) | J67: =IF(F67=" "," ",_xlfn.XLOOKUP($C67,'Power Blocks'!$C$20:$C$31,'Power Blocks'!$M$20:$M$31,,)*$G67)
C68: -- | F68: =_xlfn.XLOOKUP($C68,'Power Blocks'!$C$20:$C$31,'Power Blocks'!$D$20:$D$31,,) | G68: =IF(F68=" "," ",D68/_xlfn.XLOOKUP($C68,'Power Blocks'!$C$20:$C$31,'Power Blocks'!$I$20:$I$31,,)) | H68: =IF(F68=" "," ",_xlfn.XLOOKUP($C68,'Power Blocks'!$C$20:$C$31,'Power Blocks'!$J$20:$J$31,,)*$G68) | I68: =IF(F68=" "," ",_xlfn.XLOOKUP($C68,'Power Blocks'!$C$20:$C$31,'Power Blocks'!$K$20:$K$31,,)/1000*$G68) | J68: =IF(F68=" "," ",_xlfn.XLOOKUP($C68,'Power Blocks'!$C$20:$C$31,'Power Blocks'!$M$20:$M$31,,)*$G68)
C69: -- | F69: =_xlfn.XLOOKUP($C69,'Power Blocks'!$C$20:$C$31,'Power Blocks'!$D$20:$D$31,,) | G69: =IF(F69=" "," ",D69/_xlfn.XLOOKUP($C69,'Power Blocks'!$C$20:$C$31,'Power Blocks'!$I$20:$I$31,,)) | H69: =IF(F69=" "," ",_xlfn.XLOOKUP($C69,'Power Blocks'!$C$20:$C$31,'Power Blocks'!$J$20:$J$31,,)*$G69) | I69: =IF(F69=" "," ",_xlfn.XLOOKUP($C69,'Power Blocks'!$C$20:$C$31,'Power Blocks'!$K$20:$K$31,,)/1000*$G69) | J69: =IF(F69=" "," ",_xlfn.XLOOKUP($C69,'Power Blocks'!$C$20:$C$31,'Power Blocks'!$M$20:$M$31,,)*$G69)
C70: -- | F70: =_xlfn.XLOOKUP($C70,'Power Blocks'!$C$20:$C$31,'Power Blocks'!$D$20:$D$31,,) | G70: =IF(F70=" "," ",D70/_xlfn.XLOOKUP($C70,'Power Blocks'!$C$20:$C$31,'Power Blocks'!$I$20:$I$31,,)) | H70: =IF(F70=" "," ",_xlfn.XLOOKUP($C70,'Power Blocks'!$C$20:$C$31,'Power Blocks'!$J$20:$J$31,,)*$G70) | I70: =IF(F70=" "," ",_xlfn.XLOOKUP($C70,'Power Blocks'!$C$20:$C$31,'Power Blocks'!$K$20:$K$31,,)/1000*$G70) | J70: =IF(F70=" "," ",_xlfn.XLOOKUP($C70,'Power Blocks'!$C$20:$C$31,'Power Blocks'!$M$20:$M$31,,)*$G70)
C71: -- | F71: =_xlfn.XLOOKUP($C71,'Power Blocks'!$C$20:$C$31,'Power Blocks'!$D$20:$D$31,,) | G71: =IF(F71=" "," ",D71/_xlfn.XLOOKUP($C71,'Power Blocks'!$C$20:$C$31,'Power Blocks'!$I$20:$I$31,,)) | H71: =IF(F71=" "," ",_xlfn.XLOOKUP($C71,'Power Blocks'!$C$20:$C$31,'Power Blocks'!$J$20:$J$31,,)*$G71) | I71: =IF(F71=" "," ",_xlfn.XLOOKUP($C71,'Power Blocks'!$C$20:$C$31,'Power Blocks'!$K$20:$K$31,,)/1000*$G71) | J71: =IF(F71=" "," ",_xlfn.XLOOKUP($C71,'Power Blocks'!$C$20:$C$31,'Power Blocks'!$M$20:$M$31,,)*$G71)
... C74: -- | F74: =_xlfn.XLOOKUP($C74,'Power Blocks'!$C$20:$C$31,'Power Blocks'!$D$20:$D$31,,) | G74: =IF(F74=" "," ",D74/_xlfn.XLOOKUP($C74,'Power Blocks'!$C$20:$C$31,'Power Blocks'!$I$20:$I$31,,)) | H74: =IF(F74=" "," ",_xlfn.XLOOKUP($C74,'Power Blocks'!$C$20:$C$31,'Power Blocks'!$J$20:$J$31,,)*$G74) | I74: =IF(F74=" "," ",_xlfn.XLOOKUP($C74,'Power Blocks'!$C$20:$C$31,'Power Blocks'!$K$20:$K$31,,)/1000*$G74) | J74: =IF(F74=" "," ",_xlfn.XLOOKUP($C74,'Power Blocks'!$C$20:$C$31,'Power Blocks'!$M$20:$M$31,,)*$G74)
C101: Bloomberg Quarterly CAPEX | K101: 2024 | L101: 2024.25 | M101: 2024.5 | N101: 2024.75 | O101: 2025 | P101: 2025.25 | Q101: =P101+0.25 -> 2025.5 | R101: =Q101+0.25 -> 2025.75 | S101: =R101+0.25 -> 2026 | T101: =S101+0.25 -> 2026.25 | U101: =T101+0.25 -> 2026.5 | V101: =U101+0.25 -> 2026.75 | W101: =V101+0.25 -> 2027 | X101: =W101+0.25 -> 2027.25 | ... AD101: =AC101+0.25 -> 2028.75
K102: =SUM(K105:K128) -> 0 | L102: =SUM(L105:L128) -> 0 | M102: =SUM(M105:M128) -> 0 | N102: =SUM(N105:N128) -> 0 | O102: =SUM(O105:O128) -> 0 | P102: =SUM(P105:P128) -> 1821.42 | Q102: =SUM(Q105:Q128) -> 0 | R102: =SUM(R105:R128) -> 0 | ... AD102: =SUM(AD105:AD128) -> 0
C103: =C51 -> HPC1 | D103: =D51 -> 150 | E103: =E51 -> Existing | F103: =F51 -> CPU | G103: =G51 -> 1.5 | H103: =H51 -> 0.15 | I103: =I51 -> 1500 | J103: =J51 -> 19200 | K103: =IF(AND(ISBLANK(K51),NOT(ISBLANK(L51))),$I51,0) -> 0 | L103: =IF(AND(ISBLANK(L51),NOT(ISBLANK(M51))),$I51,0) -> 0 | M103: =IF(AND(ISBLANK(M51),NOT(ISBLANK(N51))),$I51,0) -> 0 | N103: =IF(AND(ISBLANK(N51),NOT(ISBLANK(O51))),$I51,0) -> 0 | O103: =IF(AND(ISBLANK(O51),NOT(ISBLANK(P51))),$I51,0) -> 0 | P103: =IF(AND(ISBLANK(P51),NOT(ISBLANK(Q51))),$I51,0) -> 0 | Q103: =IF(AND(ISBLANK(Q51),NOT(ISBLANK(R51))),$I51,0) -> 0 | R103: =IF(AND(ISBLANK(R51),NOT(ISBLANK(S51))),$I51,0) -> 0 | ... AD103: =IF(AND(ISBLANK(AD51),NOT(ISBLANK(AE51))),$I51,0) -> 0
C104: =C52 -> V100-4 | D104: =D52 -> 6 | E104: =E52 -> Existing | F104: =F52 -> GPU | G104: =G52 -> 0.3 | H104: =H52 -> 0.03 | I104: =I52 -> 120 | J104: =J52 -> 24 | K104: =IF(AND(ISBLANK(K52),NOT(ISBLANK(L52))),$I52,0) -> 0 | L104: =IF(AND(ISBLANK(L52),NOT(ISBLANK(M52))),$I52,0) -> 0 | M104: =IF(AND(ISBLANK(M52),NOT(ISBLANK(N52))),$I52,0) -> 0 | N104: =IF(AND(ISBLANK(N52),NOT(ISBLANK(O52))),$I52,0) -> 0 | O104: =IF(AND(ISBLANK(O52),NOT(ISBLANK(P52))),$I52,0) -> 0 | P104: =IF(AND(ISBLANK(P52),NOT(ISBLANK(Q52))),$I52,0) -> 0 | Q104: =IF(AND(ISBLANK(Q52),NOT(ISBLANK(R52))),$I52,0) -> 0 | R104: =IF(AND(ISBLANK(R52),NOT(ISBLANK(S52))),$I52,0) -> 0 | ... AD104: =IF(AND(ISBLANK(AD52),NOT(ISBLANK(AE52))),$I52,0) -> 0
C105: =C53 -> HDD | D105: =D53 -> 140 | E105: =E53 -> Existing | F105: =F53 -> Hdisk | G105: =G53 -> 1 | H105: =H53 -> 0.1 | I105: =I53 -> 3999.94 | J105: =J53 -> 74.2 | K105: =IF(AND(ISBLANK(K53),NOT(ISBLANK(L53))),$I53,0) -> 0 | L105: =IF(AND(ISBLANK(L53),NOT(ISBLANK(M53))),$I53,0) -> 0 | M105: =IF(AND(ISBLANK(M53),NOT(ISBLANK(N53))),$I53,0) -> 0 | N105: =IF(AND(ISBLANK(N53),NOT(ISBLANK(O53))),$I53,0) -> 0 | O105: =IF(AND(ISBLANK(O53),NOT(ISBLANK(P53))),$I53,0) -> 0 | P105: =IF(AND(ISBLANK(P53),NOT(ISBLANK(Q53))),$I53,0) -> 0 | Q105: =IF(AND(ISBLANK(Q53),NOT(ISBLANK(R53))),$I53,0) -> 0 | R105: =IF(AND(ISBLANK(R53),NOT(ISBLANK(S53))),$I53,0) -> 0 | ... AD105: =IF(AND(ISBLANK(AD53),NOT(ISBLANK(AE53))),$I53,0) -> 0
C106: =C54 -> SSD | D106: =D54 -> 18 | E106: =E54 -> Existing | F106: =F54 -> Sdisk | G106: =G54 -> 0.144 | H106: =H54 -> 0.0144 | I106: =I54 -> 756 | J106: =J54 -> 5.4 | K106: =IF(AND(ISBLANK(K54),NOT(ISBLANK(L54))),$I54,0) -> 0 | L106: =IF(AND(ISBLANK(L54),NOT(ISBLANK(M54))),$I54,0) -> 0 | M106: =IF(AND(ISBLANK(M54),NOT(ISBLANK(N54))),$I54,0) -> 0 | N106: =IF(AND(ISBLANK(N54),NOT(ISBLANK(O54))),$I54,0) -> 0 | O106: =IF(AND(ISBLANK(O54),NOT(ISBLANK(P54))),$I54,0) -> 0 | P106: =IF(AND(ISBLANK(P54),NOT(ISBLANK(Q54))),$I54,0) -> 0 | Q106: =IF(AND(ISBLANK(Q54),NOT(ISBLANK(R54))),$I54,0) -> 0 | R106: =IF(AND(ISBLANK(R54),NOT(ISBLANK(S54))),$I54,0) -> 0 | ... AD106: =IF(AND(ISBLANK(AD54),NOT(ISBLANK(AE54))),$I54,0) -> 0
C107: =C55 -> H100-4 | D107: =D55 -> 4 | E107: =E55 -> Schmidt | F107: =F55 -> GPU | G107: =G55 -> 0.25 | H107: =H55 -> 0.025 | I107: =I55 -> 428 | J107: =J55 -> 16 | K107: =IF(AND(ISBLANK(K55),NOT(ISBLANK(L55))),$I55,0) -> 0 | L107: =IF(AND(ISBLANK(L55),NOT(ISBLANK(M55))),$I55,0) -> 0 | M107: =IF(AND(ISBLANK(M55),NOT(ISBLANK(N55))),$I55,0) -> 0 | N107: =IF(AND(ISBLANK(N55),NOT(ISBLANK(O55))),$I55,0) -> 0 | O107: =IF(AND(ISBLANK(O55),NOT(ISBLANK(P55))),$I55,0) -> 0 | P107: =IF(AND(ISBLANK(P55),NOT(ISBLANK(Q55))),$I55,0) -> 428 | Q107: =IF(AND(ISBLANK(Q55),NOT(ISBLANK(R55))),$I55,0) -> 0 | R107: =IF(AND(ISBLANK(R55),NOT(ISBLANK(S55))),$I55,0) -> 0 | ... AD107: =IF(AND(ISBLANK(AD55),NOT(ISBLANK(AE55))),$I55,0) -> 0
C108: =C56 -> HPC2 | D108: =D56 -> 10 | E108: =E56 -> Schmidt | F108: =F56 -> CPU | G108: =G56 -> 0.125 | H108: =H56 -> 0.0125 | I108: =I56 -> 150 | J108: =J56 -> 2560 | K108: =IF(AND(ISBLANK(K56),NOT(ISBLANK(L56))),$I56,0) -> 0 | L108: =IF(AND(ISBLANK(L56),NOT(ISBLANK(M56))),$I56,0) -> 0 | M108: =IF(AND(ISBLANK(M56),NOT(ISBLANK(N56))),$I56,0) -> 0 | N108: =IF(AND(ISBLANK(N56),NOT(ISBLANK(O56))),$I56,0) -> 0 | O108: =IF(AND(ISBLANK(O56),NOT(ISBLANK(P56))),$I56,0) -> 0 | P108: =IF(AND(ISBLANK(P56),NOT(ISBLANK(Q56))),$I56,0) -> 150 | Q108: =IF(AND(ISBLANK(Q56),NOT(ISBLANK(R56))),$I56,0) -> 0 | R108: =IF(AND(ISBLANK(R56),NOT(ISBLANK(S56))),$I56,0) -> 0 | ... AD108: =IF(AND(ISBLANK(AD56),NOT(ISBLANK(AE56))),$I56,0) -> 0
C109: =C57 -> HDD | D109: =D57 -> 20 | E109: =E57 -> Schmidt | F109: =F57 -> Hdisk | G109: =G57 -> 0.14285714 | H109: =H57 -> 0.014285714 | I109: =I57 -> 571.42 | J109: =J57 -> 10.6 | K109: =IF(AND(ISBLANK(K57),NOT(ISBLANK(L57))),$I57,0) -> 0 | L109: =IF(AND(ISBLANK(L57),NOT(ISBLANK(M57))),$I57,0) -> 0 | M109: =IF(AND(ISBLANK(M57),NOT(ISBLANK(N57))),$I57,0) -> 0 | N109: =IF(AND(ISBLANK(N57),NOT(ISBLANK(O57))),$I57,0) -> 0 | O109: =IF(AND(ISBLANK(O57),NOT(ISBLANK(P57))),$I57,0) -> 0 | P109: =IF(AND(ISBLANK(P57),NOT(ISBLANK(Q57))),$I57,0) -> 571.42 | Q109: =IF(AND(ISBLANK(Q57),NOT(ISBLANK(R57))),$I57,0) -> 0 | R109: =IF(AND(ISBLANK(R57),NOT(ISBLANK(S57))),$I57,0) -> 0 | ... AD109: =IF(AND(ISBLANK(AD57),NOT(ISBLANK(AE57))),$I57,0) -> 0
C110: =C58 -> SSD | D110: =D58 -> 16 | E110: =E58 -> Schmidt | F110: =F58 -> Sdisk | G110: =G58 -> 0.128 | H110: =H58 -> 0.0128 | I110: =I58 -> 672 | J110: =J58 -> 4.8 | K110: =IF(AND(ISBLANK(K58),NOT(ISBLANK(L58))),$I58,0) -> 0 | L110: =IF(AND(ISBLANK(L58),NOT(ISBLANK(M58))),$I58,0) -> 0 | M110: =IF(AND(ISBLANK(M58),NOT(ISBLANK(N58))),$I58,0) -> 0 | N110: =IF(AND(ISBLANK(N58),NOT(ISBLANK(O58))),$I58,0) -> 0 | O110: =IF(AND(ISBLANK(O58),NOT(ISBLANK(P58))),$I58,0) -> 0 | P110: =IF(AND(ISBLANK(P58),NOT(ISBLANK(Q58))),$I58,0) -> 672 | Q110: =IF(AND(ISBLANK(Q58),NOT(ISBLANK(R58))),$I58,0) -> 0 | R110: =IF(AND(ISBLANK(R58),NOT(ISBLANK(S58))),$I58,0) -> 0 | ... AD110: =IF(AND(ISBLANK(AD58),NOT(ISBLANK(AE58))),$I58,0) -> 0
C111: =C59 -> -- | D111: =D59 | E111: =E59 | F111: =F59 | G111: =G59 | H111: =H59 | I111: =I59 | J111: =J59 | K111: =IF(AND(ISBLANK(K59),NOT(ISBLANK(L59))),$I59,0) -> 0 | L111: =IF(AND(ISBLANK(L59),NOT(ISBLANK(M59))),$I59,0) -> 0 | M111: =IF(AND(ISBLANK(M59),NOT(ISBLANK(N59))),$I59,0) -> 0 | N111: =IF(AND(ISBLANK(N59),NOT(ISBLANK(O59))),$I59,0) -> 0 | O111: =IF(AND(ISBLANK(O59),NOT(ISBLANK(P59))),$I59,0) -> 0 | P111: =IF(AND(ISBLANK(P59),NOT(ISBLANK(Q59))),$I59,0) -> 0 | Q111: =IF(AND(ISBLANK(Q59),NOT(ISBLANK(R59))),$I59,0) -> 0 | R111: =IF(AND(ISBLANK(R59),NOT(ISBLANK(S59))),$I59,0) | ... AD111: =IF(AND(ISBLANK(AD59),NOT(ISBLANK(AE59))),$I59,0) -> 0
C112: =C60 -> -- | D112: =D60 | E112: =E60 | F112: =F60 | G112: =G60 | H112: =H60 | I112: =I60 | J112: =J60 | K112: =IF(AND(ISBLANK(K60),NOT(ISBLANK(L60))),$I60,0) -> 0 | L112: =IF(AND(ISBLANK(L60),NOT(ISBLANK(M60))),$I60,0) -> 0 | M112: =IF(AND(ISBLANK(M60),NOT(ISBLANK(N60))),$I60,0) -> 0 | N112: =IF(AND(ISBLANK(N60),NOT(ISBLANK(O60))),$I60,0) -> 0 | O112: =IF(AND(ISBLANK(O60),NOT(ISBLANK(P60))),$I60,0) -> 0 | P112: =IF(AND(ISBLANK(P60),NOT(ISBLANK(Q60))),$I60,0) -> 0 | Q112: =IF(AND(ISBLANK(Q60),NOT(ISBLANK(R60))),$I60,0) -> 0 | R112: =IF(AND(ISBLANK(R60),NOT(ISBLANK(S60))),$I60,0) -> 0 | ... AD112: =IF(AND(ISBLANK(AD60),NOT(ISBLANK(AE60))),$I60,0) -> 0
C113: =C61 -> -- | D113: =D61 | E113: =E61 | F113: =F61 | G113: =G61 | H113: =H61 | I113: =I61 | J113: =J61 | K113: =IF(AND(ISBLANK(K61),NOT(ISBLANK(L61))),$I61,0) -> 0 | L113: =IF(AND(ISBLANK(L61),NOT(ISBLANK(M61))),$I61,0) -> 0 | M113: =IF(AND(ISBLANK(M61),NOT(ISBLANK(N61))),$I61,0) -> 0 | N113: =IF(AND(ISBLANK(N61),NOT(ISBLANK(O61))),$I61,0) -> 0 | O113: =IF(AND(ISBLANK(O61),NOT(ISBLANK(P61))),$I61,0) -> 0 | P113: =IF(AND(ISBLANK(P61),NOT(ISBLANK(Q61))),$I61,0) -> 0 | Q113: =IF(AND(ISBLANK(Q61),NOT(ISBLANK(R61))),$I61,0) -> 0 | R113: =IF(AND(ISBLANK(R61),NOT(ISBLANK(S61))),$I61,0) -> 0 | ... AD113: =IF(AND(ISBLANK(AD61),NOT(ISBLANK(AE61))),$I61,0) -> 0
C114: =C62 -> -- | D114: =D62 | E114: =E62 | F114: =F62 | G114: =G62 | H114: =H62 | I114: =I62 | J114: =J62 | K114: =IF(AND(ISBLANK(K62),NOT(ISBLANK(L62))),$I62,0) -> 0 | L114: =IF(AND(ISBLANK(L62),NOT(ISBLANK(M62))),$I62,0) -> 0 | M114: =IF(AND(ISBLANK(M62),NOT(ISBLANK(N62))),$I62,0) -> 0 | N114: =IF(AND(ISBLANK(N62),NOT(ISBLANK(O62))),$I62,0) -> 0 | O114: =IF(AND(ISBLANK(O62),NOT(ISBLANK(P62))),$I62,0) -> 0 | P114: =IF(AND(ISBLANK(P62),NOT(ISBLANK(Q62))),$I62,0) -> 0 | Q114: =IF(AND(ISBLANK(Q62),NOT(ISBLANK(R62))),$I62,0) -> 0 | R114: =IF(AND(ISBLANK(R62),NOT(ISBLANK(S62))),$I62,0) -> 0 | ... AD114: =IF(AND(ISBLANK(AD62),NOT(ISBLANK(AE62))),$I62,0) -> 0
... C123: =C71 -> -- | D123: =D71 | E123: =E71 | F123: =F71 | G123: =G71 | H123: =H71 | I123: =I71 | J123: =J71 | K123: =IF(AND(ISBLANK(K71),NOT(ISBLANK(L71))),$I71,0) -> 0 | L123: =IF(AND(ISBLANK(L71),NOT(ISBLANK(M71))),$I71,0) -> 0 | M123: =IF(AND(ISBLANK(M71),NOT(ISBLANK(N71))),$I71,0) -> 0 | N123: =IF(AND(ISBLANK(N71),NOT(ISBLANK(O71))),$I71,0) -> 0 | O123: =IF(AND(ISBLANK(O71),NOT(ISBLANK(P71))),$I71,0) -> 0 | P123: =IF(AND(ISBLANK(P71),NOT(ISBLANK(Q71))),$I71,0) -> 0 | Q123: =IF(AND(ISBLANK(Q71),NOT(ISBLANK(R71))),$I71,0) -> 0 | R123: =IF(AND(ISBLANK(R71),NOT(ISBLANK(S71))),$I71,0) -> 0 | ... AD123: =IF(AND(ISBLANK(AD71),NOT(ISBLANK(AE71))),$I71,0) -> 0
K151: 2024 | L151: 2024.25 | M151: 2024.5 | N151: 2024.75 | O151: 2025 | P151: 2025.25 | Q151: =P151+0.25 -> 2025.5 | R151: =Q151+0.25 -> 2025.75 | S151: =R151+0.25 -> 2026 | T151: =S151+0.25 -> 2026.25 | U151: =T151+0.25 -> 2026.5 | V151: =U151+0.25 -> 2026.75 | W151: =V151+0.25 -> 2027 | X151: =W151+0.25 -> 2027.25 | ... AD151: =AC151+0.25 -> 2028.75
J152: GPU | K152: =SUMIF($F$156:$F$176,$J152,K$156:K$176) -> 24 | L152: =SUMIF($F$156:$F$176,$J152,L$156:L$176) -> 24 | M152: =SUMIF($F$156:$F$176,$J152,M$156:M$176) -> 24 | N152: =SUMIF($F$156:$F$176,$J152,N$156:N$176) -> 24 | O152: =SUMIF($F$156:$F$176,$J152,O$156:O$176) -> 24 | P152: =SUMIF($F$156:$F$176,$J152,P$156:P$176) -> 24 | Q152: =SUMIF($F$156:$F$176,$J152,Q$156:Q$176) -> 40 | R152: =SUMIF($F$156:$F$176,$J152,R$156:R$176) -> 40 | ... AD152: =SUMIF($F$156:$F$176,$J152,AD$156:AD$176) -> 40
J153: CPU | K153: =SUMIF($F$156:$F$176,$J153,K$156:K$176) -> 19200 | L153: =SUMIF($F$156:$F$176,$J153,L$156:L$176) -> 19200 | M153: =SUMIF($F$156:$F$176,$J153,M$156:M$176) -> 19200 | N153: =SUMIF($F$156:$F$176,$J153,N$156:N$176) -> 19200 | O153: =SUMIF($F$156:$F$176,$J153,O$156:O$176) -> 19200 | P153: =SUMIF($F$156:$F$176,$J153,P$156:P$176) -> 19200 | Q153: =SUMIF($F$156:$F$176,$J153,Q$156:Q$176) -> 21760 | R153: =SUMIF($F$156:$F$176,$J153,R$156:R$176) -> 21760 | ... AD153: =SUMIF($F$156:$F$176,$J153,AD$156:AD$176) -> 21760
J154: Hdisk | K154: =SUMIF($F$156:$F$176,$J154,K$156:K$176) -> 74.2 | L154: =SUMIF($F$156:$F$176,$J154,L$156:L$176) -> 74.2 | M154: =SUMIF($F$156:$F$176,$J154,M$156:M$176) -> 74.2 | N154: =SUMIF($F$156:$F$176,$J154,N$156:N$176) -> 74.2 | O154: =SUMIF($F$156:$F$176,$J154,O$156:O$176) -> 74.2 | P154: =SUMIF($F$156:$F$176,$J154,P$156:P$176) -> 74.2 | Q154: =SUMIF($F$156:$F$176,$J154,Q$156:Q$176) -> 84.8 | R154: =SUMIF($F$156:$F$176,$J154,R$156:R$176) -> 84.8 | ... AD154: =SUMIF($F$156:$F$176,$J154,AD$156:AD$176) -> 84.8
J155: Sdisk | K155: =SUMIF($F$156:$F$176,$J155,K$156:K$176) -> 5.4 | L155: =SUMIF($F$156:$F$176,$J155,L$156:L$176) -> 5.4 | M155: =SUMIF($F$156:$F$176,$J155,M$156:M$176) -> 5.4 | N155: =SUMIF($F$156:$F$176,$J155,N$156:N$176) -> 5.4 | O155: =SUMIF($F$156:$F$176,$J155,O$156:O$176) -> 5.4 | P155: =SUMIF($F$156:$F$176,$J155,P$156:P$176) -> 5.4 | Q155: =SUMIF($F$156:$F$176,$J155,Q$156:Q$176) -> 10.2 | R155: =SUMIF($F$156:$F$176,$J155,R$156:R$176) -> 10.2 | ... AD155: =SUMIF($F$156:$F$176,$J155,AD$156:AD$176) -> 10.2
C156: =C103 -> HPC1 | F156: =F103 -> CPU | K156: =IF(NOT(ISBLANK(K51)),$J51,0) -> 19200 | L156: =IF(NOT(ISBLANK(L51)),$J51,0) -> 19200 | M156: =IF(NOT(ISBLANK(M51)),$J51,0) -> 19200 | N156: =IF(NOT(ISBLANK(N51)),$J51,0) -> 19200 | O156: =IF(NOT(ISBLANK(O51)),$J51,0) -> 19200 | P156: =IF(NOT(ISBLANK(P51)),$J51,0) -> 19200 | Q156: =IF(NOT(ISBLANK(Q51)),$J51,0) -> 19200 | R156: =IF(NOT(ISBLANK(R51)),$J51,0) -> 19200 | ... AD156: =IF(NOT(ISBLANK(AD51)),$J51,0) -> 19200
C157: =C104 -> V100-4 | F157: =F104 -> GPU | K157: =IF(NOT(ISBLANK(K52)),$J52,0) -> 24 | L157: =IF(NOT(ISBLANK(L52)),$J52,0) -> 24 | M157: =IF(NOT(ISBLANK(M52)),$J52,0) -> 24 | N157: =IF(NOT(ISBLANK(N52)),$J52,0) -> 24 | O157: =IF(NOT(ISBLANK(O52)),$J52,0) -> 24 | P157: =IF(NOT(ISBLANK(P52)),$J52,0) -> 24 | Q157: =IF(NOT(ISBLANK(Q52)),$J52,0) -> 24 | R157: =IF(NOT(ISBLANK(R52)),$J52,0) -> 24 | ... AD157: =IF(NOT(ISBLANK(AD52)),$J52,0) -> 24
C158: =C105 -> HDD | F158: =F105 -> Hdisk | K158: =IF(NOT(ISBLANK(K53)),$J53,0) -> 74.2 | L158: =IF(NOT(ISBLANK(L53)),$J53,0) -> 74.2 | M158: =IF(NOT(ISBLANK(M53)),$J53,0) -> 74.2 | N158: =IF(NOT(ISBLANK(N53)),$J53,0) -> 74.2 | O158: =IF(NOT(ISBLANK(O53)),$J53,0) -> 74.2 | P158: =IF(NOT(ISBLANK(P53)),$J53,0) -> 74.2 | Q158: =IF(NOT(ISBLANK(Q53)),$J53,0) -> 74.2 | R158: =IF(NOT(ISBLANK(R53)),$J53,0) -> 74.2 | ... AD158: =IF(NOT(ISBLANK(AD53)),$J53,0) -> 74.2
C159: =C106 -> SSD | F159: =F106 -> Sdisk | K159: =IF(NOT(ISBLANK(K54)),$J54,0) -> 5.4 | L159: =IF(NOT(ISBLANK(L54)),$J54,0) -> 5.4 | M159: =IF(NOT(ISBLANK(M54)),$J54,0) -> 5.4 | N159: =IF(NOT(ISBLANK(N54)),$J54,0) -> 5.4 | O159: =IF(NOT(ISBLANK(O54)),$J54,0) -> 5.4 | P159: =IF(NOT(ISBLANK(P54)),$J54,0) -> 5.4 | Q159: =IF(NOT(ISBLANK(Q54)),$J54,0) -> 5.4 | R159: =IF(NOT(ISBLANK(R54)),$J54,0) -> 5.4 | ... AD159: =IF(NOT(ISBLANK(AD54)),$J54,0) -> 5.4
C160: =C107 -> H100-4 | F160: =F107 -> GPU | K160: =IF(NOT(ISBLANK(K55)),$J55,0) -> 0 | L160: =IF(NOT(ISBLANK(L55)),$J55,0) -> 0 | M160: =IF(NOT(ISBLANK(M55)),$J55,0) -> 0 | N160: =IF(NOT(ISBLANK(N55)),$J55,0) -> 0 | O160: =IF(NOT(ISBLANK(O55)),$J55,0) -> 0 | P160: =IF(NOT(ISBLANK(P55)),$J55,0) -> 0 | Q160: =IF(NOT(ISBLANK(Q55)),$J55,0) -> 16 | R160: =IF(NOT(ISBLANK(R55)),$J55,0) -> 16 | ... AD160: =IF(NOT(ISBLANK(AD55)),$J55,0) -> 16
C161: =C108 -> HPC2 | F161: =F108 -> CPU | K161: =IF(NOT(ISBLANK(K56)),$J56,0) -> 0 | L161: =IF(NOT(ISBLANK(L56)),$J56,0) -> 0 | M161: =IF(NOT(ISBLANK(M56)),$J56,0) -> 0 | N161: =IF(NOT(ISBLANK(N56)),$J56,0) -> 0 | O161: =IF(NOT(ISBLANK(O56)),$J56,0) -> 0 | P161: =IF(NOT(ISBLANK(P56)),$J56,0) -> 0 | Q161: =IF(NOT(ISBLANK(Q56)),$J56,0) -> 2560 | R161: =IF(NOT(ISBLANK(R56)),$J56,0) -> 2560 | ... AD161: =IF(NOT(ISBLANK(AD56)),$J56,0) -> 2560
C162: =C109 -> HDD | F162: =F109 -> Hdisk | K162: =IF(NOT(ISBLANK(K57)),$J57,0) -> 0 | L162: =IF(NOT(ISBLANK(L57)),$J57,0) -> 0 | M162: =IF(NOT(ISBLANK(M57)),$J57,0) -> 0 | N162: =IF(NOT(ISBLANK(N57)),$J57,0) -> 0 | O162: =IF(NOT(ISBLANK(O57)),$J57,0) -> 0 | P162: =IF(NOT(ISBLANK(P57)),$J57,0) -> 0 | Q162: =IF(NOT(ISBLANK(Q57)),$J57,0) -> 10.6 | R162: =IF(NOT(ISBLANK(R57)),$J57,0) -> 10.6 | ... AD162: =IF(NOT(ISBLANK(AD57)),$J57,0) -> 10.6
C163: =C110 -> SSD | F163: =F110 -> Sdisk | K163: =IF(NOT(ISBLANK(K58)),$J58,0) -> 0 | L163: =IF(NOT(ISBLANK(L58)),$J58,0) -> 0 | M163: =IF(NOT(ISBLANK(M58)),$J58,0) -> 0 | N163: =IF(NOT(ISBLANK(N58)),$J58,0) -> 0 | O163: =IF(NOT(ISBLANK(O58)),$J58,0) -> 0 | P163: =IF(NOT(ISBLANK(P58)),$J58,0) -> 0 | Q163: =IF(NOT(ISBLANK(Q58)),$J58,0) -> 4.8 | R163: =IF(NOT(ISBLANK(R58)),$J58,0) -> 4.8 | ... AD163: =IF(NOT(ISBLANK(AD58)),$J58,0) -> 4.8
C164: =C111 -> -- | F164: =F111 | K164: =IF(NOT(ISBLANK(K59)),$J59,0) -> 0 | L164: =IF(NOT(ISBLANK(L59)),$J59,0) -> 0 | M164: =IF(NOT(ISBLANK(M59)),$J59,0) -> 0 | N164: =IF(NOT(ISBLANK(N59)),$J59,0) -> 0 | O164: =IF(NOT(ISBLANK(O59)),$J59,0) -> 0 | P164: =IF(NOT(ISBLANK(P59)),$J59,0) -> 0 | Q164: =IF(NOT(ISBLANK(Q59)),$J59,0) -> 0 | R164: =IF(NOT(ISBLANK(R59)),$J59,0) -> 0 | ... AD164: =IF(NOT(ISBLANK(AD59)),$J59,0)
C165: =C112 -> -- | F165: =F112 | K165: =IF(NOT(ISBLANK(K60)),$J60,0) -> 0 | L165: =IF(NOT(ISBLANK(L60)),$J60,0) -> 0 | M165: =IF(NOT(ISBLANK(M60)),$J60,0) -> 0 | N165: =IF(NOT(ISBLANK(N60)),$J60,0) -> 0 | O165: =IF(NOT(ISBLANK(O60)),$J60,0) -> 0 | P165: =IF(NOT(ISBLANK(P60)),$J60,0) -> 0 | Q165: =IF(NOT(ISBLANK(Q60)),$J60,0) -> 0 | R165: =IF(NOT(ISBLANK(R60)),$J60,0) -> 0 | ... AD165: =IF(NOT(ISBLANK(AD60)),$J60,0) -> 0
...

Sheet Baseline Power
J1: this is to account for legacy power (this comes off the calculation)
C3: Calendar Years | D3: Total available power for new computing | I3: IT load used by existing equipment (post Phase I) | N3: Total lT load capacity | T3: Total mechanical load
C4: 0.25 | D4: MARCC | E4: IDIES | F4: Mt. Wash | G4: BayView+ | H4: Total | I4: MARCC | J4: IDIES | K4: Mt. Wash | L4: BayView+ | M4: Total | N4: MARCC | O4: IDIES | P4: Mt. Wash | Q4: BayView+ | R4: BV total | S4: Total | T4: MARCC | U4: IDIES | V4: Mt. Wash | W4: BayView+ | X4: Total
C5: 2024 | D5: =N5-I5 -> 0.45 | E5: =O5-J5 -> 0.125 | F5: =P5-K5 -> 0.37 | G5: =Q5-L5 -> 0 | H5: =SUM(D5:G5) -> 0.945 | I5: 0.75 | J5: 0.325 | K5: 0.68 | L5: 0 | N5: 1.2 | O5: 0.45 | P5: 1.05 | Q5: 0 | R5: =N5+Q5 -> 1.2 | S5: =SUM(N5:Q5) -> 2.7 | T5: 0.3 | U5: 0.1 | V5: 0.4
C6: =C5+$C$4 -> 2024.25 | D6: =N6-I6 -> 0.45 | E6: =O6-J6 -> 0.125 | F6: =P6-K6 -> 0.37 | G6: =Q6-L6 -> 0 | H6: =SUM(D6:G6) -> 0.945 | I6: 0.75 | J6: 0.325 | K6: 0.68 | L6: 0 | N6: 1.2 | O6: 0.45 | P6: 1.05 | Q6: 0 | R6: =N6+Q6 -> 1.2 | S6: =SUM(N6:Q6) -> 2.7 | T6: 0.3 | U6: 0.1 | V6: 0.4
C7: =C6+$C$4 -> 2024.5 | D7: =N7-I7 -> 0.1 | E7: =O7-J7 -> 0.125 | F7: =P7-K7 -> 0.37 | G7: =Q7-L7 -> 0 | H7: =SUM(D7:G7) -> 0.595 | I7: 1.1 | J7: 0.325 | K7: 0.68 | L7: 0 | N7: 1.2 | O7: 0.45 | P7: 1.05 | Q7: 0 | R7: =N7+Q7 -> 1.2 | S7: =SUM(N7:Q7) -> 2.7 | T7: 0.3 | U7: 0.1 | V7: 0.4
C8: =C7+$C$4 -> 2024.75 | D8: =N8-I8 -> 0.1 | E8: =O8-J8 -> 0.125 | F8: =P8-K8 -> 0.47 | G8: =Q8-L8 -> 0 | H8: =SUM(D8:G8) -> 0.695 | I8: 1.1 | J8: 0.325 | K8: 0.58 | L8: 0 | N8: 1.2 | O8: 0.45 | P8: 1.05 | Q8: 0 | R8: =N8+Q8 -> 1.2 | S8: =SUM(N8:Q8) -> 2.7 | T8: 0.3 | U8: 0.1 | V8: 0.4
C9: =C8+$C$4 -> 2025 | D9: =N9-I9 -> 0 | E9: =O9-J9 -> 0.1 | F9: =P9-K9 -> 0.4 | G9: =Q9-L9 -> 0 | H9: =SUM(D9:G9) -> 0.5 | I9: 1.2 | J9: 0.35 | K9: 0.65 | L9: 0 | N9: 1.2 | O9: 0.45 | P9: 1.05 | Q9: 0 | R9: =N9+Q9 -> 1.2 | S9: =SUM(N9:Q9) -> 2.7 | T9: 0.3 | U9: 0.1 | V9: 0.4
C10: =C9+$C$4 -> 2025.25 | D10: =N10-I10 -> 0 | E10: =O10-J10 -> 0.1 | F10: =P10-K10 -> 0.4 | G10: =Q10-L10 -> 0 | H10: =SUM(D10:G10) -> 0.5 | I10: 1.2 | J10: 0.35 | K10: 0.65 | L10: 0 | N10: 1.2 | O10: 0.45 | P10: 1.05 | Q10: 0 | R10: =N10+Q10 -> 1.2 | S10: =SUM(N10:Q10) -> 2.7 | T10: 0.3 | U10: 0.1 | V10: 0.4
C11: =C10+$C$4 -> 2025.5 | D11: =N11-I11 -> 0 | E11: =O11-J11 -> 0.1 | F11: =P11-K11 -> 0.4 | G11: =Q11-L11 -> 0 | H11: =SUM(D11:G11) -> 0.5 | I11: 1.2 | J11: 0.35 | K11: 0.65 | L11: 0 | N11: 1.2 | O11: 0.45 | P11: 1.05 | Q11: 0 | R11: =N11+Q11 -> 1.2 | S11: =SUM(N11:Q11) -> 2.7 | T11: 0.3 | U11: 0.15 | V11: 0.4
C12: =C11+$C$4 -> 2025.75 | D12: =N12-I12 -> 0.8 | E12: =O12-J12 -> 0.1 | F12: =P12-K12 -> 0.4 | G12: =Q12-L12 -> 0 | H12: =SUM(D12:G12) -> 1.3 | I12: 1.2 | J12: 0.35 | K12: 0.65 | L12: 0 | N12: 2 | O12: 0.45 | P12: 1.05 | Q12: 0 | R12: =N12+Q12 -> 2 | S12: =SUM(N12:Q12) -> 3.5 | T12: 0.4 | U12: 0.15 | V12: 0.4
C13: =C12+$C$4 -> 2026 | D13: =N13-I13 -> 0.8 | E13: =O13-J13 -> 0.1 | F13: =P13-K13 -> 0.4 | G13: =Q13-L13 -> 0 | H13: =SUM(D13:G13) -> 1.3 | I13: 1.2 | J13: 0.35 | K13: 0.65 | L13: 0 | N13: 2 | O13: 0.45 | P13: 1.05 | Q13: 0 | R13: =N13+Q13 -> 2 | S13: =SUM(N13:Q13) -> 3.5 | T13: 0.4 | U13: 0.15 | V13: 0.4
C14: =C13+$C$4 -> 2026.25 | D14: =N14-I14 -> 0.8 | E14: =O14-J14 -> 0.1 | F14: =P14-K14 -> 0.4 | G14: =Q14-L14 -> 0 | H14: =SUM(D14:G14) -> 1.3 | I14: 1.2 | J14: 0.35 | K14: 0.65 | L14: 0 | N14: 2 | O14: 0.45 | P14: 1.05 | Q14: 0 | R14: =N14+Q14 -> 2 | S14: =SUM(N14:Q14) -> 3.5 | T14: 0.4 | U14: 0.15 | V14: 0.4
C15: =C14+$C$4 -> 2026.5 | D15: =N15-I15 -> 0.8 | E15: =O15-J15 -> 0.1 | F15: =P15-K15 -> 0.4 | G15: =Q15-L15 -> 0 | H15: =SUM(D15:G15) -> 1.3 | I15: 1.2 | J15: 0.35 | K15: 0.65 | L15: 0 | N15: 2 | O15: 0.45 | P15: 1.05 | Q15: 0 | R15: =N15+Q15 -> 2 | S15: =SUM(N15:Q15) -> 3.5 | T15: 0.4 | U15: 0.15 | V15: 0.4
C16: =C15+$C$4 -> 2026.75 | D16: =N16-I16 -> 0.8 | E16: =O16-J16 -> 0.1 | F16: =P16-K16 -> 0.4 | G16: =Q16-L16 -> 0 | H16: =SUM(D16:G16) -> 1.3 | I16: 1.2 | J16: 0.35 | K16: 0.65 | L16: 0 | N16: 2 | O16: 0.45 | P16: 1.05 | Q16: 0 | R16: =N16+Q16 -> 2 | S16: =SUM(N16:Q16) -> 3.5 | T16: 0.4 | U16: 0.15 | V16: 0.4
C17: =C16+$C$4 -> 2027 | D17: =N17-I17 -> 1.35 | E17: =O17-J17 -> 0.1 | F17: =P17-K17 -> 0.4 | G17: =Q17-L17 -> 0 | H17: =SUM(D17:G17) -> 1.85 | I17: 0.65 | J17: 0.35 | K17: 0.65 | L17: 0 | N17: 2 | O17: 0.45 | P17: 1.05 | Q17: 0 | R17: =N17+Q17 -> 2 | S17: =SUM(N17:Q17) -> 3.5 | T17: 0.4 | U17: 0.15 | V17: 0.8
C18: =C17+$C$4 -> 2027.25 | D18: =N18-I18 -> 1.35 | E18: =O18-J18 -> 0.1 | F18: =P18-K18 -> 0.4 | G18: =Q18-L18 -> 5 | H18: =SUM(D18:G18) -> 6.85 | I18: 0.65 | J18: 0.35 | K18: 0.65 | L18: 0 | N18: 2 | O18: 0.45 | P18: 1.05 | Q18: 5 | R18: =N18+Q18 -> 7 | S18: =SUM(N18:Q18) -> 8.5 | T18: 0.4 | U18: 0.15 | V18: 0.8 | W18: 0.8
C19: =C18+$C$4 -> 2027.5 | D19: =N19-I19 -> 1.35 | E19: =O19-J19 -> 0.1 | F19: =P19-K19 -> 0.4 | G19: =Q19-L19 -> 5 | H19: =SUM(D19:G19) -> 6.85 | I19: 0.65 | J19: 0.35 | K19: 0.65 | L19: 0 | N19: 2 | O19: 0.45 | P19: 1.05 | Q19: 5 | R19: =N19+Q19 -> 7 | S19: =SUM(N19:Q19) -> 8.5 | T19: 0.4 | U19: 0.15 | V19: 0.8 | W19: 0.8
C20: =C19+$C$4 -> 2027.75 | D20: =N20-I20 -> 1.35 | E20: =O20-J20 -> 0.1 | F20: =P20-K20 -> 0.4 | G20: =Q20-L20 -> 5 | H20: =SUM(D20:G20) -> 6.85 | I20: 0.65 | J20: 0.35 | K20: 0.65 | L20: 0 | N20: 2 | O20: 0.45 | P20: 1.05 | Q20: 5 | R20: =N20+Q20 -> 7 | S20: =SUM(N20:Q20) -> 8.5 | T20: 0.4 | U20: 0.15 | V20: 0.8 | W20: 0.8
C21: =C20+$C$4 -> 2028 | D21: =N21-I21 -> 1.55 | E21: =O21-J21 -> 0.1 | F21: =P21-K21 -> 2.2 | G21: =Q21-L21 -> 5 | H21: =SUM(D21:G21) -> 8.85 | I21: 0.45 | J21: 0.35 | K21: 0.65 | L21: 0 | N21: 2 | O21: 0.45 | P21: 2.85 | Q21: 5 | R21: =N21+Q21 -> 7 | S21: =SUM(N21:Q21) -> 10.3 | T21: 0.4 | U21: 0.15 | V21: 0.8 | W21: 0.8
C22: =C21+$C$4 -> 2028.25 | D22: =N22-I22 -> 1.35 | E22: =O22-J22 -> 0 | F22: =P22-K22 -> 2.2 | G22: =Q22-L22 -> 5 | H22: =SUM(D22:G22) -> 8.55 | I22: 0.65 | J22: 0 | K22: 0.65 | L22: 0 | N22: 2 | O22: 0 | P22: 2.85 | Q22: 5 | R22: =N22+Q22 -> 7 | S22: =SUM(N22:Q22) -> 9.85 | T22: 0.4 | U22: 0 | V22: 0.8 | W22: 0.8
C23: =C22+$C$4 -> 2028.5 | D23: =N23-I23 -> 1.35 | E23: =O23-J23 -> 0 | F23: =P23-K23 -> 2.2 | G23: =Q23-L23 -> 5 | H23: =SUM(D23:G23) -> 8.55 | I23: 0.65 | J23: 0 | K23: 0.65 | L23: 0 | N23: 2 | O23: 0 | P23: 2.85 | Q23: 5 | R23: =N23+Q23 -> 7 | S23: =SUM(N23:Q23) -> 9.85 | T23: 0.4 | U23: 0 | V23: 0.8 | W23: 0.8
C24: =C23+$C$4 -> 2028.75 | D24: =N24-I24 -> 1.35 | E24: =O24-J24 -> 0 | F24: =P24-K24 -> 2.2 | G24: =Q24-L24 -> 5 | H24: =SUM(D24:G24) -> 8.55 | I24: 0.65 | J24: 0 | K24: 0.65 | L24: 0 | N24: 2 | O24: 0 | P24: 2.85 | Q24: 5 | R24: =N24+Q24 -> 7 | S24: =SUM(N24:Q24) -> 9.85 | T24: 0.4 | U24: 0 | V24: 0.8 | W24: 0.8
C25: =C24+$C$4 -> 2029 | D25: =N25-I25 -> 1.35 | E25: =O25-J25 -> 0 | F25: =P25-K25 -> 2.2 | G25: =Q25-L25 -> 5 | H25: =SUM(D25:G25) -> 8.55 | I25: 0.65 | J25: 0 | K25: 0.65 | L25: 0 | N25: 2 | O25: 0 | P25: 2.85 | Q25: 5 | R25: =N25+Q25 -> 7 | S25: =SUM(N25:Q25) -> 9.85 | T25: 0.4 | U25: 0 | V25: 0.8 | W25: 0.8
C26: =C25+$C$4 -> 2029.25 | D26: =N26-I26 -> 1.35 | E26: =O26-J26 -> 0 | F26: =P26-K26 -> 2.2 | G26: =Q26-L26 -> 5 | H26: =SUM(D26:G26) -> 8.55 | I26: 0.65 | J26: 0 | K26: 0.65 | L26: 0 | N26: 2 | O26: 0 | P26: 2.85 | Q26: 5 | R26: =N26+Q26 -> 7 | S26: =SUM(N26:Q26) -> 9.85 | T26: 0.4 | U26: 0 | V26: 0.8 | W26: 0.8
C27: =C26+$C$4 -> 2029.5 | D27: =N27-I27 -> 1.35 | E27: =O27-J27 -> 0 | F27: =P27-K27 -> 2.2 | G27: =Q27-L27 -> 5 | H27: =SUM(D27:G27) -> 8.55 | I27: 0.65 | J27: 0 | K27: 0.65 | L27: 0 | N27: 2 | O27: 0 | P27: 2.85 | Q27: 5 | R27: =N27+Q27 -> 7 | S27: =SUM(N27:Q27) -> 9.85 | T27: 0.4 | U27: 0 | V27: 0.8 | W27: 0.8
C28: =C27+$C$4 -> 2029.75 | D28: =N28-I28 -> 1.35 | E28: =O28-J28 -> 0 | F28: =P28-K28 -> 2.2 | G28: =Q28-L28 -> 5 | H28: =SUM(D28:G28) -> 8.55 | I28: 0.65 | J28: 0 | K28: 0.65 | L28: 0 | N28: 2 | O28: 0 | P28: 2.85 | Q28: 5 | R28: =N28+Q28 -> 7 | S28: =SUM(N28:Q28) -> 9.85 | T28: 0.4 | U28: 0 | V28: 0.8 | W28: 0.8
C29: =C28+$C$4 -> 2030 | D29: =N29-I29 -> 1.35 | E29: =O29-J29 -> 0 | F29: =P29-K29 -> 2.2 | G29: =Q29-L29 -> 5 | H29: =SUM(D29:G29) -> 8.55 | I29: 0.65 | J29: 0 | K29: 0.65 | L29: 0 | N29: 2 | O29: 0 | P29: 2.85 | Q29: 5 | R29: =N29+Q29 -> 7 | S29: =SUM(N29:Q29) -> 9.85 | T29: 0.4 | U29: 0 | V29: 0.8 | W29: 0.8
H32: don't change anything in the helper tables - there are for visualization purposes
C33: Helper table for the stairs plot | M33: Helper table for the stairs plot
C34: 2024 | D34: =D5 -> 0.45 | E34: =E5 -> 0.125 | F34: =F5 -> 0.37 | G34: =G5 -> 0 | H34: =H5 -> 0.945 | M34: 2024 | N34: =N5 -> 1.2 | O34: =O5 -> 0.45 | P34: =P5 -> 1.05 | Q34: =Q5 -> 0 | R34: =R5 -> 1.2 | S34: =S5 -> 2.7
C35: 2024.25 | D35: =D34 -> 0.45 | E35: =E34 -> 0.125 | F35: =F34 -> 0.37 | G35: =G34 -> 0 | H35: =H34 -> 0.945 | M35: 2024.25 | N35: =N34 -> 1.2 | O35: =O34 -> 0.45 | P35: =P34 -> 1.05 | Q35: =Q34 -> 0 | R35: =R34 -> 1.2 | S35: =S34 -> 2.7
C36: =C35 -> 2024.25 | D36: =D6 -> 0.45 | E36: =E6 -> 0.125 | F36: =F6 -> 0.37 | G36: =G6 -> 0 | H36: =H6 -> 0.945 | M36: =M35 -> 2024.25 | N36: =N6 -> 1.2 | O36: =O6 -> 0.45 | P36: =P6 -> 1.05 | Q36: =Q6 -> 0 | R36: =R6 -> 1.2 | S36: =S6 -> 2.7
C37: 2024.5 | D37: =D36 -> 0.45 | E37: =E36 -> 0.125 | F37: =F36 -> 0.37 | G37: =G36 -> 0 | H37: =H36 -> 0.945 | M37: 2024.5 | N37: =N36 -> 1.2 | O37: =O36 -> 0.45 | P37: =P36 -> 1.05 | Q37: =Q36 -> 0 | R37: =R36 -> 1.2 | S37: =S36 -> 2.7
C38: =C37 -> 2024.5 | D38: =D7 -> 0.1 | E38: =E7 -> 0.125 | F38: =F7 -> 0.37 | G38: =G7 -> 0 | H38: =H7 -> 0.595 | M38: =M37 -> 2024.5 | N38: =N7 -> 1.2 | O38: =O7 -> 0.45 | P38: =P7 -> 1.05 | Q38: =Q7 -> 0 | R38: =R7 -> 1.2 | S38: =S7 -> 2.7
C39: 2024.75 | D39: =D38 -> 0.1 | E39: =E38 -> 0.125 | F39: =F38 -> 0.37 | G39: =G38 -> 0 | H39: =H38 -> 0.595 | M39: 2024.75 | N39: =N38 -> 1.2 | O39: =O38 -> 0.45 | P39: =P38 -> 1.05 | Q39: =Q38 -> 0 | R39: =R38 -> 1.2 | S39: =S38 -> 2.7
C40: =C39 -> 2024.75 | D40: =D8 -> 0.1 | E40: =E8 -> 0.125 | F40: =F8 -> 0.47 | G40: =G8 -> 0 | H40: =H8 -> 0.695 | M40: =M39 -> 2024.75 | N40: =N8 -> 1.2 | O40: =O8 -> 0.45 | P40: =P8 -> 1.05 | Q40: =Q8 -> 0 | R40: =R8 -> 1.2 | S40: =S8 -> 2.7
C41: 2025 | D41: =D40 -> 0.1 | E41: =E40 -> 0.125 | F41: =F40 -> 0.47 | G41: =G40 -> 0 | H41: =H40 -> 0.695 | M41: 2025 | N41: =N40 -> 1.2 | O41: =O40 -> 0.45 | P41: =P40 -> 1.05 | Q41: =Q40 -> 0 | R41: =R40 -> 1.2 | S41: =S40 -> 2.7
C42: =C41 -> 2025 | D42: =D9 -> 0 | E42: =E9 -> 0.1 | F42: =F9 -> 0.4 | G42: =G9 -> 0 | H42: =H9 -> 0.5 | M42: =M41 -> 2025 | N42: =N9 -> 1.2 | O42: =O9 -> 0.45 | P42: =P9 -> 1.05 | Q42: =Q9 -> 0 | R42: =R9 -> 1.2 | S42: =S9 -> 2.7
C43: 2025.25 | D43: =D42 -> 0 | E43: =E42 -> 0.1 | F43: =F42 -> 0.4 | G43: =G42 -> 0 | H43: =H42 -> 0.5 | M43: 2025.25 | N43: =N42 -> 1.2 | O43: =O42 -> 0.45 | P43: =P42 -> 1.05 | Q43: =Q42 -> 0 | R43: =R42 -> 1.2 | S43: =S42 -> 2.7
C44: =C43 -> 2025.25 | D44: =D10 -> 0 | E44: =E10 -> 0.1 | F44: =F10 -> 0.4 | G44: =G10 -> 0 | H44: =H10 -> 0.5 | M44: =M43 -> 2025.25 | N44: =N10 -> 1.2 | O44: =O10 -> 0.45 | P44: =P10 -> 1.05 | Q44: =Q10 -> 0 | R44: =R10 -> 1.2 | S44: =S10 -> 2.7
C45: 2025.5 | D45: =D44 -> 0 | E45: =E44 -> 0.1 | F45: =F44 -> 0.4 | G45: =G44 -> 0 | H45: =H44 -> 0.5 | M45: 2025.5 | N45: =N44 -> 1.2 | O45: =O44 -> 0.45 | P45: =P44 -> 1.05 | Q45: =Q44 -> 0 | R45: =R44 -> 1.2 | S45: =S44 -> 2.7
C46: =C45 -> 2025.5 | D46: =D11 -> 0 | E46: =E11 -> 0.1 | F46: =F11 -> 0.4 | G46: =G11 -> 0 | H46: =H11 -> 0.5 | M46: =M45 -> 2025.5 | N46: =N11 -> 1.2 | O46: =O11 -> 0.45 | P46: =P11 -> 1.05 | Q46: =Q11 -> 0 | R46: =R11 -> 1.2 | S46: =S11 -> 2.7
C47: 2025.75 | D47: =D46 -> 0 | E47: =E46 -> 0.1 | F47: =F46 -> 0.4 | G47: =G46 -> 0 | H47: =H46 -> 0.5 | M47: 2025.75 | N47: =N46 -> 1.2 | O47: =O46 -> 0.45 | P47: =P46 -> 1.05 | Q47: =Q46 -> 0 | R47: =R46 -> 1.2 | S47: =S46 -> 2.7
C48: =C47 -> 2025.75 | D48: =D12 -> 0.8 | E48: =E12 -> 0.1 | F48: =F12 -> 0.4 | G48: =G12 -> 0 | H48: =H12 -> 1.3 | M48: =M47 -> 2025.75 | N48: =N12 -> 2 | O48: =O12 -> 0.45 | P48: =P12 -> 1.05 | Q48: =Q12 -> 0 | R48: =R12 -> 2 | S48: =S12 -> 3.5
C49: 2026 | D49: =D48 -> 0.8 | E49: =E48 -> 0.1 | F49: =F48 -> 0.4 | G49: =G48 -> 0 | H49: =H48 -> 1.3 | M49: 2026 | N49: =N48 -> 2 | O49: =O48 -> 0.45 | P49: =P48 -> 1.05 | Q49: =Q48 -> 0 | R49: =R48 -> 2 | S49: =S48 -> 3.5
C50: =C49 -> 2026 | D50: =D13 -> 0.8 | E50: =E13 -> 0.1 | F50: =F13 -> 0.4 | G50: =G13 -> 0 | H50: =H13 -> 1.3 | M50: =M49 -> 2026 | N50: =N13 -> 2 | O50: =O13 -> 0.45 | P50: =P13 -> 1.05 | Q50: =Q13 -> 0 | R50: =R13 -> 2 | S50: =S13 -> 3.5
C51: 2026.25 | D51: =D50 -> 0.8 | E51: =E50 -> 0.1 | F51: =F50 -> 0.4 | G51: =G50 -> 0 | H51: =H50 -> 1.3 | M51: 2026.25 | N51: =N50 -> 2 | O51: =O50 -> 0.45 | P51: =P50 -> 1.05 | Q51: =Q50 -> 0 | R51: =R50 -> 2 | S51: =S50 -> 3.5
C52: =C51 -> 2026.25 | D52: =D14 -> 0.8 | E52: =E14 -> 0.1 | F52: =F14 -> 0.4 | G52: =G14 -> 0 | H52: =H14 -> 1.3 | M52: =M51 -> 2026.25 | N52: =N14 -> 2 | O52: =O14 -> 0.45 | P52: =P14 -> 1.05 | Q52: =Q14 -> 0 | R52: =R14 -> 2 | S52: =S14 -> 3.5
C53: 2026.5 | D53: =D52 -> 0.8 | E53: =E52 -> 0.1 | F53: =F52 -> 0.4 | G53: =G52 -> 0 | H53: =H52 -> 1.3 | M53: 2026.5 | N53: =N52 -> 2 | O53: =O52 -> 0.45 | P53: =P52 -> 1.05 | Q53: =Q52 -> 0 | R53: =R52 -> 2 | S53: =S52 -> 3.5
C54: =C53 -> 2026.5 | D54: =D15 -> 0.8 | E54: =E15 -> 0.1 | F54: =F15 -> 0.4 | G54: =G15 -> 0 | H54: =H15 -> 1.3 | M54: =M53 -> 2026.5 | N54: =N15 -> 2 | O54: =O15 -> 0.45 | P54: =P15 -> 1.05 | Q54: =Q15 -> 0 | R54: =R15 -> 2 | S54: =S15 -> 3.5
C55: 2026.75 | D55: =D54 -> 0.8 | E55: =E54 -> 0.1 | F55: =F54 -> 0.4 | G55: =G54 -> 0 | H55: =H54 -> 1.3 | M55: 2026.75 | N55: =N54 -> 2 | O55: =O54 -> 0.45 | P55: =P54 -> 1.05 | Q55: =Q54 -> 0 | R55: =R54 -> 2 | S55: =S54 -> 3.5
C56: =C55 -> 2026.75 | D56: =D16 -> 0.8 | E56: =E16 -> 0.1 | F56: =F16 -> 0.4 | G56: =G16 -> 0 | H56: =H16 -> 1.3 | M56: =M55 -> 2026.75 | N56: =N16 -> 2 | O56: =O16 -> 0.45 | P56: =P16 -> 1.05 | Q56: =Q16 -> 0 | R56: =R16 -> 2 | S56: =S16 -> 3.5
C57: 2027 | D57: =D56 -> 0.8 | E57: =E56 -> 0.1 | F57: =F56 -> 0.4 | G57: =G56 -> 0 | H57: =H56 -> 1.3 | M57: 2027 | N57: =N56 -> 2 | O57: =O56 -> 0.45 | P57: =P56 -> 1.05 | Q57: =Q56 -> 0 | R57: =R56 -> 2 | S57: =S56 -> 3.5
C58: =C57 -> 2027 | D58: =D17 -> 1.35 | E58: =E17 -> 0.1 | F58: =F17 -> 0.4 | G58: =G17 -> 0 | H58: =H17 -> 1.85 | M58: =M57 -> 2027 | N58: =N17 -> 2 | O58: =O17 -> 0.45 | P58: =P17 -> 1.05 | Q58: =Q17 -> 0 | R58: =R17 -> 2 | S58: =S17 -> 3.5
C59: 2027.25 | D59: =D58 -> 1.35 | E59: =E58 -> 0.1 | F59: =F58 -> 0.4 | G59: =G58 -> 0 | H59: =H58 -> 1.85 | M59: 2027.25 | N59: =N58 -> 2 | O59: =O58 -> 0.45 | P59: =P58 -> 1.05 | Q59: =Q58 -> 0 | R59: =R58 -> 2 | S59: =S58 -> 3.5
C60: =C59 -> 2027.25 | D60: =D18 -> 1.35 | E60: =E18 -> 0.1 | F60: =F18 -> 0.4 | G60: =G18 -> 5 | H60: =H18 -> 6.85 | M60: =M59 -> 2027.25 | N60: =N18 -> 2 | O60: =O18 -> 0.45 | P60: =P18 -> 1.05 | Q60: =Q18 -> 5 | R60: =R18 -> 7 | S60: =S18 -> 8.5
C61: 2027.5 | D61: =D60 -> 1.35 | E61: =E60 -> 0.1 | F61: =F60 -> 0.4 | G61: =G60 -> 5 | H61: =H60 -> 6.85 | M61: 2027.5 | N61: =N60 -> 2 | O61: =O60 -> 0.45 | P61: =P60 -> 1.05 | Q61: =Q60 -> 5 | R61: =R60 -> 7 | S61: =S60 -> 8.5
C62: =C61 -> 2027.5 | D62: =D19 -> 1.35 | E62: =E19 -> 0.1 | F62: =F19 -> 0.4 | G62: =G19 -> 5 | H62: =H19 -> 6.85 | M62: =M61 -> 2027.5 | N62: =N19 -> 2 | O62: =O19 -> 0.45 | P62: =P19 -> 1.05 | Q62: =Q19 -> 5 | R62: =R19 -> 7 | S62: =S19 -> 8.5
C63: 2027.75 | D63: =D62 -> 1.35 | E63: =E62 -> 0.1 | F63: =F62 -> 0.4 | G63: =G62 -> 5 | H63: =H62 -> 6.85 | M63: 2027.75 | N63: =N62 -> 2 | O63: =O62 -> 0.45 | P63: =P62 -> 1.05 | Q63: =Q62 -> 5 | R63: =R62 -> 7 | S63: =S62 -> 8.5
C64: =C63 -> 2027.75 | D64: =D20 -> 1.35 | E64: =E20 -> 0.1 | F64: =F20 -> 0.4 | G64: =G20 -> 5 | H64: =H20 -> 6.85 | M64: =M63 -> 2027.75 | N64: =N20 -> 2 | O64: =O20 -> 0.45 | P64: =P20 -> 1.05 | Q64: =Q20 -> 5 | R64: =R20 -> 7 | S64: =S20 -> 8.5
C65: 2028 | D65: =D64 -> 1.35 | E65: =E64 -> 0.1 | F65: =F64 -> 0.4 | G65: =G64 -> 5 | H65: =H64 -> 6.85 | M65: 2028 | N65: =N64 -> 2 | O65: =O64 -> 0.45 | P65: =P64 -> 1.05 | Q65: =Q64 -> 5 | R65: =R64 -> 7 | S65: =S64 -> 8.5
C66: =C65 -> 2028 | D66: =D21 -> 1.55 | E66: =E21 -> 0.1 | F66: =F21 -> 2.2 | G66: =G21 -> 5 | H66: =H21 -> 8.85 | M66: =M65 -> 2028 | N66: =N21 -> 2 | O66: =O21 -> 0.45 | P66: =P21 -> 2.85 | Q66: =Q21 -> 5 | R66: =R21 -> 7 | S66: =S21 -> 10.3
C67: 2028.25 | D67: =D66 -> 1.55 | E67: =E66 -> 0.1 | F67: =F66 -> 2.2 | G67: =G66 -> 5 | H67: =H66 -> 8.85 | M67: 2028.25 | N67: =N66 -> 2 | O67: =O66 -> 0.45 | P67: =P66 -> 2.85 | Q67: =Q66 -> 5 | R67: =R66 -> 7 | S67: =S66 -> 10.3
C68: =C67 -> 2028.25 | D68: =D22 -> 1.35 | E68: =E22 -> 0 | F68: =F22 -> 2.2 | G68: =G22 -> 5 | H68: =H22 -> 8.55 | M68: =M67 -> 2028.25 | N68: =N22 -> 2 | O68: =O22 -> 0 | P68: =P22 -> 2.85 | Q68: =Q22 -> 5 | R68: =R22 -> 7 | S68: =S22 -> 9.85
C69: 2028.5 | D69: =D68 -> 1.35 | E69: =E68 -> 0 | F69: =F68 -> 2.2 | G69: =G68 -> 5 | H69: =H68 -> 8.55 | M69: 2028.5 | N69: =N68 -> 2 | O69: =O68 -> 0 | P69: =P68 -> 2.85 | Q69: =Q68 -> 5 | R69: =R68 -> 7 | S69: =S68 -> 9.85
C70: =C69 -> 2028.5 | D70: =D23 -> 1.35 | E70: =E23 -> 0 | F70: =F23 -> 2.2 | G70: =G23 -> 5 | H70: =H23 -> 8.55 | M70: =M69 -> 2028.5 | N70: =N23 -> 2 | O70: =O23 -> 0 | P70: =P23 -> 2.85 | Q70: =Q23 -> 5 | R70: =R23 -> 7 | S70: =S23 -> 9.85
C71: 2028.75 | D71: =D70 -> 1.35 | E71: =E70 -> 0 | F71: =F70 -> 2.2 | G71: =G70 -> 5 | H71: =H70 -> 8.55 | M71: 2028.75 | N71: =N70 -> 2 | O71: =O70 -> 0 | P71: =P70 -> 2.85 | Q71: =Q70 -> 5 | R71: =R70 -> 7 | S71: =S70 -> 9.85
C72: =C71 -> 2028.75 | D72: =D24 -> 1.35 | E72: =E24 -> 0 | F72: =F24 -> 2.2 | G72: =G24 -> 5 | H72: =H24 -> 8.55 | M72: =M71 -> 2028.75 | N72: =N24 -> 2 | O72: =O24 -> 0 | P72: =P24 -> 2.85 | Q72: =Q24 -> 5 | R72: =R24 -> 7 | S72: =S24 -> 9.85
C73: 2029 | D73: =D72 -> 1.35 | E73: =E72 -> 0 | F73: =F72 -> 2.2 | G73: =G72 -> 5 | H73: =H72 -> 8.55 | M73: 2029 | N73: =N72 -> 2 | O73: =O72 -> 0 | P73: =P72 -> 2.85 | Q73: =Q72 -> 5 | R73: =R72 -> 7 | S73: =S72 -> 9.85
C74: =C73 -> 2029 | D74: =D25 -> 1.35 | E74: =E25 -> 0 | F74: =F25 -> 2.2 | G74: =G25 -> 5 | H74: =H25 -> 8.55 | M74: =M73 -> 2029 | N74: =N25 -> 2 | O74: =O25 -> 0 | P74: =P25 -> 2.85 | Q74: =Q25 -> 5 | R74: =R25 -> 7 | S74: =S25 -> 9.85
C75: 2029.25 | D75: =D74 -> 1.35 | E75: =E74 -> 0 | F75: =F74 -> 2.2 | G75: =G74 -> 5 | H75: =H74 -> 8.55 | M75: 2029.25 | N75: =N74 -> 2 | O75: =O74 -> 0 | P75: =P74 -> 2.85 | Q75: =Q74 -> 5 | R75: =R74 -> 7 | S75: =S74 -> 9.85
C76: =C75 -> 2029.25 | D76: =D26 -> 1.35 | E76: =E26 -> 0 | F76: =F26 -> 2.2 | G76: =G26 -> 5 | H76: =H26 -> 8.55 | M76: =M75 -> 2029.25 | N76: =N26 -> 2 | O76: =O26 -> 0 | P76: =P26 -> 2.85 | Q76: =Q26 -> 5 | R76: =R26 -> 7 | S76: =S26 -> 9.85
C77: 2029.5 | D77: =D76 -> 1.35 | E77: =E76 -> 0 | F77: =F76 -> 2.2 | G77: =G76 -> 5 | H77: =H76 -> 8.55 | M77: 2029.5 | N77: =N76 -> 2 | O77: =O76 -> 0 | P77: =P76 -> 2.85 | Q77: =Q76 -> 5 | R77: =R76 -> 7 | S77: =S76 -> 9.85
C78: =C77 -> 2029.5 | D78: =D27 -> 1.35 | E78: =E27 -> 0 | F78: =F27 -> 2.2 | G78: =G27 -> 5 | H78: =H27 -> 8.55 | M78: =M77 -> 2029.5 | N78: =N27 -> 2 | O78: =O27 -> 0 | P78: =P27 -> 2.85 | Q78: =Q27 -> 5 | R78: =R27 -> 7 | S78: =S27 -> 9.85
C79: 2029.75 | D79: =D78 -> 1.35 | E79: =E78 -> 0 | F79: =F78 -> 2.2 | G79: =G78 -> 5 | H79: =H78 -> 8.55 | M79: 2029.75 | N79: =N78 -> 2 | O79: =O78 -> 0 | P79: =P78 -> 2.85 | Q79: =Q78 -> 5 | R79: =R78 -> 7 | S79: =S78 -> 9.85
C80: =C79 -> 2029.75 | D80: =D28 -> 1.35 | E80: =E28 -> 0 | F80: =F28 -> 2.2 | G80: =G28 -> 5 | H80: =H28 -> 8.55 | M80: =M79 -> 2029.75 | N80: =N28 -> 2 | O80: =O28 -> 0 | P80: =P28 -> 2.85 | Q80: =Q28 -> 5 | R80: =R28 -> 7 | S80: =S28 -> 9.85
C81: 2030 | D81: =D80 -> 1.35 | E81: =E80 -> 0 | F81: =F80 -> 2.2 | G81: =G80 -> 5 | H81: =H80 -> 8.55 | M81: 2030 | N81: =N80 -> 2 | O81: =O80 -> 0 | P81: =P80 -> 2.85 | Q81: =Q80 -> 5 | R81: =R80 -> 7 | S81: =S80 -> 9.85

Sheet Change Log
A4: 45862 | B4: Mt Washington facility - anticipate 24 months to increase by 1.8
B5: Bloomberg facility - anticipate migrating to current Bayview container - and retiring equipment
B6: Added Schmidt infrastructure in current Bayview container
B7: Added Mt Washington - research storage
B8: Note: we need to add some new categories to cover the new equipment - comments in cells

Sheet Power Blocks
C2: The equiment purchased in the later installments can be modified in the yellow cells | P2: Estimated electricity rates for 1kW
C3: The lifecycle of the installed hardware is shown in cells P4..AK20 | P3: location | Q3: $/kW.h | R3: $/kW.yr | S3: inflation
C4: The power of each block is propagated from Col J | P4: Bayview | Q4: 0.1 | R4: =Q4*24*365 -> 876 | S4: 0.1
C5: Add the estimated power for exisiting equipment in the purple cells | P5: MTW | Q5: 0.0755 | R5: =Q5*24*365 -> 661.38
C6: The spreadsheet calculates the total power (needed and available) for every semester | P6: Homewood | Q6: =Q4 -> 0.1 | R6: =Q6*24*365 -> 876
C7: It also shows the total estimated cost (in 2024 $$) | P7: Cooling overhead | S7: 0.2
S10: 2024 | T10: 2024.25 | U10: 2024.5 | V10: 2024.75 | W10: 2025 | X10: 2025.25 | Y10: =X10+0.25 -> 2025.5 | Z10: =Y10+0.25 -> 2025.75 | AA10: =Z10+0.25 -> 2026 | AB10: =AA10+0.25 -> 2026.25 | AC10: =AB10+0.25 -> 2026.5 | AD10: =AC10+0.25 -> 2026.75 | AE10: =AD10+0.25 -> 2027 | AF10: =AE10+0.25 -> 2027.25 | ... AL10: =AK10+0.25 -> 2028.75
P11: =P4 -> Bayview | R11: Hourly | S11: =Q4 -> 0.1 | T11: =S11 -> 0.1 | U11: =T11 -> 0.1 | V11: =U11 -> 0.1 | W11: =V11 -> 0.1 | X11: =W11 -> 0.1 | Y11: =X11*(1+$S$4) -> 0.11 | Z11: =Y11 -> 0.11 | AA11: =Z11 -> 0.11 | AB11: =AA11 -> 0.11 | AC11: =AB11*(1+$S$4) -> 0.121 | AD11: =AC11 -> 0.121 | AE11: =AD11 -> 0.121 | AF11: =AE11 -> 0.121 | AG11: =AF11*(1+$S$4) -> 0.1331 | AH11: =AG11 -> 0.1331 | AI11: =AH11 -> 0.1331 | AJ11: =AI11 -> 0.1331 | AK11: =AJ11*(1+$S$4) -> 0.14641 | AL11: =AK11 -> 0.14641 | AM11: *using current rates and 10% inflation every July
R12: Annual | S12: =S11*24*365 -> 876 | T12: =T11*24*365 -> 876 | U12: =U11*24*365 -> 876 | V12: =V11*24*365 -> 876 | W12: =W11*24*365 -> 876 | X12: =X11*24*365 -> 876 | Y12: =Y11*24*365 -> 963.6 | Z12: =Z11*24*365 -> 963.6 | ... AL12: =AL11*24*365 -> 1282.5516
P13: =P5 -> MTW | R13: Hourly | S13: =Q5 -> 0.0755 | T13: =S13 -> 0.0755 | U13: 0.091 | V13: 0.091 | W13: 0.091 | X13: 0.091 | Y13: 0.091 | Z13: 0.091 | AA13: 0.091 | AB13: 0.091 | AC13: 0.091 | AD13: 0.091 | AE13: 0.091 | AF13: 0.091 | AG13: =AF13*1.1 -> 0.1001 | AH13: =AG13 -> 0.1001 | AI13: =AH13 -> 0.1001 | AJ13: =AI13 -> 0.1001 | AK13: =AJ13*1.1 -> 0.11011 | AL13: =AK13 -> 0.11011 | AM13: * source: Rob Anderson email 11/25/24
R14: Annual | S14: =S13*24*365 -> 661.38 | T14: =T13*24*365 -> 661.38 | U14: =U13*24*365 -> 797.16 | V14: =V13*24*365 -> 797.16 | W14: =W13*24*365 -> 797.16 | X14: =X13*24*365 -> 797.16 | Y14: =Y13*24*365 -> 797.16 | Z14: =Z13*24*365 -> 797.16 | ... AL14: =AL13*24*365 -> 964.5636
P15: =P6 -> Homewood | R15: Hourly | S15: =Q6 -> 0.1 | T15: =S15 -> 0.1 | U15: =T15 -> 0.1 | V15: =U15 -> 0.1 | W15: =V15*(1+$S$4) -> 0.11 | X15: =W15 -> 0.11 | Y15: =X15 -> 0.11 | Z15: =Y15 -> 0.11 | AA15: =Z15*(1+$S$4) -> 0.121 | AB15: =AA15 -> 0.121 | AC15: 0.13165 | AD15: 0.13165 | AE15: =AD15 -> 0.13165 | AF15: =AE15 -> 0.13165 | AG15: 0.13377 | AH15: 0.13377 | AI15: 0.1388 | AJ15: =AI15 -> 0.1388 | AK15: =AJ15 -> 0.1388 | AL15: =AK15 -> 0.1388 | AM15: *source TJ Rosson email 11/21/24
R16: Annual | S16: =S15*24*365 -> 876 | T16: =T15*24*365 -> 876 | U16: =U15*24*365 -> 876 | V16: =V15*24*365 -> 876 | W16: =W15*24*365 -> 963.6 | X16: =X15*24*365 -> 963.6 | Y16: =Y15*24*365 -> 963.6 | Z16: =Z15*24*365 -> 963.6 | ... AL16: =AL15*24*365 -> 1215.888
C18: system | F18: per server | I18: block
C19: name | D19: type | E19: build | F19: price | G19: [kW] | H19: GPU.. | I19: qty | J19: power[MW] | K19: capex | L19: opex [$K] | M19: GPU/CPU | N19: unit
C20: A100-8 | D20: GPU | E20: SMC | F20: 112000 | G20: 10 | H20: 8 | I20: 10 | J20: =I20*G20/1000 -> 0.1 | K20: =I20*F20 -> 1120000 | L20: =J20*$R$4 -> 87.6 | M20: =H20*I20 -> 80 | N20: GPU
C21: H100-4 | D21: GPU | E21: Lenovo | F21: 107000 | G21: 6.25 | H21: 4 | I21: 16 | J21: =I21*G21/1000 -> 0.1 | K21: =I21*F21 -> 1712000 | L21: =J21*$R$4 -> 87.6 | M21: =H21*I21 -> 64 | N21: GPU
C22: H100-8 | D22: GPU | E22: SMC | F22: 250000 | G22: 12.5 | H22: 8 | I22: 8 | J22: =I22*G22/1000 -> 0.1 | K22: =I22*F22 -> 2000000 | L22: =J22*$R$4 -> 87.6 | M22: =H22*I22 -> 64 | N22: GPU
C23: H200-8 | D23: GPU | E23: Dell | F23: 275000 | G23: 10 | H23: 8 | I23: 10 | J23: =I23*G23/1000 -> 0.1 | K23: =I23*F23 -> 2750000 | L23: =J23*$R$4 -> 87.6 | M23: =H23*I23 -> 80 | N23: GPU
C24: L40-8 | D24: GPU | E24: Lenovo | F24: 61300 | G24: 5 | H24: 8 | I24: 20 | J24: =I24*G24/1000 -> 0.1 | K24: =I24*F24 -> 1226000 | L24: =J24*$R$4 -> 87.6 | M24: =H24*I24 -> 160 | N24: GPU
C25: NVL72 | D25: GPU | E25: Nvidia | F25: 7000000 | G25: 135 | H25: 72 | I25: 1 | J25: =I25*G25/1000 -> 0.135 | K25: =I25*F25 -> 7000000 | L25: =J25*$R$4 -> 118.26 | M25: =H25*I25 -> 72 | N25: GPU
C26: HPC1 | D26: CPU | E26: Dell | F26: 10000 | G26: 1 | H26: 128 | I26: 100 | J26: =I26*G26/1000 -> 0.1 | K26: =I26*F26 -> 1000000 | L26: =J26*$R$4 -> 87.6 | M26: =H26*I26 -> 12800 | N26: core
C27: HPC2 | D27: CPU | E27: Dell | F27: 15000 | G27: 1.25 | H27: 256 | I27: 80 | J27: =I27*G27/1000 -> 0.1 | K27: =I27*F27 -> 1200000 | L27: =J27*$R$4 -> 87.6 | M27: =H27*I27 -> 20480 | N27: core
C28: SSD | D28: Sdisk | E28: SMC | F28: 42000 | G28: 0.8 | H28: 0.3 | I28: 125 | J28: =I28*G28/1000 -> 0.1 | K28: =I28*F28 -> 5250000 | L28: =J28*$R$4 -> 87.6 | M28: =H28*I28 -> 37.5 | N28: PB
C29: HDD | D29: Hdisk | E29: SMC | F29: 28571 | G29: =100/140 -> 0.71428571 | H29: 0.53 | I29: 140 | J29: =I29*G29/1000 -> 0.1 | K29: =I29*F29 -> 3999940 | L29: =J29*$R$4 -> 87.6 | M29: =H29*I29 -> 74.2 | N29: PB
C30: V100-4 | D30: GPU | E30: Dell | F30: 20000 | G30: 5 | H30: 4 | I30: 20 | J30: =I30*G30/1000 -> 0.1 | K30: =I30*F30 -> 400000 | L30: =J30*$R$4 -> 87.6 | M30: =H30*I30 -> 80 | N30: GPU
C31: --
